Workbook

Sheet Раздел 0
B2: ФЕДЕРАЛЬНОЕ СТАТИСТИЧЕСКОЕ НАБЛЮДЕНИЕ
B4: КОНФИДЕНЦИАЛЬНОСТЬ ГАРАНТИРУЕТСЯ ПОЛУЧАТЕЛЕМ ИНФОРМАЦИИ
B6: Нарушение порядка предоставления первичных статистических данных или несвоевременное предоставление этих данных, либо предоставление недостоверных первичных статистических данных влечет ответственность, установленную Кодексом Российской Федерации об административных правонарушениях
B8: Обязанность предоставления административных данных предусмотрена статьей 8 Федерального закона от 29 ноября 2007 г. № 282-ФЗ «Об официальном статистическом учете и системе государственной статистики в Российской Федерации»
B10: СВЕДЕНИЯ ПО ПОДГОТОВКЕ СПОРТИВНОГО РЕЗЕРВА
B11: по состоянию на 31 декабря 20__ г.
B13: Предоставляют: | K13: Сроки предоставления | Q13: Форма № 5-ФК
B14: юридические лица – организации государственной, муниципальной и иной формы собственности (кроме субъектов малого и среднего предпринимательства), реализующие дополнительные образовательные программы спортивной подготовки или обеспечивающие подготовку спортивного резерва (полный перечень категорий респондентов приведен в указаниях по заполнению формы федерального статистического наблюдения): – исполнительно-распорядительным органам местного самоуправления муниципального образования, уполномоченному органу публичной власти федеральной территории «Сириус» (схема предоставления приведена в указаниях по заполнению формы); исполнительно-распорядительные органы местного самоуправления муниципального образования: – органам исполнительной власти субъектов Российской Федерации в области физической культуры и спорта; органы исполнительной власти субъектов Российской Федерации в области физической культуры и спорта, уполномоченный орган публичной власти федеральной территории «Сириус»: – Министерству спорта Российской Федерации. | K14: до 15 января после отчетного периода до 19 января после отчетного периода до 25 января после отчетного периода | Q14: Приказ Росстата: Об утверждении формы от _________ № ___ О внесении изменений (при наличии) от __________ № ___ от __________ № ___
Q16: Годовая
A20: 1 | B20: Наименование отчитывающейся организации | L20: Краткое наименование отчитывающейся организации
A21: 2 | B21: Почтовый адрес
B22: Муниципальный район | I22: Городской округ | M22: Муниципальный округ | S22: Сельское поселение
A23: 3
B24: Код формы по ОКУД | E24: Код
E25: отчитывающейся организации по ОКПО (для обособленного подразделения и головного подразделения юридического лица – идентификационный номер) | I25: Регистрационный номер лицензии на осуществление образовательной деятельности | M25: Код субъекта Российской Федерации | P25: Код ОКТМО | S25: Находится на территории сельского поселения Код: нет - 0, да - 1
A26: 4 | B26: 1 | E26: 2 | I26: 3 | M26: 4 | P26: 5 | S26: 6
A27: 5 | B27: 0609403

Sheet Раздел 1
B1: Раздел I. Число организаций, единица
B2: Ведомственная принадлежность | C2: № строки | D2: Число организаций и обособленных структурных подразделений – всего | E2: в том числе по наименованию организации:
E3: СШ | F3: СШОР | G3: УОР | H3: ЦСП | I3: Другие организации
B4: 1 | C4: 2 | D4: 3 | E4: 4 | F4: 5 | G4: 6 | H4: 7 | I4: 8
B5: Организации в ведении органов управления в сфере физической культуры и спорта | C5: 01 | D5: =E5+F5+G5+H5+I5 -> 1 | H5: 1
B6: Обособленные структурные подразделения в сфере физической культуры и спорта, реализующие дополнительные общеобразовательные программы в области физической культуры и спорта | C6: 02 | D6: =E6+F6+G6+H6+I6 -> 0
B7: Организации в ведении органов управления в сфере образования | C7: 03 | D7: =E7+F7+G7+H7+I7 -> 0
B8: Обособленные структурные подразделения в сфере образования, реализующие дополнительные общеобразовательные программы в области физической культуры и спорта | C8: 04 | D8: =E8+F8+G8+H8+I8 -> 0
B9: Организации другой ведомственной принадлежности | C9: 05 | D9: =E9+F9+G9+H9+I9 -> 0
B10: Обособленные структурные подразделения другой ведомственной принадлежности, реализующие дополнительные общеобразовательные программы в области физической культуры и спорта | C10: 06 | D10: =E10+F10+G10+H10+I10 -> 0
B11: Частные организации (из стр. 05) | C11: 07 | D11: =E11+F11+G11+H11+I11 -> 0
B12: Итого организаций | C12: 08 | D12: =D5+D7+D9 -> 1 | E12: =E5+E7+E9 -> 0 | F12: =F5+F7+F9 -> 0 | G12: =G5+G7+G9 -> 0 | H12: =H5+H7+H9 -> 1 | I12: =I5+I7+I9 -> 0
B13: Итого обособленных структурных подразделений, реализующих дополнительные общеобразовательные программы в области физической культуры и спорта | C13: 09 | D13: =D6+D8+D10 -> 0 | E13: =E6+E8+E10 -> 0 | F13: =F6+F8+F10 -> 0 | G13: =G6+G8+G10 -> 0 | H13: =H6+H8+H10 -> 0 | I13: =I6+I8+I10 -> 0
B15: ОГРН/для обособленных структурных подразделений ОГРН головной организации | C15: 10 | E15: =IF($D$12=1,$D$15,"") -> 0
B17: Виды правовых образований | C17: 11 | D17: Публичные правовые образования | H17: Иные правовые образования (в том числе частные)
D18: Российская Федерация | E18: Субъект Российской Федерации | F18: Муниципальное образование
A19: 11
B21: Наличие структурного подразделения интерната | C21: 12 | E21: Код: нет - 0, да - 1

Sheet Раздел 2
G5: Раздел II. Численность обучающихся
G6: Виды спорта | H6: № строки | I6: Число отделений по видам спорта, единица | J6: Базовый вид спорта, единица | K6: Численность обучающихся на 31 декабря отчетного периода, человек
K7: Итого обучающихся | L7: Обучающиеся по дополнительным общеобразовательным программам в области физической культуры и спорта
L8: Всего обучающихся по дополнительным образовательным программам спортивной подготовки | M8: по дополнительным образовательным программам спортивной подготовки | Q8: по возрастам (из гр. 6) | S8: по договорам платных образовательных услуг (из гр. 6) | X8: по дополнительным общеразвивающим программам (спортивно-оздоровительный этап) | Y8: по возрастам (из гр. 18) | AB8: по договорам платных образовательных услуг (из гр. 18) | AE8: из гр. 5:
A9: Код региона | B9: ОГРН | C9: Ведоственная принадлежность | D9: Вид организации | E9: ОСП | F9: Вид правового образования | M9: начальной подготовки | N9: учебно-тренировочный | O9: совершен-ствования спортивного мастерства | P9: высшего спортивного мастерства | Q9: 5-17 лет | R9: старше 18 лет | S9: начальной подготовки | T9: учебно - тренировочный | U9: совершен-ствования спортивного мастерства | V9: высшего спортивного мастерства | W9: в возрасте 5-17 лет (из гр. 11) | Y9: до 4 лет | Z9: 5-17 лет | AA9: старше 18 лет | AB9: до 4 лет | AC9: 5-17 лет | AD9: старше 18 лет | AE9: мальчиков, юношей, юниоров, мужчин | AF9: девочек, девушек, юниорок, женщин
A10: ='Раздел 0'!M27 -> 0 | B10: ='Раздел 1'!D15 -> 0 | C10: {=_xlfn.IFS(SUM('Раздел 1'!$D$5:$D$6)>0,"ФКиС",SUM('Раздел 1'!$D$7:$D$8)>0,"Образование",SUM('Раздел 1'!$D$9:$D$10)>0,"Другая")} -> ФКиС | D10: {=_xlfn.IFS(SUM('Раздел 1'!$E$12)>0,"СШ",SUM('Раздел 1'!$F$12)>0,"СШОР",SUM('Раздел 1'!$G$12)>0,"УОР",SUM('Раздел 1'!$H$12)>0,"ЦСП",SUM('Раздел 1'!$I$12)>0,"ДРУГИЕ",SUM('Раздел 1'!$E$13)>0,"ОСП СШ",SUM('Раздел 1'!$F$13)>0,"ОСП СШОР",SUM('Раздел 1'!$I$13)>0,"ОСП ДРУГИЕ")} -> ЦСП | E10: =IF(SUM('Раздел 1'!$D$12)>0,SUM('Раздел 1'!$D$13),"") -> 0 | F10: {=_xlfn.IFS(SUM('Раздел 1'!$D$19)>0,"РФ",SUM('Раздел 1'!$E$19)>0,"СУБЪЕКТ",SUM('Раздел 1'!$F$19:$G$19)>0,"МУНИЦИПАЛ",SUM('Раздел 1'!$H$19:$I$19)>0,"ИНЫЕ")} -> #N/A | G10: 1 | H10: 2 | I10: 3 | J10: 4 | K10: 5 | L10: 6 | M10: 7 | N10: 8 | O10: 9 | P10: 10 | Q10: 11 | R10: 12 | S10: 13 | T10: 14 | U10: 15 | V10: 16 | W10: 17 | X10: 18 | Y10: 19 | Z10: 20 | AA10: 21 | AB10: 22 | AC10: 23 | AD10: 24 | AE10: 25 | AF10: 26 | AG10: 27
G11: Авиамодельный спорт | H11: 01 | I11: 1 | K11: =L11+X11 -> 0 | L11: =SUM(M11:P11) -> 0 | AG11: =SUM(I11:AF11) -> 1
G12: Авиационные гонки | H12: 02 | K12: =L12+X12 -> 0 | L12: =SUM(M12:P12) -> 0 | AG12: =SUM(I12:AF12) -> 0
G13: Автомобильный спорт | H13: 03 | K13: =L13+X13 -> 0 | L13: =SUM(M13:P13) -> 0 | AG13: =SUM(I13:AF13) -> 0
G14: Автомодельный спорт | H14: 04 | K14: =L14+X14 -> 0 | L14: =SUM(M14:P14) -> 0 | AG14: =SUM(I14:AF14) -> 0
G15: Айкидо | H15: 05 | K15: =L15+X15 -> 0 | L15: =SUM(M15:P15) -> 0 | AG15: =SUM(I15:AF15) -> 0
G16: Акробатический рок-н-ролл | H16: 06 | K16: =L16+X16 -> 0 | L16: =SUM(M16:P16) -> 0 | AG16: =SUM(I16:AF16) -> 0
G17: Альпинизм - всего | H17: 07 | I17: =IF(SUM(I18:I19)>=1,1,0) -> 0 | K17: =L17+X17 -> 0 | L17: =SUM(M17:P17) -> 0 | M17: =SUM(M18:M19) -> 0 | N17: =SUM(N18:N19) -> 0 | O17: =SUM(O18:O19) -> 0 | P17: =SUM(P18:P19) -> 0 | Q17: =SUM(Q18:Q19) -> 0 | R17: =SUM(R18:R19) -> 0 | S17: =SUM(S18:S19) -> 0 | T17: =SUM(T18:T19) -> 0 | ... AF17: =SUM(AF18:AF19) -> 0 | AG17: =SUM(I17:AF17) -> 0
G18: в том числе: Ски-альпинизм | H18: 08 | K18: =L18+X18 -> 0 | L18: =SUM(M18:P18) -> 0 | AG18: =SUM(I18:AF18) -> 0
G19: Иные дисциплины вида спорта "альпинизм" | H19: 09 | K19: =L19+X19 -> 0 | L19: =SUM(M19:P19) -> 0 | AG19: =SUM(I19:AF19) -> 0
G20: Американский футбол | H20: 10 | K20: =L20+X20 -> 0 | L20: =SUM(M20:P20) -> 0 | AG20: =SUM(I20:AF20) -> 0
G21: Армейская высокоточная стрельба | H21: 11 | K21: =L21+X21 -> 0 | L21: =SUM(M21:P21) -> 0 | AG21: =SUM(I21:AF21) -> 0
G22: Армейский рукопашный бой | H22: 12 | K22: =L22+X22 -> 0 | L22: =SUM(M22:P22) -> 0 | AG22: =SUM(I22:AF22) -> 0
G23: Армейское тактико-стрелковое многоборье | H23: 13 | K23: =L23+X23 -> 0 | L23: =SUM(M23:P23) -> 0 | AG23: =SUM(I23:AF23) -> 0
G24: Армрестлинг | H24: 14 | K24: =L24+X24 -> 0 | L24: =SUM(M24:P24) -> 0 | AG24: =SUM(I24:AF24) -> 0
G25: Бадминтон | H25: 15 | K25: =L25+X25 -> 0 | L25: =SUM(M25:P25) -> 0 | AG25: =SUM(I25:AF25) -> 0
G26: Баскетбол - всего | H26: 16 | I26: =IF(SUM(I27:I30)>=1,1,0) -> 0 | K26: =L26+X26 -> 0 | L26: =SUM(M26:P26) -> 0 | M26: =SUM(M27:M30) -> 0 | N26: =SUM(N27:N30) -> 0 | O26: =SUM(O27:O30) -> 0 | P26: =SUM(P27:P30) -> 0 | Q26: =SUM(Q27:Q30) -> 0 | R26: =SUM(R27:R30) -> 0 | S26: =SUM(S27:S30) -> 0 | T26: =SUM(T27:T30) -> 0 | ... AF26: =SUM(AF27:AF30) -> 0 | AG26: =SUM(I26:AF26) -> 0
G27: в том числе: Баскетбол | H27: 17 | K27: =L27+X27 -> 0 | L27: =SUM(M27:P27) -> 0 | AG27: =SUM(I27:AF27) -> 0
G28: Баскетбол 3х3 | H28: 18 | K28: =L28+X28 -> 0 | L28: =SUM(M28:P28) -> 0 | AG28: =SUM(I28:AF28) -> 0
G29: Интерактивный баскетбол | H29: 19 | K29: =L29+X29 -> 0 | L29: =SUM(M29:P29) -> 0 | AG29: =SUM(I29:AF29) -> 0
G30: Иные дисциплины вида спорта "баскетбол" | H30: 20 | K30: =L30+X30 -> 0 | L30: =SUM(M30:P30) -> 0 | AG30: =SUM(I30:AF30) -> 0
G31: Бейсбол | H31: 21 | K31: =L31+X31 -> 0 | L31: =SUM(M31:P31) -> 0 | AG31: =SUM(I31:AF31) -> 0
G32: Биатлон | H32: 22 | K32: =L32+X32 -> 0 | L32: =SUM(M32:P32) -> 0 | AG32: =SUM(I32:AF32) -> 0
G33: Бильярдный спорт | H33: 23 | K33: =L33+X33 -> 0 | L33: =SUM(M33:P33) -> 0 | AG33: =SUM(I33:AF33) -> 0
G34: Бобслей - всего | H34: 24 | I34: =IF(SUM(I35:I38)>=1,1,0) -> 0 | K34: =L34+X34 -> 0 | L34: =SUM(M34:P34) -> 0 | M34: =SUM(M35:M38) -> 0 | N34: =SUM(N35:N38) -> 0 | O34: =SUM(O35:O38) -> 0 | P34: =SUM(P35:P38) -> 0 | Q34: =SUM(Q35:Q38) -> 0 | R34: =SUM(R35:R38) -> 0 | S34: =SUM(S35:S38) -> 0 | T34: =SUM(T35:T38) -> 0 | ... AF34: =SUM(AF35:AF38) -> 0 | AG34: =SUM(I34:AF34) -> 0
G35: в том числе: Скелетон | H35: 25 | K35: =L35+X35 -> 0 | L35: =SUM(M35:P35) -> 0 | AG35: =SUM(I35:AF35) -> 0
G36: Экипаж | H36: 26 | K36: =L36+X36 -> 0 | L36: =SUM(M36:P36) -> 0 | AG36: =SUM(I36:AF36) -> 0
G37: Монобоб | H37: 27 | K37: =L37+X37 -> 0 | L37: =SUM(M37:P37) -> 0 | AG37: =SUM(I37:AF37) -> 0
G38: Иные дисциплины вида спорта "бобслей" | H38: 28 | K38: =L38+X38 -> 0 | L38: =SUM(M38:P38) -> 0 | AG38: =SUM(I38:AF38) -> 0
G39: Бодибилдинг | H39: 29 | K39: =L39+X39 -> 0 | L39: =SUM(M39:P39) -> 0 | AG39: =SUM(I39:AF39) -> 0
G40: Бокс | H40: 30 | K40: =L40+X40 -> 0 | L40: =SUM(M40:P40) -> 0 | AG40: =SUM(I40:AF40) -> 0
G41: Борьба на поясах | H41: 31 | K41: =L41+X41 -> 0 | L41: =SUM(M41:P41) -> 0 | AG41: =SUM(I41:AF41) -> 0
G42: Боулинг | H42: 32 | K42: =L42+X42 -> 0 | L42: =SUM(M42:P42) -> 0 | AG42: =SUM(I42:AF42) -> 0
G43: Боулспорт | H43: 33 | K43: =L43+X43 -> 0 | L43: =SUM(M43:P43) -> 0 | AG43: =SUM(I43:AF43) -> 0
G44: Брейкинг | H44: 34 | K44: =L44+X44 -> 0 | L44: =SUM(M44:P44) -> 0 | AG44: =SUM(I44:AF44) -> 0
G45: Велосипедный спорт - всего | H45: 35 | I45: =IF(SUM(I46:I51)>=1,1,0) -> 0 | K45: =L45+X45 -> 0 | L45: =SUM(M45:P45) -> 0 | M45: =SUM(M46:M51) -> 0 | N45: =SUM(N46:N51) -> 0 | O45: =SUM(O46:O51) -> 0 | P45: =SUM(P46:P51) -> 0 | Q45: =SUM(Q46:Q51) -> 0 | R45: =SUM(R46:R51) -> 0 | S45: =SUM(S46:S51) -> 0 | T45: =SUM(T46:T51) -> 0 | ... AF45: =SUM(AF46:AF51) -> 0 | AG45: =SUM(I45:AF45) -> 0
G46: в том числе: BMX (гонка, эстафета) | H46: 36 | K46: =L46+X46 -> 0 | L46: =SUM(M46:P46) -> 0 | AG46: =SUM(I46:AF46) -> 0
G47: BMX - фристайл | H47: 37 | K47: =L47+X47 -> 0 | L47: =SUM(M47:P47) -> 0 | AG47: =SUM(I47:AF47) -> 0
G48: Маунтинбайк | H48: 38 | K48: =L48+X48 -> 0 | L48: =SUM(M48:P48) -> 0 | AG48: =SUM(I48:AF48) -> 0
G49: Трек | H49: 39 | K49: =L49+X49 -> 0 | L49: =SUM(M49:P49) -> 0 | AG49: =SUM(I49:AF49) -> 0
G50: Шоссе | H50: 40 | K50: =L50+X50 -> 0 | L50: =SUM(M50:P50) -> 0 | AG50: =SUM(I50:AF50) -> 0
G51: Технический симулятор | H51: 41 | K51: =L51+X51 -> 0 | L51: =SUM(M51:P51) -> 0 | AG51: =SUM(I51:AF51) -> 0
G52: Вертолетный спорт | H52: 42 | K52: =L52+X52 -> 0 | L52: =SUM(M52:P52) -> 0 | AG52: =SUM(I52:AF52) -> 0
G53: Водное поло - всего | H53: 43 | I53: =IF(SUM(I54:I55)>=1,1,0) -> 0 | K53: =L53+X53 -> 0 | L53: =SUM(M53:P53) -> 0 | M53: =SUM(M54:M55) -> 0 | N53: =SUM(N54:N55) -> 0 | O53: =SUM(O54:O55) -> 0 | P53: =SUM(P54:P55) -> 0 | Q53: =SUM(Q54:Q55) -> 0 | R53: =SUM(R54:R55) -> 0 | S53: =SUM(S54:S55) -> 0 | T53: =SUM(T54:T55) -> 0 | ... AF53: =SUM(AF54:AF55) -> 0 | AG53: =SUM(I53:AF53) -> 0
G54: в том числе: Водное поло | H54: 44 | K54: =L54+X54 -> 0 | L54: =SUM(M54:P54) -> 0 | AG54: =SUM(I54:AF54) -> 0
G55: Иные дисциплины вида спорта "водное поло" | H55: 45 | K55: =L55+X55 -> 0 | L55: =SUM(M55:P55) -> 0 | AG55: =SUM(I55:AF55) -> 0
G56: Воднолыжный спорт | H56: 46 | K56: =L56+X56 -> 0 | L56: =SUM(M56:P56) -> 0 | AG56: =SUM(I56:AF56) -> 0
G57: Водно-моторный спорт | H57: 47 | K57: =L57+X57 -> 0 | L57: =SUM(M57:P57) -> 0 | AG57: =SUM(I57:AF57) -> 0
G58: Водно-спасательное многоборье | H58: 48 | K58: =L58+X58 -> 0 | L58: =SUM(M58:P58) -> 0 | AG58: =SUM(I58:AF58) -> 0
G59: Военно-прикладной спорт | H59: 49 | K59: =L59+X59 -> 0 | L59: =SUM(M59:P59) -> 0 | AG59: =SUM(I59:AF59) -> 0
G60: Военно-спортивное многоборье | H60: 50 | K60: =L60+X60 -> 0 | L60: =SUM(M60:P60) -> 0 | AG60: =SUM(I60:AF60) -> 0
G61: Воздухоплавательный спорт | H61: 51 | K61: =L61+X61 -> 0 | L61: =SUM(M61:P61) -> 0 | AG61: =SUM(I61:AF61) -> 0
G62: Воздушная гимнастика | H62: 52 | K62: =L62+X62 -> 0 | L62: =SUM(M62:P62) -> 0 | AG62: =SUM(I62:AF62) -> 0
G63: Воздушно-силовая атлетика | H63: 53 | K63: =L63+X63 -> 0 | L63: =SUM(M63:P63) -> 0 | AG63: =SUM(I63:AF63) -> 0
G64: Волейбол - всего | H64: 54 | I64: =IF(SUM(I65:I67)>=1,1,0) -> 0 | K64: =L64+X64 -> 0 | L64: =SUM(M64:P64) -> 0 | M64: =SUM(M65:M67) -> 0 | N64: =SUM(N65:N67) -> 0 | O64: =SUM(O65:O67) -> 0 | P64: =SUM(P65:P67) -> 0 | Q64: =SUM(Q65:Q67) -> 0 | R64: =SUM(R65:R67) -> 0 | S64: =SUM(S65:S67) -> 0 | T64: =SUM(T65:T67) -> 0 | ... AF64: =SUM(AF65:AF67) -> 0 | AG64: =SUM(I64:AF64) -> 0
G65: в том числе: Волейбол | H65: 55 | K65: =L65+X65 -> 0 | L65: =SUM(M65:P65) -> 0 | AG65: =SUM(I65:AF65) -> 0
G66: Пляжный волейбол | H66: 56 | K66: =L66+X66 -> 0 | L66: =SUM(M66:P66) -> 0 | AG66: =SUM(I66:AF66) -> 0
G67: Волейбол на снегу | H67: 57 | K67: =L67+X67 -> 0 | L67: =SUM(M67:P67) -> 0 | AG67: =SUM(I67:AF67) -> 0
G68: Восточное боевое единоборство | H68: 58 | K68: =L68+X68 -> 0 | L68: =SUM(M68:P68) -> 0 | AG68: =SUM(I68:AF68) -> 0
G69: Всестилевое каратэ | H69: 59 | K69: =L69+X69 -> 0 | L69: =SUM(M69:P69) -> 0 | AG69: =SUM(I69:AF69) -> 0
G70: Гандбол - всего | H70: 60 | I70: =IF(SUM(I71:I72)>=1,1,0) -> 0 | K70: =L70+X70 -> 0 | L70: =SUM(M70:P70) -> 0 | M70: =SUM(M71:M72) -> 0 | N70: =SUM(N71:N72) -> 0 | O70: =SUM(O71:O72) -> 0 | P70: =SUM(P71:P72) -> 0 | Q70: =SUM(Q71:Q72) -> 0 | R70: =SUM(R71:R72) -> 0 | S70: =SUM(S71:S72) -> 0 | T70: =SUM(T71:T72) -> 0 | ... AF70: =SUM(AF71:AF72) -> 0 | AG70: =SUM(I70:AF70) -> 0
G71: в том числе: Гандбол | H71: 61 | K71: =L71+X71 -> 0 | L71: =SUM(M71:P71) -> 0 | AG71: =SUM(I71:AF71) -> 0
G72: Пляжный гандбол | H72: 62 | K72: =L72+X72 -> 0 | L72: =SUM(M72:P72) -> 0 | AG72: =SUM(I72:AF72) -> 0
G73: Гиревой спорт | H73: 63 | K73: =L73+X73 -> 0 | L73: =SUM(M73:P73) -> 0 | AG73: =SUM(I73:AF73) -> 0
G74: Го | H74: 64 | K74: =L74+X74 -> 0 | L74: =SUM(M74:P74) -> 0 | AG74: =SUM(I74:AF74) -> 0
G75: Гольф | H75: 65 | K75: =L75+X75 -> 0 | L75: =SUM(M75:P75) -> 0 | AG75: =SUM(I75:AF75) -> 0
G76: Гонки дронов (беспилотных воздушных судов) - всего | H76: 66 | I76: =IF(SUM(I77:I80)>=1,1,0) -> 0 | K76: =L76+X76 -> 0 | L76: =SUM(M76:P76) -> 0 | M76: =SUM(M77:M80) -> 0 | N76: =SUM(N77:N80) -> 0 | O76: =SUM(O77:O80) -> 0 | P76: =SUM(P77:P80) -> 0 | Q76: =SUM(Q77:Q80) -> 0 | R76: =SUM(R77:R80) -> 0 | S76: =SUM(S77:S80) -> 0 | T76: =SUM(T77:T80) -> 0 | ... AF76: =SUM(AF77:AF80) -> 0 | AG76: =SUM(I76:AF76) -> 0
G77: в том числе: Класс 75 мм | H77: 67 | K77: =L77+X77 -> 0 | L77: =SUM(M77:P77) -> 0 | AG77: =SUM(I77:AF77) -> 0
G78: Класс 200 мм | H78: 68 | K78: =L78+X78 -> 0 | L78: =SUM(M78:P78) -> 0 | AG78: =SUM(I78:AF78) -> 0
G79: Класс 330 мм | H79: 69 | K79: =L79+X79 -> 0 | L79: =SUM(M79:P79) -> 0 | AG79: =SUM(I79:AF79) -> 0
G80: Технический симулятор | H80: 70 | K80: =L80+X80 -> 0 | L80: =SUM(M80:P80) -> 0 | AG80: =SUM(I80:AF80) -> 0
G81: Гонки на охотничьих лыжах | H81: 71 | K81: =L81+X81 -> 0 | L81: =SUM(M81:P81) -> 0 | AG81: =SUM(I81:AF81) -> 0
G82: Гонки с препятствиями | H82: 72 | K82: =L82+X82 -> 0 | L82: =SUM(M82:P82) -> 0 | AG82: =SUM(I82:AF82) -> 0
G83: Горнолыжный спорт | H83: 73 | K83: =L83+X83 -> 0 | L83: =SUM(M83:P83) -> 0 | AG83: =SUM(I83:AF83) -> 0
G84: Городошный спорт | H84: 74 | K84: =L84+X84 -> 0 | L84: =SUM(M84:P84) -> 0 | AG84: =SUM(I84:AF84) -> 0
G85: Гребля на байдарках и каноэ | H85: 75 | K85: =L85+X85 -> 0 | L85: =SUM(M85:P85) -> 0 | AG85: =SUM(I85:AF85) -> 0
G86: Гребля на шлюпках | H86: 76 | K86: =L86+X86 -> 0 | L86: =SUM(M86:P86) -> 0 | AG86: =SUM(I86:AF86) -> 0
G87: Гребной слалом | H87: 77 | K87: =L87+X87 -> 0 | L87: =SUM(M87:P87) -> 0 | AG87: =SUM(I87:AF87) -> 0
G88: Гребной спорт - всего | H88: 78 | I88: =IF(SUM(I89:I90)>=1,1,0) -> 0 | K88: =L88+X88 -> 0 | L88: =SUM(M88:P88) -> 0 | M88: =SUM(M89:M90) -> 0 | N88: =SUM(N89:N90) -> 0 | O88: =SUM(O89:O90) -> 0 | P88: =SUM(P89:P90) -> 0 | Q88: =SUM(Q89:Q90) -> 0 | R88: =SUM(R89:R90) -> 0 | S88: =SUM(S89:S90) -> 0 | T88: =SUM(T89:T90) -> 0 | ... AF88: =SUM(AF89:AF90) -> 0 | AG88: =SUM(I88:AF88) -> 0
G89: в том числе: Академическая гребля | H89: 79 | K89: =L89+X89 -> 0 | L89: =SUM(M89:P89) -> 0 | AG89: =SUM(I89:AF89) -> 0
G90: Иные дисциплины вида спорта "гребной спорт" | H90: 80 | K90: =L90+X90 -> 0 | L90: =SUM(M90:P90) -> 0 | AG90: =SUM(I90:AF90) -> 0
G91: Гребно-парусное двоеборье | H91: 81 | K91: =L91+X91 -> 0 | L91: =SUM(M91:P91) -> 0 | AG91: =SUM(I91:AF91) -> 0
G92: Дартс | H92: 82 | K92: =L92+X92 -> 0 | L92: =SUM(M92:P92) -> 0 | AG92: =SUM(I92:AF92) -> 0
G93: Джиу-джитсу | H93: 83 | K93: =L93+X93 -> 0 | L93: =SUM(M93:P93) -> 0 | AG93: =SUM(I93:AF93) -> 0
G94: Джутайдо | H94: 84 | K94: =L94+X94 -> 0 | L94: =SUM(M94:P94) -> 0 | AG94: =SUM(I94:AF94) -> 0
G95: Дзюдо | H95: 85 | K95: =L95+X95 -> 0 | L95: =SUM(M95:P95) -> 0 | AG95: =SUM(I95:AF95) -> 0
G96: Ездовой спорт | H96: 86 | K96: =L96+X96 -> 0 | L96: =SUM(M96:P96) -> 0 | AG96: =SUM(I96:AF96) -> 0
G97: Зимнее плавание | H97: 87 | K97: =L97+X97 -> 0 | L97: =SUM(M97:P97) -> 0 | AG97: =SUM(I97:AF97) -> 0
G98: Капоэйра | H98: 88 | K98: =L98+X98 -> 0 | L98: =SUM(M98:P98) -> 0 | AG98: =SUM(I98:AF98) -> 0
G99: Каратэ | H99: 89 | K99: =L99+X99 -> 0 | L99: =SUM(M99:P99) -> 0 | AG99: =SUM(I99:AF99) -> 0
G100: Кендо | H100: 90 | K100: =L100+X100 -> 0 | L100: =SUM(M100:P100) -> 0 | AG100: =SUM(I100:AF100) -> 0
G101: Керешу | H101: 91 | K101: =L101+X101 -> 0 | L101: =SUM(M101:P101) -> 0 | AG101: =SUM(I101:AF101) -> 0
G102: Кёрлинг - всего | H102: 92 | I102: =IF(SUM(I103:I104)>=1,1,0) -> 0 | K102: =L102+X102 -> 0 | L102: =SUM(M102:P102) -> 0 | M102: =SUM(M103:M104) -> 0 | N102: =SUM(N103:N104) -> 0 | O102: =SUM(O103:O104) -> 0 | P102: =SUM(P103:P104) -> 0 | Q102: =SUM(Q103:Q104) -> 0 | R102: =SUM(R103:R104) -> 0 | S102: =SUM(S103:S104) -> 0 | T102: =SUM(T103:T104) -> 0 | ... AF102: =SUM(AF103:AF104) -> 0 | AG102: =SUM(I102:AF102) -> 0
G103: в том числе: Кёрлинг | H103: 93 | K103: =L103+X103 -> 0 | L103: =SUM(M103:P103) -> 0 | AG103: =SUM(I103:AF103) -> 0
G104: Кёрлинг - смешанные пары | H104: 94 | K104: =L104+X104 -> 0 | L104: =SUM(M104:P104) -> 0 | AG104: =SUM(I104:AF104) -> 0
...

Sheet Раздел 3
G5: Раздел III. Численность обучающихся по дополнительным образовательным программам спортивной подготовки, человек
G6: Виды спорта | H6: № строки | I6: Численность обучающихся по дополнительным образовательным программам спортивной подготовки на 31 декабря отчетного периода (из гр.6 раздела II) | AC6: Численность обучающихся, зачисленных на дополнительные образовательные программы спортивной подготовки в отчетном периоде | AH6: Численность обучающихся, отчисленных с дополнительных образовательных программ спортивной подготовки в отчетном периоде
I7: Всего | J7: в том числе по этапам и годам подготовки | AC7: Всего | AD7: в том числе по этапам подготовки | AH7: Всего | AI7: в том числе по этапам подготовки
J8: начальной подготовки | M8: учебно-тренировочный | S8: совершенствования спортивного мастерства | X8: высшего спортивного мастерства
J9: 1 | K9: 2 | L9: более 2 | M9: 1 | N9: 2 | O9: 3 | P9: 4 | Q9: 5 | R9: более 5 | S9: 1 | T9: 2 | U9: 3 | V9: 4 | W9: более 4 | X9: 1 | Y9: 2 | Z9: 3 | AA9: 4 | AB9: более 4 | AD9: начальной подготовки | AE9: учебно-тренировочный | AF9: совершен-ствования спортивного мастерства | AG9: высшего спортивного мастерства | AI9: начальной подготовки | AJ9: учебно-тренировочный | AK9: совершен-ствования спортивного мастерства | AL9: высшего спортивного мастерства
A10: ='Раздел 0'!M27 -> 0 | B10: ='Раздел 1'!D15 -> 0 | C10: {=_xlfn.IFS(SUM('Раздел 1'!$D$5:$D$6)>0,"ФКиС",SUM('Раздел 1'!$D$7:$D$8)>0,"Образование",SUM('Раздел 1'!$D$9:$D$10)>0,"Другая")} -> ФКиС | D10: {=_xlfn.IFS(SUM('Раздел 1'!$E$12)>0,"СШ",SUM('Раздел 1'!$F$12)>0,"СШОР",SUM('Раздел 1'!$G$12)>0,"УОР",SUM('Раздел 1'!$H$12)>0,"ЦСП",SUM('Раздел 1'!$I$12)>0,"ДРУГИЕ",SUM('Раздел 1'!$E$13)>0,"ОСП СШ",SUM('Раздел 1'!$F$13)>0,"ОСП СШОР",SUM('Раздел 1'!$I$13)>0,"ОСП ДРУГИЕ")} -> ЦСП | E10: =IF(SUM('Раздел 1'!$D$12)>0,SUM('Раздел 1'!$D$13),"") -> 0 | F10: {=_xlfn.IFS(SUM('Раздел 1'!$D$19)>0,"РФ",SUM('Раздел 1'!$E$19)>0,"СУБЪЕКТ",SUM('Раздел 1'!$F$19:$G$19)>0,"МУНИЦИПАЛ",SUM('Раздел 1'!$H$19:$I$19)>0,"ИНЫЕ")} -> #N/A | G10: 1 | H10: 2 | I10: 3 | J10: 4 | K10: 5 | L10: 6 | M10: 7 | N10: 8 | O10: 9 | P10: 10 | Q10: 11 | R10: 12 | S10: 13 | T10: 14 | U10: 15 | V10: 16 | W10: 17 | X10: 18 | Y10: 19 | Z10: 20 | AA10: 21 | AB10: 22 | AC10: 23 | AD10: 24 | AE10: 25 | AF10: 26 | AG10: 27 | AH10: 28 | AI10: 29 | AJ10: 30 | AK10: 31 | AL10: 32 | AM10: 33
G11: Авиамодельный спорт | H11: 01 | I11: =SUM(J11:AB11) -> 0 | AC11: =SUM(AD11:AG11) -> 0 | AH11: =SUM(AI11:AL11) -> 0 | AM11: =SUM(J11:AL11) -> 0
G12: Авиационные гонки | H12: 02 | I12: =SUM(J12:AB12) -> 0 | AC12: =SUM(AD12:AG12) -> 0 | AH12: =SUM(AI12:AL12) -> 0 | AM12: =SUM(J12:AL12) -> 0
G13: Автомобильный спорт | H13: 03 | I13: =SUM(J13:AB13) -> 0 | AC13: =SUM(AD13:AG13) -> 0 | AH13: =SUM(AI13:AL13) -> 0 | AM13: =SUM(J13:AL13) -> 0
G14: Автомодельный спорт | H14: 04 | I14: =SUM(J14:AB14) -> 0 | AC14: =SUM(AD14:AG14) -> 0 | AH14: =SUM(AI14:AL14) -> 0 | AM14: =SUM(J14:AL14) -> 0
G15: Айкидо | H15: 05 | I15: =SUM(J15:AB15) -> 0 | AC15: =SUM(AD15:AG15) -> 0 | AH15: =SUM(AI15:AL15) -> 0 | AM15: =SUM(J15:AL15) -> 0
G16: Акробатический рок-н-ролл | H16: 06 | I16: =SUM(J16:AB16) -> 0 | AC16: =SUM(AD16:AG16) -> 0 | AH16: =SUM(AI16:AL16) -> 0 | AM16: =SUM(J16:AL16) -> 0
G17: Альпинизм - всего | H17: 07 | I17: =SUM(J17:AB17) -> 0 | J17: =SUM(J18:J19) -> 0 | K17: =SUM(K18:K19) -> 0 | L17: =SUM(L18:L19) -> 0 | M17: =SUM(M18:M19) -> 0 | N17: =SUM(N18:N19) -> 0 | O17: =SUM(O18:O19) -> 0 | P17: =SUM(P18:P19) -> 0 | Q17: =SUM(Q18:Q19) -> 0 | ... AB17: =SUM(AB18:AB19) -> 0 | AC17: =SUM(AD17:AG17) -> 0 | AD17: =SUM(AD18:AD19) -> 0 | AE17: =SUM(AE18:AE19) -> 0 | AF17: =SUM(AF18:AF19) -> 0 | AG17: =SUM(AG18:AG19) -> 0 | AH17: =SUM(AI17:AL17) -> 0 | AI17: =SUM(AI18:AI19) -> 0 | AJ17: =SUM(AJ18:AJ19) -> 0 | AK17: =SUM(AK18:AK19) -> 0 | AL17: =SUM(AL18:AL19) -> 0 | AM17: =SUM(J17:AL17) -> 0
G18: в том числе: Ски-альпинизм | H18: 08 | I18: =SUM(J18:AB18) -> 0 | AC18: =SUM(AD18:AG18) -> 0 | AH18: =SUM(AI18:AL18) -> 0 | AM18: =SUM(J18:AL18) -> 0
G19: Иные дисциплины вида спорта "альпинизм" | H19: 09 | I19: =SUM(J19:AB19) -> 0 | AC19: =SUM(AD19:AG19) -> 0 | AH19: =SUM(AI19:AL19) -> 0 | AM19: =SUM(J19:AL19) -> 0
G20: Американский футбол | H20: 10 | I20: =SUM(J20:AB20) -> 0 | AC20: =SUM(AD20:AG20) -> 0 | AH20: =SUM(AI20:AL20) -> 0 | AM20: =SUM(J20:AL20) -> 0
G21: Армейская высокоточная стрельба | H21: 11 | I21: =SUM(J21:AB21) -> 0 | AC21: =SUM(AD21:AG21) -> 0 | AH21: =SUM(AI21:AL21) -> 0 | AM21: =SUM(J21:AL21) -> 0
G22: Армейский рукопашный бой | H22: 12 | I22: =SUM(J22:AB22) -> 0 | AC22: =SUM(AD22:AG22) -> 0 | AH22: =SUM(AI22:AL22) -> 0 | AM22: =SUM(J22:AL22) -> 0
G23: Армейское тактико-стрелковое многоборье | H23: 13 | I23: =SUM(J23:AB23) -> 0 | AC23: =SUM(AD23:AG23) -> 0 | AH23: =SUM(AI23:AL23) -> 0 | AM23: =SUM(J23:AL23) -> 0
G24: Армрестлинг | H24: 14 | I24: =SUM(J24:AB24) -> 0 | AC24: =SUM(AD24:AG24) -> 0 | AH24: =SUM(AI24:AL24) -> 0 | AM24: =SUM(J24:AL24) -> 0
G25: Бадминтон | H25: 15 | I25: =SUM(J25:AB25) -> 0 | AC25: =SUM(AD25:AG25) -> 0 | AH25: =SUM(AI25:AL25) -> 0 | AM25: =SUM(J25:AL25) -> 0
G26: Баскетбол - всего | H26: 16 | I26: =SUM(J26:AB26) -> 0 | J26: =SUM(J27:J30) -> 0 | K26: =SUM(K27:K30) -> 0 | L26: =SUM(L27:L30) -> 0 | M26: =SUM(M27:M30) -> 0 | N26: =SUM(N27:N30) -> 0 | O26: =SUM(O27:O30) -> 0 | P26: =SUM(P27:P30) -> 0 | Q26: =SUM(Q27:Q30) -> 0 | ... AB26: =SUM(AB27:AB30) -> 0 | AC26: =SUM(AD26:AG26) -> 0 | AD26: =SUM(AD27:AD30) -> 0 | AE26: =SUM(AE27:AE30) -> 0 | AF26: =SUM(AF27:AF30) -> 0 | AG26: =SUM(AG27:AG30) -> 0 | AH26: =SUM(AI26:AL26) -> 0 | AI26: =SUM(AI27:AI30) -> 0 | AJ26: =SUM(AJ27:AJ30) -> 0 | AK26: =SUM(AK27:AK30) -> 0 | AL26: =SUM(AL27:AL30) -> 0 | AM26: =SUM(J26:AL26) -> 0
G27: в том числе: Баскетбол | H27: 17 | I27: =SUM(J27:AB27) -> 0 | AC27: =SUM(AD27:AG27) -> 0 | AH27: =SUM(AI27:AL27) -> 0 | AM27: =SUM(J27:AL27) -> 0
G28: Баскетбол 3х3 | H28: 18 | I28: =SUM(J28:AB28) -> 0 | AC28: =SUM(AD28:AG28) -> 0 | AH28: =SUM(AI28:AL28) -> 0 | AM28: =SUM(J28:AL28) -> 0
G29: Интерактивный баскетбол | H29: 19 | I29: =SUM(J29:AB29) -> 0 | AC29: =SUM(AD29:AG29) -> 0 | AH29: =SUM(AI29:AL29) -> 0 | AM29: =SUM(J29:AL29) -> 0
G30: Иные дисциплины вида спорта "баскетбол" | H30: 20 | I30: =SUM(J30:AB30) -> 0 | AC30: =SUM(AD30:AG30) -> 0 | AH30: =SUM(AI30:AL30) -> 0 | AM30: =SUM(J30:AL30) -> 0
G31: Бейсбол | H31: 21 | I31: =SUM(J31:AB31) -> 0 | AC31: =SUM(AD31:AG31) -> 0 | AH31: =SUM(AI31:AL31) -> 0 | AM31: =SUM(J31:AL31) -> 0
G32: Биатлон | H32: 22 | I32: =SUM(J32:AB32) -> 0 | AC32: =SUM(AD32:AG32) -> 0 | AH32: =SUM(AI32:AL32) -> 0 | AM32: =SUM(J32:AL32) -> 0
G33: Бильярдный спорт | H33: 23 | I33: =SUM(J33:AB33) -> 0 | AC33: =SUM(AD33:AG33) -> 0 | AH33: =SUM(AI33:AL33) -> 0 | AM33: =SUM(J33:AL33) -> 0
G34: Бобслей - всего | H34: 24 | I34: =SUM(J34:AB34) -> 0 | J34: =SUM(J35:J38) -> 0 | K34: =SUM(K35:K38) -> 0 | L34: =SUM(L35:L38) -> 0 | M34: =SUM(M35:M38) -> 0 | N34: =SUM(N35:N38) -> 0 | O34: =SUM(O35:O38) -> 0 | P34: =SUM(P35:P38) -> 0 | Q34: =SUM(Q35:Q38) -> 0 | ... AB34: =SUM(AB35:AB38) -> 0 | AC34: =SUM(AD34:AG34) -> 0 | AD34: =SUM(AD35:AD38) -> 0 | AE34: =SUM(AE35:AE38) -> 0 | AF34: =SUM(AF35:AF38) -> 0 | AG34: =SUM(AG35:AG38) -> 0 | AH34: =SUM(AI34:AL34) -> 0 | AI34: =SUM(AI35:AI38) -> 0 | AJ34: =SUM(AJ35:AJ38) -> 0 | AK34: =SUM(AK35:AK38) -> 0 | AL34: =SUM(AL35:AL38) -> 0 | AM34: =SUM(J34:AL34) -> 0
G35: в том числе: Скелетон | H35: 25 | I35: =SUM(J35:AB35) -> 0 | AC35: =SUM(AD35:AG35) -> 0 | AH35: =SUM(AI35:AL35) -> 0 | AM35: =SUM(J35:AL35) -> 0
G36: Экипаж | H36: 26 | I36: =SUM(J36:AB36) -> 0 | AC36: =SUM(AD36:AG36) -> 0 | AH36: =SUM(AI36:AL36) -> 0 | AM36: =SUM(J36:AL36) -> 0
G37: Монобоб | H37: 27 | I37: =SUM(J37:AB37) -> 0 | AC37: =SUM(AD37:AG37) -> 0 | AH37: =SUM(AI37:AL37) -> 0 | AM37: =SUM(J37:AL37) -> 0
G38: Иные дисциплины вида спорта "бобслей" | H38: 28 | I38: =SUM(J38:AB38) -> 0 | AC38: =SUM(AD38:AG38) -> 0 | AH38: =SUM(AI38:AL38) -> 0 | AM38: =SUM(J38:AL38) -> 0
G39: Бодибилдинг | H39: 29 | I39: =SUM(J39:AB39) -> 0 | AC39: =SUM(AD39:AG39) -> 0 | AH39: =SUM(AI39:AL39) -> 0 | AM39: =SUM(J39:AL39) -> 0
G40: Бокс | H40: 30 | I40: =SUM(J40:AB40) -> 0 | AC40: =SUM(AD40:AG40) -> 0 | AH40: =SUM(AI40:AL40) -> 0 | AM40: =SUM(J40:AL40) -> 0
G41: Борьба на поясах | H41: 31 | I41: =SUM(J41:AB41) -> 0 | AC41: =SUM(AD41:AG41) -> 0 | AH41: =SUM(AI41:AL41) -> 0 | AM41: =SUM(J41:AL41) -> 0
G42: Боулинг | H42: 32 | I42: =SUM(J42:AB42) -> 0 | AC42: =SUM(AD42:AG42) -> 0 | AH42: =SUM(AI42:AL42) -> 0 | AM42: =SUM(J42:AL42) -> 0
G43: Боулспорт | H43: 33 | I43: =SUM(J43:AB43) -> 0 | AC43: =SUM(AD43:AG43) -> 0 | AH43: =SUM(AI43:AL43) -> 0 | AM43: =SUM(J43:AL43) -> 0
G44: Брейкинг | H44: 34 | I44: =SUM(J44:AB44) -> 0 | AC44: =SUM(AD44:AG44) -> 0 | AH44: =SUM(AI44:AL44) -> 0 | AM44: =SUM(J44:AL44) -> 0
G45: Велосипедный спорт - всего | H45: 35 | I45: =SUM(J45:AB45) -> 0 | J45: =SUM(J46:J51) -> 0 | K45: =SUM(K46:K51) -> 0 | L45: =SUM(L46:L51) -> 0 | M45: =SUM(M46:M51) -> 0 | N45: =SUM(N46:N51) -> 0 | O45: =SUM(O46:O51) -> 0 | P45: =SUM(P46:P51) -> 0 | Q45: =SUM(Q46:Q51) -> 0 | ... AB45: =SUM(AB46:AB51) -> 0 | AC45: =SUM(AD45:AG45) -> 0 | AD45: =SUM(AD46:AD51) -> 0 | AE45: =SUM(AE46:AE51) -> 0 | AF45: =SUM(AF46:AF51) -> 0 | AG45: =SUM(AG46:AG51) -> 0 | AH45: =SUM(AI45:AL45) -> 0 | AI45: =SUM(AI46:AI51) -> 0 | AJ45: =SUM(AJ46:AJ51) -> 0 | AK45: =SUM(AK46:AK51) -> 0 | AL45: =SUM(AL46:AL51) -> 0 | AM45: =SUM(J45:AL45) -> 0
G46: в том числе: BMX (гонка, эстафета) | H46: 36 | I46: =SUM(J46:AB46) -> 0 | AC46: =SUM(AD46:AG46) -> 0 | AH46: =SUM(AI46:AL46) -> 0 | AM46: =SUM(J46:AL46) -> 0
G47: BMX - фристайл | H47: 37 | I47: =SUM(J47:AB47) -> 0 | AC47: =SUM(AD47:AG47) -> 0 | AH47: =SUM(AI47:AL47) -> 0 | AM47: =SUM(J47:AL47) -> 0
G48: Маунтинбайк | H48: 38 | I48: =SUM(J48:AB48) -> 0 | AC48: =SUM(AD48:AG48) -> 0 | AH48: =SUM(AI48:AL48) -> 0 | AM48: =SUM(J48:AL48) -> 0
G49: Трек | H49: 39 | I49: =SUM(J49:AB49) -> 0 | AC49: =SUM(AD49:AG49) -> 0 | AH49: =SUM(AI49:AL49) -> 0 | AM49: =SUM(J49:AL49) -> 0
G50: Шоссе | H50: 40 | I50: =SUM(J50:AB50) -> 0 | AC50: =SUM(AD50:AG50) -> 0 | AH50: =SUM(AI50:AL50) -> 0 | AM50: =SUM(J50:AL50) -> 0
G51: Технический симулятор | H51: 41 | I51: =SUM(J51:AB51) -> 0 | AC51: =SUM(AD51:AG51) -> 0 | AH51: =SUM(AI51:AL51) -> 0 | AM51: =SUM(J51:AL51) -> 0
G52: Вертолетный спорт | H52: 42 | I52: =SUM(J52:AB52) -> 0 | AC52: =SUM(AD52:AG52) -> 0 | AH52: =SUM(AI52:AL52) -> 0 | AM52: =SUM(J52:AL52) -> 0
G53: Водное поло - всего | H53: 43 | I53: =SUM(J53:AB53) -> 0 | J53: =SUM(J54:J55) -> 0 | K53: =SUM(K54:K55) -> 0 | L53: =SUM(L54:L55) -> 0 | M53: =SUM(M54:M55) -> 0 | N53: =SUM(N54:N55) -> 0 | O53: =SUM(O54:O55) -> 0 | P53: =SUM(P54:P55) -> 0 | Q53: =SUM(Q54:Q55) -> 0 | ... AB53: =SUM(AB54:AB55) -> 0 | AC53: =SUM(AD53:AG53) -> 0 | AD53: =SUM(AD54:AD55) -> 0 | AE53: =SUM(AE54:AE55) -> 0 | AF53: =SUM(AF54:AF55) -> 0 | AG53: =SUM(AG54:AG55) -> 0 | AH53: =SUM(AI53:AL53) -> 0 | AI53: =SUM(AI54:AI55) -> 0 | AJ53: =SUM(AJ54:AJ55) -> 0 | AK53: =SUM(AK54:AK55) -> 0 | AL53: =SUM(AL54:AL55) -> 0 | AM53: =SUM(J53:AL53) -> 0
G54: в том числе: Водное поло | H54: 44 | I54: =SUM(J54:AB54) -> 0 | AC54: =SUM(AD54:AG54) -> 0 | AH54: =SUM(AI54:AL54) -> 0 | AM54: =SUM(J54:AL54) -> 0
G55: Иные дисциплины вида спорта "водное поло" | H55: 45 | I55: =SUM(J55:AB55) -> 0 | AC55: =SUM(AD55:AG55) -> 0 | AH55: =SUM(AI55:AL55) -> 0 | AM55: =SUM(J55:AL55) -> 0
G56: Воднолыжный спорт | H56: 46 | I56: =SUM(J56:AB56) -> 0 | AC56: =SUM(AD56:AG56) -> 0 | AH56: =SUM(AI56:AL56) -> 0 | AM56: =SUM(J56:AL56) -> 0
G57: Водно-моторный спорт | H57: 47 | I57: =SUM(J57:AB57) -> 0 | AC57: =SUM(AD57:AG57) -> 0 | AH57: =SUM(AI57:AL57) -> 0 | AM57: =SUM(J57:AL57) -> 0
G58: Водно-спасательное многоборье | H58: 48 | I58: =SUM(J58:AB58) -> 0 | AC58: =SUM(AD58:AG58) -> 0 | AH58: =SUM(AI58:AL58) -> 0 | AM58: =SUM(J58:AL58) -> 0
G59: Военно-прикладной спорт | H59: 49 | I59: =SUM(J59:AB59) -> 0 | AC59: =SUM(AD59:AG59) -> 0 | AH59: =SUM(AI59:AL59) -> 0 | AM59: =SUM(J59:AL59) -> 0
G60: Военно-спортивное многоборье | H60: 50 | I60: =SUM(J60:AB60) -> 0 | AC60: =SUM(AD60:AG60) -> 0 | AH60: =SUM(AI60:AL60) -> 0 | AM60: =SUM(J60:AL60) -> 0
G61: Воздухоплавательный спорт | H61: 51 | I61: =SUM(J61:AB61) -> 0 | AC61: =SUM(AD61:AG61) -> 0 | AH61: =SUM(AI61:AL61) -> 0 | AM61: =SUM(J61:AL61) -> 0
G62: Воздушная гимнастика | H62: 52 | I62: =SUM(J62:AB62) -> 0 | AC62: =SUM(AD62:AG62) -> 0 | AH62: =SUM(AI62:AL62) -> 0 | AM62: =SUM(J62:AL62) -> 0
G63: Воздушно-силовая атлетика | H63: 53 | I63: =SUM(J63:AB63) -> 0 | AC63: =SUM(AD63:AG63) -> 0 | AH63: =SUM(AI63:AL63) -> 0 | AM63: =SUM(J63:AL63) -> 0
G64: Волейбол - всего | H64: 54 | I64: =SUM(J64:AB64) -> 0 | J64: =SUM(J65:J67) -> 0 | K64: =SUM(K65:K67) -> 0 | L64: =SUM(L65:L67) -> 0 | M64: =SUM(M65:M67) -> 0 | N64: =SUM(N65:N67) -> 0 | O64: =SUM(O65:O67) -> 0 | P64: =SUM(P65:P67) -> 0 | Q64: =SUM(Q65:Q67) -> 0 | ... AB64: =SUM(AB65:AB67) -> 0 | AC64: =SUM(AD64:AG64) -> 0 | AD64: =SUM(AD65:AD67) -> 0 | AE64: =SUM(AE65:AE67) -> 0 | AF64: =SUM(AF65:AF67) -> 0 | AG64: =SUM(AG65:AG67) -> 0 | AH64: =SUM(AI64:AL64) -> 0 | AI64: =SUM(AI65:AI67) -> 0 | AJ64: =SUM(AJ65:AJ67) -> 0 | AK64: =SUM(AK65:AK67) -> 0 | AL64: =SUM(AL65:AL67) -> 0 | AM64: =SUM(J64:AL64) -> 0
G65: в том числе: Волейбол | H65: 55 | I65: =SUM(J65:AB65) -> 0 | AC65: =SUM(AD65:AG65) -> 0 | AH65: =SUM(AI65:AL65) -> 0 | AM65: =SUM(J65:AL65) -> 0
G66: Пляжный волейбол | H66: 56 | I66: =SUM(J66:AB66) -> 0 | AC66: =SUM(AD66:AG66) -> 0 | AH66: =SUM(AI66:AL66) -> 0 | AM66: =SUM(J66:AL66) -> 0
G67: Волейбол на снегу | H67: 57 | I67: =SUM(J67:AB67) -> 0 | AC67: =SUM(AD67:AG67) -> 0 | AH67: =SUM(AI67:AL67) -> 0 | AM67: =SUM(J67:AL67) -> 0
G68: Восточное боевое единоборство | H68: 58 | I68: =SUM(J68:AB68) -> 0 | AC68: =SUM(AD68:AG68) -> 0 | AH68: =SUM(AI68:AL68) -> 0 | AM68: =SUM(J68:AL68) -> 0
G69: Всестилевое каратэ | H69: 59 | I69: =SUM(J69:AB69) -> 0 | AC69: =SUM(AD69:AG69) -> 0 | AH69: =SUM(AI69:AL69) -> 0 | AM69: =SUM(J69:AL69) -> 0
G70: Гандбол - всего | H70: 60 | I70: =SUM(J70:AB70) -> 0 | J70: =SUM(J71:J72) -> 0 | K70: =SUM(K71:K72) -> 0 | L70: =SUM(L71:L72) -> 0 | M70: =SUM(M71:M72) -> 0 | N70: =SUM(N71:N72) -> 0 | O70: =SUM(O71:O72) -> 0 | P70: =SUM(P71:P72) -> 0 | Q70: =SUM(Q71:Q72) -> 0 | ... AB70: =SUM(AB71:AB72) -> 0 | AC70: =SUM(AD70:AG70) -> 0 | AD70: =SUM(AD71:AD72) -> 0 | AE70: =SUM(AE71:AE72) -> 0 | AF70: =SUM(AF71:AF72) -> 0 | AG70: =SUM(AG71:AG72) -> 0 | AH70: =SUM(AI70:AL70) -> 0 | AI70: =SUM(AI71:AI72) -> 0 | AJ70: =SUM(AJ71:AJ72) -> 0 | AK70: =SUM(AK71:AK72) -> 0 | AL70: =SUM(AL71:AL72) -> 0 | AM70: =SUM(J70:AL70) -> 0
G71: в том числе: Гандбол | H71: 61 | I71: =SUM(J71:AB71) -> 0 | AC71: =SUM(AD71:AG71) -> 0 | AH71: =SUM(AI71:AL71) -> 0 | AM71: =SUM(J71:AL71) -> 0
G72: Пляжный гандбол | H72: 62 | I72: =SUM(J72:AB72) -> 0 | AC72: =SUM(AD72:AG72) -> 0 | AH72: =SUM(AI72:AL72) -> 0 | AM72: =SUM(J72:AL72) -> 0
G73: Гиревой спорт | H73: 63 | I73: =SUM(J73:AB73) -> 0 | AC73: =SUM(AD73:AG73) -> 0 | AH73: =SUM(AI73:AL73) -> 0 | AM73: =SUM(J73:AL73) -> 0
G74: Го | H74: 64 | I74: =SUM(J74:AB74) -> 0 | AC74: =SUM(AD74:AG74) -> 0 | AH74: =SUM(AI74:AL74) -> 0 | AM74: =SUM(J74:AL74) -> 0
G75: Гольф | H75: 65 | I75: =SUM(J75:AB75) -> 0 | AC75: =SUM(AD75:AG75) -> 0 | AH75: =SUM(AI75:AL75) -> 0 | AM75: =SUM(J75:AL75) -> 0
G76: Гонки дронов (беспилотных воздушных судов) - всего | H76: 66 | I76: =SUM(J76:AB76) -> 0 | J76: =SUM(J77:J80) -> 0 | K76: =SUM(K77:K80) -> 0 | L76: =SUM(L77:L80) -> 0 | M76: =SUM(M77:M80) -> 0 | N76: =SUM(N77:N80) -> 0 | O76: =SUM(O77:O80) -> 0 | P76: =SUM(P77:P80) -> 0 | Q76: =SUM(Q77:Q80) -> 0 | ... AB76: =SUM(AB77:AB80) -> 0 | AC76: =SUM(AD76:AG76) -> 0 | AD76: =SUM(AD77:AD80) -> 0 | AE76: =SUM(AE77:AE80) -> 0 | AF76: =SUM(AF77:AF80) -> 0 | AG76: =SUM(AG77:AG80) -> 0 | AH76: =SUM(AI76:AL76) -> 0 | AI76: =SUM(AI77:AI80) -> 0 | AJ76: =SUM(AJ77:AJ80) -> 0 | AK76: =SUM(AK77:AK80) -> 0 | AL76: =SUM(AL77:AL80) -> 0 | AM76: =SUM(J76:AL76) -> 0
G77: в том числе: Класс 75 мм | H77: 67 | I77: =SUM(J77:AB77) -> 0 | AC77: =SUM(AD77:AG77) -> 0 | AH77: =SUM(AI77:AL77) -> 0 | AM77: =SUM(J77:AL77) -> 0
G78: Класс 200 мм | H78: 68 | I78: =SUM(J78:AB78) -> 0 | AC78: =SUM(AD78:AG78) -> 0 | AH78: =SUM(AI78:AL78) -> 0 | AM78: =SUM(J78:AL78) -> 0
G79: Класс 330 мм | H79: 69 | I79: =SUM(J79:AB79) -> 0 | AC79: =SUM(AD79:AG79) -> 0 | AH79: =SUM(AI79:AL79) -> 0 | AM79: =SUM(J79:AL79) -> 0
G80: Технический симулятор | H80: 70 | I80: =SUM(J80:AB80) -> 0 | AC80: =SUM(AD80:AG80) -> 0 | AH80: =SUM(AI80:AL80) -> 0 | AM80: =SUM(J80:AL80) -> 0
G81: Гонки на охотничьих лыжах | H81: 71 | I81: =SUM(J81:AB81) -> 0 | AC81: =SUM(AD81:AG81) -> 0 | AH81: =SUM(AI81:AL81) -> 0 | AM81: =SUM(J81:AL81) -> 0
G82: Гонки с препятствиями | H82: 72 | I82: =SUM(J82:AB82) -> 0 | AC82: =SUM(AD82:AG82) -> 0 | AH82: =SUM(AI82:AL82) -> 0 | AM82: =SUM(J82:AL82) -> 0
G83: Горнолыжный спорт | H83: 73 | I83: =SUM(J83:AB83) -> 0 | AC83: =SUM(AD83:AG83) -> 0 | AH83: =SUM(AI83:AL83) -> 0 | AM83: =SUM(J83:AL83) -> 0
G84: Городошный спорт | H84: 74 | I84: =SUM(J84:AB84) -> 0 | AC84: =SUM(AD84:AG84) -> 0 | AH84: =SUM(AI84:AL84) -> 0 | AM84: =SUM(J84:AL84) -> 0
G85: Гребля на байдарках и каноэ | H85: 75 | I85: =SUM(J85:AB85) -> 0 | AC85: =SUM(AD85:AG85) -> 0 | AH85: =SUM(AI85:AL85) -> 0 | AM85: =SUM(J85:AL85) -> 0
G86: Гребля на шлюпках | H86: 76 | I86: =SUM(J86:AB86) -> 0 | AC86: =SUM(AD86:AG86) -> 0 | AH86: =SUM(AI86:AL86) -> 0 | AM86: =SUM(J86:AL86) -> 0
G87: Гребной слалом | H87: 77 | I87: =SUM(J87:AB87) -> 0 | AC87: =SUM(AD87:AG87) -> 0 | AH87: =SUM(AI87:AL87) -> 0 | AM87: =SUM(J87:AL87) -> 0
G88: Гребной спорт - всего | H88: 78 | I88: =SUM(J88:AB88) -> 0 | J88: =SUM(J89:J90) -> 0 | K88: =SUM(K89:K90) -> 0 | L88: =SUM(L89:L90) -> 0 | M88: =SUM(M89:M90) -> 0 | N88: =SUM(N89:N90) -> 0 | O88: =SUM(O89:O90) -> 0 | P88: =SUM(P89:P90) -> 0 | Q88: =SUM(Q89:Q90) -> 0 | ... AB88: =SUM(AB89:AB90) -> 0 | AC88: =SUM(AD88:AG88) -> 0 | AD88: =SUM(AD89:AD90) -> 0 | AE88: =SUM(AE89:AE90) -> 0 | AF88: =SUM(AF89:AF90) -> 0 | AG88: =SUM(AG89:AG90) -> 0 | AH88: =SUM(AI88:AL88) -> 0 | AI88: =SUM(AI89:AI90) -> 0 | AJ88: =SUM(AJ89:AJ90) -> 0 | AK88: =SUM(AK89:AK90) -> 0 | AL88: =SUM(AL89:AL90) -> 0 | AM88: =SUM(J88:AL88) -> 0
G89: в том числе: Академическая гребля | H89: 79 | I89: =SUM(J89:AB89) -> 0 | AC89: =SUM(AD89:AG89) -> 0 | AH89: =SUM(AI89:AL89) -> 0 | AM89: =SUM(J89:AL89) -> 0
G90: Иные дисциплины вида спорта "гребной спорт" | H90: 80 | I90: =SUM(J90:AB90) -> 0 | AC90: =SUM(AD90:AG90) -> 0 | AH90: =SUM(AI90:AL90) -> 0 | AM90: =SUM(J90:AL90) -> 0
G91: Гребно-парусное двоеборье | H91: 81 | I91: =SUM(J91:AB91) -> 0 | AC91: =SUM(AD91:AG91) -> 0 | AH91: =SUM(AI91:AL91) -> 0 | AM91: =SUM(J91:AL91) -> 0
G92: Дартс | H92: 82 | I92: =SUM(J92:AB92) -> 0 | AC92: =SUM(AD92:AG92) -> 0 | AH92: =SUM(AI92:AL92) -> 0 | AM92: =SUM(J92:AL92) -> 0
G93: Джиу-джитсу | H93: 83 | I93: =SUM(J93:AB93) -> 0 | AC93: =SUM(AD93:AG93) -> 0 | AH93: =SUM(AI93:AL93) -> 0 | AM93: =SUM(J93:AL93) -> 0
G94: Джутайдо | H94: 84 | I94: =SUM(J94:AB94) -> 0 | AC94: =SUM(AD94:AG94) -> 0 | AH94: =SUM(AI94:AL94) -> 0 | AM94: =SUM(J94:AL94) -> 0
G95: Дзюдо | H95: 85 | I95: =SUM(J95:AB95) -> 0 | AC95: =SUM(AD95:AG95) -> 0 | AH95: =SUM(AI95:AL95) -> 0 | AM95: =SUM(J95:AL95) -> 0
G96: Ездовой спорт | H96: 86 | I96: =SUM(J96:AB96) -> 0 | AC96: =SUM(AD96:AG96) -> 0 | AH96: =SUM(AI96:AL96) -> 0 | AM96: =SUM(J96:AL96) -> 0
G97: Зимнее плавание | H97: 87 | I97: =SUM(J97:AB97) -> 0 | AC97: =SUM(AD97:AG97) -> 0 | AH97: =SUM(AI97:AL97) -> 0 | AM97: =SUM(J97:AL97) -> 0
G98: Капоэйра | H98: 88 | I98: =SUM(J98:AB98) -> 0 | AC98: =SUM(AD98:AG98) -> 0 | AH98: =SUM(AI98:AL98) -> 0 | AM98: =SUM(J98:AL98) -> 0
G99: Каратэ | H99: 89 | I99: =SUM(J99:AB99) -> 0 | AC99: =SUM(AD99:AG99) -> 0 | AH99: =SUM(AI99:AL99) -> 0 | AM99: =SUM(J99:AL99) -> 0
G100: Кендо | H100: 90 | I100: =SUM(J100:AB100) -> 0 | AC100: =SUM(AD100:AG100) -> 0 | AH100: =SUM(AI100:AL100) -> 0 | AM100: =SUM(J100:AL100) -> 0
G101: Керешу | H101: 91 | I101: =SUM(J101:AB101) -> 0 | AC101: =SUM(AD101:AG101) -> 0 | AH101: =SUM(AI101:AL101) -> 0 | AM101: =SUM(J101:AL101) -> 0
G102: Кёрлинг - всего | H102: 92 | I102: =SUM(J102:AB102) -> 0 | J102: =SUM(J103:J104) -> 0 | K102: =SUM(K103:K104) -> 0 | L102: =SUM(L103:L104) -> 0 | M102: =SUM(M103:M104) -> 0 | N102: =SUM(N103:N104) -> 0 | O102: =SUM(O103:O104) -> 0 | P102: =SUM(P103:P104) -> 0 | Q102: =SUM(Q103:Q104) -> 0 | ... AB102: =SUM(AB103:AB104) -> 0 | AC102: =SUM(AD102:AG102) -> 0 | AD102: =SUM(AD103:AD104) -> 0 | AE102: =SUM(AE103:AE104) -> 0 | AF102: =SUM(AF103:AF104) -> 0 | AG102: =SUM(AG103:AG104) -> 0 | AH102: =SUM(AI102:AL102) -> 0 | AI102: =SUM(AI103:AI104) -> 0 | AJ102: =SUM(AJ103:AJ104) -> 0 | AK102: =SUM(AK103:AK104) -> 0 | AL102: =SUM(AL103:AL104) -> 0 | AM102: =SUM(J102:AL102) -> 0
G103: в том числе: Кёрлинг | H103: 93 | I103: =SUM(J103:AB103) -> 0 | AC103: =SUM(AD103:AG103) -> 0 | AH103: =SUM(AI103:AL103) -> 0 | AM103: =SUM(J103:AL103) -> 0
G104: Кёрлинг - смешанные пары | H104: 94 | I104: =SUM(J104:AB104) -> 0 | AC104: =SUM(AD104:AG104) -> 0 | AH104: =SUM(AI104:AL104) -> 0 | AM104: =SUM(J104:AL104) -> 0
...

Sheet Раздел 4
G1: Раздел IV. Спортивные разряды, спортивные звания
G6: Виды спорта | H6: № строки | I6: Из численности обучающихся и спортсменов, спортсменов-инструкторов на ставках (гр.5 раздела II и стр. 05 раздела IX), имеющих разряды, звания, человек | U6: Разряды, звания, присвоенные в отчетном периоде, единица
I7: Итого | J7: спортивные разряды | P7: спортивные звания | U7: Итого | V7: спортивные разряды присвоенные | AB7: спортивные звания присвоенные
J8: Всего | K8: в том числе: | P8: Всего | Q8: в том числе: | V8: Всего | W8: в том числе: | AB8: Всего | AC8: в том числе:
K9: КМС | L9: 1 разряд | M9: 2 разряд | N9: 3 разряд | O9: юношеские разряды | Q9: ЗМС | R9: МСМК | S9: МС | T9: гроссмейстер | W9: КМС | X9: 1 разряд | Y9: 2 разряд | Z9: 3 разряд | AA9: юношеские разряды | AC9: ЗМС | AD9: МСМК | AE9: МС | AF9: гроссмейстер
A10: ='Раздел 0'!M27 -> 0 | B10: ='Раздел 1'!D15 -> 0 | C10: {=_xlfn.IFS(SUM('Раздел 1'!$D$5:$D$6)>0,"ФКиС",SUM('Раздел 1'!$D$7:$D$8)>0,"Образование",SUM('Раздел 1'!$D$9:$D$10)>0,"Другая")} -> ФКиС | D10: {=_xlfn.IFS(SUM('Раздел 1'!$E$12)>0,"СШ",SUM('Раздел 1'!$F$12)>0,"СШОР",SUM('Раздел 1'!$G$12)>0,"УОР",SUM('Раздел 1'!$H$12)>0,"ЦСП",SUM('Раздел 1'!$I$12)>0,"ДРУГИЕ",SUM('Раздел 1'!$E$13)>0,"ОСП СШ",SUM('Раздел 1'!$F$13)>0,"ОСП СШОР",SUM('Раздел 1'!$I$13)>0,"ОСП ДРУГИЕ")} -> ЦСП | E10: =IF(SUM('Раздел 1'!$D$12)>0,SUM('Раздел 1'!$D$13),"") -> 0 | F10: {=_xlfn.IFS(SUM('Раздел 1'!$D$19)>0,"РФ",SUM('Раздел 1'!$E$19)>0,"СУБЪЕКТ",SUM('Раздел 1'!$F$19:$G$19)>0,"МУНИЦИПАЛ",SUM('Раздел 1'!$H$19:$I$19)>0,"ИНЫЕ")} -> #N/A | G10: 1 | H10: 2 | I10: 3 | J10: 4 | K10: 5 | L10: 6 | M10: 7 | N10: 8 | O10: 9 | P10: 10 | Q10: 11 | R10: 12 | S10: 13 | T10: 14 | U10: 15 | V10: 16 | W10: 17 | X10: 18 | Y10: 19 | Z10: 20 | AA10: 21 | AB10: 22 | AC10: 23 | AD10: 24 | AE10: 25 | AF10: 26 | AG10: 27
G11: Авиамодельный спорт | H11: 01 | I11: =J11+P11 -> 0 | J11: =SUM(K11:O11) -> 0 | P11: =SUM(Q11:T11) -> 0 | U11: =V11+AB11 -> 0 | V11: =SUM(W11:AA11) -> 0 | AB11: =SUM(AC11:AF11) -> 0 | AG11: =SUM(I11:AF11) -> 0
G12: Авиационные гонки | H12: 02 | I12: =J12+P12 -> 0 | J12: =SUM(K12:O12) -> 0 | P12: =SUM(Q12:T12) -> 0 | U12: =V12+AB12 -> 0 | V12: =SUM(W12:AA12) -> 0 | AB12: =SUM(AC12:AF12) -> 0 | AG12: =SUM(I12:AF12) -> 0
G13: Автомобильный спорт | H13: 03 | I13: =J13+P13 -> 0 | J13: =SUM(K13:O13) -> 0 | P13: =SUM(Q13:T13) -> 0 | U13: =V13+AB13 -> 0 | V13: =SUM(W13:AA13) -> 0 | AB13: =SUM(AC13:AF13) -> 0 | AG13: =SUM(I13:AF13) -> 0
G14: Автомодельный спорт | H14: 04 | I14: =J14+P14 -> 0 | J14: =SUM(K14:O14) -> 0 | P14: =SUM(Q14:T14) -> 0 | U14: =V14+AB14 -> 0 | V14: =SUM(W14:AA14) -> 0 | AB14: =SUM(AC14:AF14) -> 0 | AG14: =SUM(I14:AF14) -> 0
G15: Айкидо | H15: 05 | I15: =J15+P15 -> 0 | J15: =SUM(K15:O15) -> 0 | P15: =SUM(Q15:T15) -> 0 | U15: =V15+AB15 -> 0 | V15: =SUM(W15:AA15) -> 0 | AB15: =SUM(AC15:AF15) -> 0 | AG15: =SUM(I15:AF15) -> 0
G16: Акробатический рок-н-ролл | H16: 06 | I16: =J16+P16 -> 0 | J16: =SUM(K16:O16) -> 0 | P16: =SUM(Q16:T16) -> 0 | U16: =V16+AB16 -> 0 | V16: =SUM(W16:AA16) -> 0 | AB16: =SUM(AC16:AF16) -> 0 | AG16: =SUM(I16:AF16) -> 0
G17: Альпинизм - всего | H17: 07 | I17: =J17+P17 -> 0 | J17: =SUM(K17:O17) -> 0 | K17: =SUM(K18:K19) -> 0 | L17: =SUM(L18:L19) -> 0 | M17: =SUM(M18:M19) -> 0 | N17: =SUM(N18:N19) -> 0 | O17: =SUM(O18:O19) -> 0 | P17: =SUM(Q17:T17) -> 0 | Q17: =SUM(Q18:Q19) -> 0 | R17: =SUM(R18:R19) -> 0 | S17: =SUM(S18:S19) -> 0 | T17: =SUM(T18:T19) -> 0 | U17: =V17+AB17 -> 0 | V17: =SUM(W17:AA17) -> 0 | W17: =SUM(W18:W19) -> 0 | X17: =SUM(X18:X19) -> 0 | Y17: =SUM(Y18:Y19) -> 0 | Z17: =SUM(Z18:Z19) -> 0 | AA17: =SUM(AA18:AA19) -> 0 | AB17: =SUM(AC17:AF17) -> 0 | AC17: =SUM(AC18:AC19) -> 0 | AD17: =SUM(AD18:AD19) -> 0 | AE17: =SUM(AE18:AE19) -> 0 | AF17: =SUM(AF18:AF19) -> 0 | AG17: =SUM(I17:AF17) -> 0
G18: в том числе: Ски-альпинизм | H18: 08 | I18: =J18+P18 -> 0 | J18: =SUM(K18:O18) -> 0 | P18: =SUM(Q18:T18) -> 0 | U18: =V18+AB18 -> 0 | V18: =SUM(W18:AA18) -> 0 | AB18: =SUM(AC18:AF18) -> 0 | AG18: =SUM(I18:AF18) -> 0
G19: Иные дисциплины вида спорта "альпинизм" | H19: 09 | I19: =J19+P19 -> 0 | J19: =SUM(K19:O19) -> 0 | P19: =SUM(Q19:T19) -> 0 | U19: =V19+AB19 -> 0 | V19: =SUM(W19:AA19) -> 0 | AB19: =SUM(AC19:AF19) -> 0 | AG19: =SUM(I19:AF19) -> 0
G20: Американский футбол | H20: 10 | I20: =J20+P20 -> 0 | J20: =SUM(K20:O20) -> 0 | P20: =SUM(Q20:T20) -> 0 | U20: =V20+AB20 -> 0 | V20: =SUM(W20:AA20) -> 0 | AB20: =SUM(AC20:AF20) -> 0 | AG20: =SUM(I20:AF20) -> 0
G21: Армейская высокоточная стрельба | H21: 11 | I21: =J21+P21 -> 0 | J21: =SUM(K21:O21) -> 0 | P21: =SUM(Q21:T21) -> 0 | U21: =V21+AB21 -> 0 | V21: =SUM(W21:AA21) -> 0 | AB21: =SUM(AC21:AF21) -> 0 | AG21: =SUM(I21:AF21) -> 0
G22: Армейский рукопашный бой | H22: 12 | I22: =J22+P22 -> 0 | J22: =SUM(K22:O22) -> 0 | P22: =SUM(Q22:T22) -> 0 | U22: =V22+AB22 -> 0 | V22: =SUM(W22:AA22) -> 0 | AB22: =SUM(AC22:AF22) -> 0 | AG22: =SUM(I22:AF22) -> 0
G23: Армейское тактико-стрелковое многоборье | H23: 13 | I23: =J23+P23 -> 0 | J23: =SUM(K23:O23) -> 0 | P23: =SUM(Q23:T23) -> 0 | U23: =V23+AB23 -> 0 | V23: =SUM(W23:AA23) -> 0 | AB23: =SUM(AC23:AF23) -> 0 | AG23: =SUM(I23:AF23) -> 0
G24: Армрестлинг | H24: 14 | I24: =J24+P24 -> 0 | J24: =SUM(K24:O24) -> 0 | P24: =SUM(Q24:T24) -> 0 | U24: =V24+AB24 -> 0 | V24: =SUM(W24:AA24) -> 0 | AB24: =SUM(AC24:AF24) -> 0 | AG24: =SUM(I24:AF24) -> 0
G25: Бадминтон | H25: 15 | I25: =J25+P25 -> 0 | J25: =SUM(K25:O25) -> 0 | P25: =SUM(Q25:T25) -> 0 | U25: =V25+AB25 -> 0 | V25: =SUM(W25:AA25) -> 0 | AB25: =SUM(AC25:AF25) -> 0 | AG25: =SUM(I25:AF25) -> 0
G26: Баскетбол - всего | H26: 16 | I26: =J26+P26 -> 0 | J26: =SUM(K26:O26) -> 0 | K26: =SUM(K27:K30) -> 0 | L26: =SUM(L27:L30) -> 0 | M26: =SUM(M27:M30) -> 0 | N26: =SUM(N27:N30) -> 0 | O26: =SUM(O27:O30) -> 0 | P26: =SUM(Q26:T26) -> 0 | Q26: =SUM(Q27:Q30) -> 0 | R26: =SUM(R27:R30) -> 0 | S26: =SUM(S27:S30) -> 0 | T26: =SUM(T27:T30) -> 0 | U26: =V26+AB26 -> 0 | V26: =SUM(W26:AA26) -> 0 | W26: =SUM(W27:W30) -> 0 | X26: =SUM(X27:X30) -> 0 | Y26: =SUM(Y27:Y30) -> 0 | Z26: =SUM(Z27:Z30) -> 0 | AA26: =SUM(AA27:AA30) -> 0 | AB26: =SUM(AC26:AF26) -> 0 | AC26: =SUM(AC27:AC30) -> 0 | AD26: =SUM(AD27:AD30) -> 0 | AE26: =SUM(AE27:AE30) -> 0 | AF26: =SUM(AF27:AF30) -> 0 | AG26: =SUM(I26:AF26) -> 0
G27: в том числе: Баскетбол | H27: 17 | I27: =J27+P27 -> 0 | J27: =SUM(K27:O27) -> 0 | P27: =SUM(Q27:T27) -> 0 | U27: =V27+AB27 -> 0 | V27: =SUM(W27:AA27) -> 0 | AB27: =SUM(AC27:AF27) -> 0 | AG27: =SUM(I27:AF27) -> 0
G28: Баскетбол 3х3 | H28: 18 | I28: =J28+P28 -> 0 | J28: =SUM(K28:O28) -> 0 | P28: =SUM(Q28:T28) -> 0 | U28: =V28+AB28 -> 0 | V28: =SUM(W28:AA28) -> 0 | AB28: =SUM(AC28:AF28) -> 0 | AG28: =SUM(I28:AF28) -> 0
G29: Интерактивный баскетбол | H29: 19 | I29: =J29+P29 -> 0 | J29: =SUM(K29:O29) -> 0 | P29: =SUM(Q29:T29) -> 0 | U29: =V29+AB29 -> 0 | V29: =SUM(W29:AA29) -> 0 | AB29: =SUM(AC29:AF29) -> 0 | AG29: =SUM(I29:AF29) -> 0
G30: Иные дисциплины вида спорта "баскетбол" | H30: 20 | I30: =J30+P30 -> 0 | J30: =SUM(K30:O30) -> 0 | P30: =SUM(Q30:T30) -> 0 | U30: =V30+AB30 -> 0 | V30: =SUM(W30:AA30) -> 0 | AB30: =SUM(AC30:AF30) -> 0 | AG30: =SUM(I30:AF30) -> 0
G31: Бейсбол | H31: 21 | I31: =J31+P31 -> 0 | J31: =SUM(K31:O31) -> 0 | P31: =SUM(Q31:T31) -> 0 | U31: =V31+AB31 -> 0 | V31: =SUM(W31:AA31) -> 0 | AB31: =SUM(AC31:AF31) -> 0 | AG31: =SUM(I31:AF31) -> 0
G32: Биатлон | H32: 22 | I32: =J32+P32 -> 0 | J32: =SUM(K32:O32) -> 0 | P32: =SUM(Q32:T32) -> 0 | U32: =V32+AB32 -> 0 | V32: =SUM(W32:AA32) -> 0 | AB32: =SUM(AC32:AF32) -> 0 | AG32: =SUM(I32:AF32) -> 0
G33: Бильярдный спорт | H33: 23 | I33: =J33+P33 -> 0 | J33: =SUM(K33:O33) -> 0 | P33: =SUM(Q33:T33) -> 0 | U33: =V33+AB33 -> 0 | V33: =SUM(W33:AA33) -> 0 | AB33: =SUM(AC33:AF33) -> 0 | AG33: =SUM(I33:AF33) -> 0
G34: Бобслей - всего | H34: 24 | I34: =J34+P34 -> 0 | J34: =SUM(K34:O34) -> 0 | K34: =SUM(K35:K38) -> 0 | L34: =SUM(L35:L38) -> 0 | M34: =SUM(M35:M38) -> 0 | N34: =SUM(N35:N38) -> 0 | O34: =SUM(O35:O38) -> 0 | P34: =SUM(Q34:T34) -> 0 | Q34: =SUM(Q35:Q38) -> 0 | R34: =SUM(R35:R38) -> 0 | S34: =SUM(S35:S38) -> 0 | T34: =SUM(T35:T38) -> 0 | U34: =V34+AB34 -> 0 | V34: =SUM(W34:AA34) -> 0 | W34: =SUM(W35:W38) -> 0 | X34: =SUM(X35:X38) -> 0 | Y34: =SUM(Y35:Y38) -> 0 | Z34: =SUM(Z35:Z38) -> 0 | AA34: =SUM(AA35:AA38) -> 0 | AB34: =SUM(AC34:AF34) -> 0 | AC34: =SUM(AC35:AC38) -> 0 | AD34: =SUM(AD35:AD38) -> 0 | AE34: =SUM(AE35:AE38) -> 0 | AF34: =SUM(AF35:AF38) -> 0 | AG34: =SUM(I34:AF34) -> 0
G35: в том числе: Скелетон | H35: 25 | I35: =J35+P35 -> 0 | J35: =SUM(K35:O35) -> 0 | P35: =SUM(Q35:T35) -> 0 | U35: =V35+AB35 -> 0 | V35: =SUM(W35:AA35) -> 0 | AB35: =SUM(AC35:AF35) -> 0 | AG35: =SUM(I35:AF35) -> 0
G36: Экипаж | H36: 26 | I36: =J36+P36 -> 0 | J36: =SUM(K36:O36) -> 0 | P36: =SUM(Q36:T36) -> 0 | U36: =V36+AB36 -> 0 | V36: =SUM(W36:AA36) -> 0 | AB36: =SUM(AC36:AF36) -> 0 | AG36: =SUM(I36:AF36) -> 0
G37: Монобоб | H37: 27 | I37: =J37+P37 -> 0 | J37: =SUM(K37:O37) -> 0 | P37: =SUM(Q37:T37) -> 0 | U37: =V37+AB37 -> 0 | V37: =SUM(W37:AA37) -> 0 | AB37: =SUM(AC37:AF37) -> 0 | AG37: =SUM(I37:AF37) -> 0
G38: Иные дисциплины вида спорта "бобслей" | H38: 28 | I38: =J38+P38 -> 0 | J38: =SUM(K38:O38) -> 0 | P38: =SUM(Q38:T38) -> 0 | U38: =V38+AB38 -> 0 | V38: =SUM(W38:AA38) -> 0 | AB38: =SUM(AC38:AF38) -> 0 | AG38: =SUM(I38:AF38) -> 0
G39: Бодибилдинг | H39: 29 | I39: =J39+P39 -> 0 | J39: =SUM(K39:O39) -> 0 | P39: =SUM(Q39:T39) -> 0 | U39: =V39+AB39 -> 0 | V39: =SUM(W39:AA39) -> 0 | AB39: =SUM(AC39:AF39) -> 0 | AG39: =SUM(I39:AF39) -> 0
G40: Бокс | H40: 30 | I40: =J40+P40 -> 0 | J40: =SUM(K40:O40) -> 0 | P40: =SUM(Q40:T40) -> 0 | U40: =V40+AB40 -> 0 | V40: =SUM(W40:AA40) -> 0 | AB40: =SUM(AC40:AF40) -> 0 | AG40: =SUM(I40:AF40) -> 0
G41: Борьба на поясах | H41: 31 | I41: =J41+P41 -> 0 | J41: =SUM(K41:O41) -> 0 | P41: =SUM(Q41:T41) -> 0 | U41: =V41+AB41 -> 0 | V41: =SUM(W41:AA41) -> 0 | AB41: =SUM(AC41:AF41) -> 0 | AG41: =SUM(I41:AF41) -> 0
G42: Боулинг | H42: 32 | I42: =J42+P42 -> 0 | J42: =SUM(K42:O42) -> 0 | P42: =SUM(Q42:T42) -> 0 | U42: =V42+AB42 -> 0 | V42: =SUM(W42:AA42) -> 0 | AB42: =SUM(AC42:AF42) -> 0 | AG42: =SUM(I42:AF42) -> 0
G43: Боулспорт | H43: 33 | I43: =J43+P43 -> 0 | J43: =SUM(K43:O43) -> 0 | P43: =SUM(Q43:T43) -> 0 | U43: =V43+AB43 -> 0 | V43: =SUM(W43:AA43) -> 0 | AB43: =SUM(AC43:AF43) -> 0 | AG43: =SUM(I43:AF43) -> 0
G44: Брейкинг | H44: 34 | I44: =J44+P44 -> 0 | J44: =SUM(K44:O44) -> 0 | P44: =SUM(Q44:T44) -> 0 | U44: =V44+AB44 -> 0 | V44: =SUM(W44:AA44) -> 0 | AB44: =SUM(AC44:AF44) -> 0 | AG44: =SUM(I44:AF44) -> 0
G45: Велосипедный спорт - всего | H45: 35 | I45: =J45+P45 -> 0 | J45: =SUM(K45:O45) -> 0 | K45: =SUM(K46:K51) -> 0 | L45: =SUM(L46:L51) -> 0 | M45: =SUM(M46:M51) -> 0 | N45: =SUM(N46:N51) -> 0 | O45: =SUM(O46:O51) -> 0 | P45: =SUM(Q45:T45) -> 0 | Q45: =SUM(Q46:Q51) -> 0 | R45: =SUM(R46:R51) -> 0 | S45: =SUM(S46:S51) -> 0 | T45: =SUM(T46:T51) -> 0 | U45: =V45+AB45 -> 0 | V45: =SUM(W45:AA45) -> 0 | W45: =SUM(W46:W51) -> 0 | X45: =SUM(X46:X51) -> 0 | Y45: =SUM(Y46:Y51) -> 0 | Z45: =SUM(Z46:Z51) -> 0 | AA45: =SUM(AA46:AA51) -> 0 | AB45: =SUM(AC45:AF45) -> 0 | AC45: =SUM(AC46:AC51) -> 0 | AD45: =SUM(AD46:AD51) -> 0 | AE45: =SUM(AE46:AE51) -> 0 | AF45: =SUM(AF46:AF51) -> 0 | AG45: =SUM(I45:AF45) -> 0
G46: в том числе: BMX (гонка, эстафета) | H46: 36 | I46: =J46+P46 -> 0 | J46: =SUM(K46:O46) -> 0 | P46: =SUM(Q46:T46) -> 0 | U46: =V46+AB46 -> 0 | V46: =SUM(W46:AA46) -> 0 | AB46: =SUM(AC46:AF46) -> 0 | AG46: =SUM(I46:AF46) -> 0
G47: BMX - фристайл | H47: 37 | I47: =J47+P47 -> 0 | J47: =SUM(K47:O47) -> 0 | P47: =SUM(Q47:T47) -> 0 | U47: =V47+AB47 -> 0 | V47: =SUM(W47:AA47) -> 0 | AB47: =SUM(AC47:AF47) -> 0 | AG47: =SUM(I47:AF47) -> 0
G48: Маунтинбайк | H48: 38 | I48: =J48+P48 -> 0 | J48: =SUM(K48:O48) -> 0 | P48: =SUM(Q48:T48) -> 0 | U48: =V48+AB48 -> 0 | V48: =SUM(W48:AA48) -> 0 | AB48: =SUM(AC48:AF48) -> 0 | AG48: =SUM(I48:AF48) -> 0
G49: Трек | H49: 39 | I49: =J49+P49 -> 0 | J49: =SUM(K49:O49) -> 0 | P49: =SUM(Q49:T49) -> 0 | U49: =V49+AB49 -> 0 | V49: =SUM(W49:AA49) -> 0 | AB49: =SUM(AC49:AF49) -> 0 | AG49: =SUM(I49:AF49) -> 0
G50: Шоссе | H50: 40 | I50: =J50+P50 -> 0 | J50: =SUM(K50:O50) -> 0 | P50: =SUM(Q50:T50) -> 0 | U50: =V50+AB50 -> 0 | V50: =SUM(W50:AA50) -> 0 | AB50: =SUM(AC50:AF50) -> 0 | AG50: =SUM(I50:AF50) -> 0
G51: Технический симулятор | H51: 41 | I51: =J51+P51 -> 0 | J51: =SUM(K51:O51) -> 0 | P51: =SUM(Q51:T51) -> 0 | U51: =V51+AB51 -> 0 | V51: =SUM(W51:AA51) -> 0 | AB51: =SUM(AC51:AF51) -> 0 | AG51: =SUM(I51:AF51) -> 0
G52: Вертолетный спорт | H52: 42 | I52: =J52+P52 -> 0 | J52: =SUM(K52:O52) -> 0 | P52: =SUM(Q52:T52) -> 0 | U52: =V52+AB52 -> 0 | V52: =SUM(W52:AA52) -> 0 | AB52: =SUM(AC52:AF52) -> 0 | AG52: =SUM(I52:AF52) -> 0
G53: Водное поло - всего | H53: 43 | I53: =J53+P53 -> 0 | J53: =SUM(K53:O53) -> 0 | K53: =SUM(K54:K55) -> 0 | L53: =SUM(L54:L55) -> 0 | M53: =SUM(M54:M55) -> 0 | N53: =SUM(N54:N55) -> 0 | O53: =SUM(O54:O55) -> 0 | P53: =SUM(Q53:T53) -> 0 | Q53: =SUM(Q54:Q55) -> 0 | R53: =SUM(R54:R55) -> 0 | S53: =SUM(S54:S55) -> 0 | T53: =SUM(T54:T55) -> 0 | U53: =V53+AB53 -> 0 | V53: =SUM(W53:AA53) -> 0 | W53: =SUM(W54:W55) -> 0 | X53: =SUM(X54:X55) -> 0 | Y53: =SUM(Y54:Y55) -> 0 | Z53: =SUM(Z54:Z55) -> 0 | AA53: =SUM(AA54:AA55) -> 0 | AB53: =SUM(AC53:AF53) -> 0 | AC53: =SUM(AC54:AC55) -> 0 | AD53: =SUM(AD54:AD55) -> 0 | AE53: =SUM(AE54:AE55) -> 0 | AF53: =SUM(AF54:AF55) -> 0 | AG53: =SUM(I53:AF53) -> 0
G54: в том числе: Водное поло | H54: 44 | I54: =J54+P54 -> 0 | J54: =SUM(K54:O54) -> 0 | P54: =SUM(Q54:T54) -> 0 | U54: =V54+AB54 -> 0 | V54: =SUM(W54:AA54) -> 0 | AB54: =SUM(AC54:AF54) -> 0 | AG54: =SUM(I54:AF54) -> 0
G55: Иные дисциплины вида спорта "водное поло" | H55: 45 | I55: =J55+P55 -> 0 | J55: =SUM(K55:O55) -> 0 | P55: =SUM(Q55:T55) -> 0 | U55: =V55+AB55 -> 0 | V55: =SUM(W55:AA55) -> 0 | AB55: =SUM(AC55:AF55) -> 0 | AG55: =SUM(I55:AF55) -> 0
G56: Воднолыжный спорт | H56: 46 | I56: =J56+P56 -> 0 | J56: =SUM(K56:O56) -> 0 | P56: =SUM(Q56:T56) -> 0 | U56: =V56+AB56 -> 0 | V56: =SUM(W56:AA56) -> 0 | AB56: =SUM(AC56:AF56) -> 0 | AG56: =SUM(I56:AF56) -> 0
G57: Водно-моторный спорт | H57: 47 | I57: =J57+P57 -> 0 | J57: =SUM(K57:O57) -> 0 | P57: =SUM(Q57:T57) -> 0 | U57: =V57+AB57 -> 0 | V57: =SUM(W57:AA57) -> 0 | AB57: =SUM(AC57:AF57) -> 0 | AG57: =SUM(I57:AF57) -> 0
G58: Водно-спасательное многоборье | H58: 48 | I58: =J58+P58 -> 0 | J58: =SUM(K58:O58) -> 0 | P58: =SUM(Q58:T58) -> 0 | U58: =V58+AB58 -> 0 | V58: =SUM(W58:AA58) -> 0 | AB58: =SUM(AC58:AF58) -> 0 | AG58: =SUM(I58:AF58) -> 0
G59: Военно-прикладной спорт | H59: 49 | I59: =J59+P59 -> 0 | J59: =SUM(K59:O59) -> 0 | P59: =SUM(Q59:T59) -> 0 | U59: =V59+AB59 -> 0 | V59: =SUM(W59:AA59) -> 0 | AB59: =SUM(AC59:AF59) -> 0 | AG59: =SUM(I59:AF59) -> 0
G60: Военно-спортивное многоборье | H60: 50 | I60: =J60+P60 -> 0 | J60: =SUM(K60:O60) -> 0 | P60: =SUM(Q60:T60) -> 0 | U60: =V60+AB60 -> 0 | V60: =SUM(W60:AA60) -> 0 | AB60: =SUM(AC60:AF60) -> 0 | AG60: =SUM(I60:AF60) -> 0
G61: Воздухоплавательный спорт | H61: 51 | I61: =J61+P61 -> 0 | J61: =SUM(K61:O61) -> 0 | P61: =SUM(Q61:T61) -> 0 | U61: =V61+AB61 -> 0 | V61: =SUM(W61:AA61) -> 0 | AB61: =SUM(AC61:AF61) -> 0 | AG61: =SUM(I61:AF61) -> 0
G62: Воздушная гимнастика | H62: 52 | I62: =J62+P62 -> 0 | J62: =SUM(K62:O62) -> 0 | P62: =SUM(Q62:T62) -> 0 | U62: =V62+AB62 -> 0 | V62: =SUM(W62:AA62) -> 0 | AB62: =SUM(AC62:AF62) -> 0 | AG62: =SUM(I62:AF62) -> 0
G63: Воздушно-силовая атлетика | H63: 53 | I63: =J63+P63 -> 0 | J63: =SUM(K63:O63) -> 0 | P63: =SUM(Q63:T63) -> 0 | U63: =V63+AB63 -> 0 | V63: =SUM(W63:AA63) -> 0 | AB63: =SUM(AC63:AF63) -> 0 | AG63: =SUM(I63:AF63) -> 0
G64: Волейбол - всего | H64: 54 | I64: =J64+P64 -> 0 | J64: =SUM(K64:O64) -> 0 | K64: =SUM(K65:K67) -> 0 | L64: =SUM(L65:L67) -> 0 | M64: =SUM(M65:M67) -> 0 | N64: =SUM(N65:N67) -> 0 | O64: =SUM(O65:O67) -> 0 | P64: =SUM(Q64:T64) -> 0 | Q64: =SUM(Q65:Q67) -> 0 | R64: =SUM(R65:R67) -> 0 | S64: =SUM(S65:S67) -> 0 | T64: =SUM(T65:T67) -> 0 | U64: =V64+AB64 -> 0 | V64: =SUM(W64:AA64) -> 0 | W64: =SUM(W65:W67) -> 0 | X64: =SUM(X65:X67) -> 0 | Y64: =SUM(Y65:Y67) -> 0 | Z64: =SUM(Z65:Z67) -> 0 | AA64: =SUM(AA65:AA67) -> 0 | AB64: =SUM(AC64:AF64) -> 0 | AC64: =SUM(AC65:AC67) -> 0 | AD64: =SUM(AD65:AD67) -> 0 | AE64: =SUM(AE65:AE67) -> 0 | AF64: =SUM(AF65:AF67) -> 0 | AG64: =SUM(I64:AF64) -> 0
G65: в том числе: Волейбол | H65: 55 | I65: =J65+P65 -> 0 | J65: =SUM(K65:O65) -> 0 | P65: =SUM(Q65:T65) -> 0 | U65: =V65+AB65 -> 0 | V65: =SUM(W65:AA65) -> 0 | AB65: =SUM(AC65:AF65) -> 0 | AG65: =SUM(I65:AF65) -> 0
G66: Пляжный волейбол | H66: 56 | I66: =J66+P66 -> 0 | J66: =SUM(K66:O66) -> 0 | P66: =SUM(Q66:T66) -> 0 | U66: =V66+AB66 -> 0 | V66: =SUM(W66:AA66) -> 0 | AB66: =SUM(AC66:AF66) -> 0 | AG66: =SUM(I66:AF66) -> 0
G67: Волейбол на снегу | H67: 57 | I67: =J67+P67 -> 0 | J67: =SUM(K67:O67) -> 0 | P67: =SUM(Q67:T67) -> 0 | U67: =V67+AB67 -> 0 | V67: =SUM(W67:AA67) -> 0 | AB67: =SUM(AC67:AF67) -> 0 | AG67: =SUM(I67:AF67) -> 0
G68: Восточное боевое единоборство | H68: 58 | I68: =J68+P68 -> 0 | J68: =SUM(K68:O68) -> 0 | P68: =SUM(Q68:T68) -> 0 | U68: =V68+AB68 -> 0 | V68: =SUM(W68:AA68) -> 0 | AB68: =SUM(AC68:AF68) -> 0 | AG68: =SUM(I68:AF68) -> 0
G69: Всестилевое каратэ | H69: 59 | I69: =J69+P69 -> 0 | J69: =SUM(K69:O69) -> 0 | P69: =SUM(Q69:T69) -> 0 | U69: =V69+AB69 -> 0 | V69: =SUM(W69:AA69) -> 0 | AB69: =SUM(AC69:AF69) -> 0 | AG69: =SUM(I69:AF69) -> 0
G70: Гандбол - всего | H70: 60 | I70: =J70+P70 -> 0 | J70: =SUM(K70:O70) -> 0 | K70: =SUM(K71:K72) -> 0 | L70: =SUM(L71:L72) -> 0 | M70: =SUM(M71:M72) -> 0 | N70: =SUM(N71:N72) -> 0 | O70: =SUM(O71:O72) -> 0 | P70: =SUM(Q70:T70) -> 0 | Q70: =SUM(Q71:Q72) -> 0 | R70: =SUM(R71:R72) -> 0 | S70: =SUM(S71:S72) -> 0 | T70: =SUM(T71:T72) -> 0 | U70: =V70+AB70 -> 0 | V70: =SUM(W70:AA70) -> 0 | W70: =SUM(W71:W72) -> 0 | X70: =SUM(X71:X72) -> 0 | Y70: =SUM(Y71:Y72) -> 0 | Z70: =SUM(Z71:Z72) -> 0 | AA70: =SUM(AA71:AA72) -> 0 | AB70: =SUM(AC70:AF70) -> 0 | AC70: =SUM(AC71:AC72) -> 0 | AD70: =SUM(AD71:AD72) -> 0 | AE70: =SUM(AE71:AE72) -> 0 | AF70: =SUM(AF71:AF72) -> 0 | AG70: =SUM(I70:AF70) -> 0
G71: в том числе: Гандбол | H71: 61 | I71: =J71+P71 -> 0 | J71: =SUM(K71:O71) -> 0 | P71: =SUM(Q71:T71) -> 0 | U71: =V71+AB71 -> 0 | V71: =SUM(W71:AA71) -> 0 | AB71: =SUM(AC71:AF71) -> 0 | AG71: =SUM(I71:AF71) -> 0
G72: Пляжный гандбол | H72: 62 | I72: =J72+P72 -> 0 | J72: =SUM(K72:O72) -> 0 | P72: =SUM(Q72:T72) -> 0 | U72: =V72+AB72 -> 0 | V72: =SUM(W72:AA72) -> 0 | AB72: =SUM(AC72:AF72) -> 0 | AG72: =SUM(I72:AF72) -> 0
G73: Гиревой спорт | H73: 63 | I73: =J73+P73 -> 0 | J73: =SUM(K73:O73) -> 0 | P73: =SUM(Q73:T73) -> 0 | U73: =V73+AB73 -> 0 | V73: =SUM(W73:AA73) -> 0 | AB73: =SUM(AC73:AF73) -> 0 | AG73: =SUM(I73:AF73) -> 0
G74: Го | H74: 64 | I74: =J74+P74 -> 0 | J74: =SUM(K74:O74) -> 0 | P74: =SUM(Q74:T74) -> 0 | U74: =V74+AB74 -> 0 | V74: =SUM(W74:AA74) -> 0 | AB74: =SUM(AC74:AF74) -> 0 | AG74: =SUM(I74:AF74) -> 0
G75: Гольф | H75: 65 | I75: =J75+P75 -> 0 | J75: =SUM(K75:O75) -> 0 | P75: =SUM(Q75:T75) -> 0 | U75: =V75+AB75 -> 0 | V75: =SUM(W75:AA75) -> 0 | AB75: =SUM(AC75:AF75) -> 0 | AG75: =SUM(I75:AF75) -> 0
G76: Гонки дронов (беспилотных воздушных судов) - всего | H76: 66 | I76: =J76+P76 -> 0 | J76: =SUM(K76:O76) -> 0 | K76: =SUM(K77:K80) -> 0 | L76: =SUM(L77:L80) -> 0 | M76: =SUM(M77:M80) -> 0 | N76: =SUM(N77:N80) -> 0 | O76: =SUM(O77:O80) -> 0 | P76: =SUM(Q76:T76) -> 0 | Q76: =SUM(Q77:Q80) -> 0 | R76: =SUM(R77:R80) -> 0 | S76: =SUM(S77:S80) -> 0 | T76: =SUM(T77:T80) -> 0 | U76: =V76+AB76 -> 0 | V76: =SUM(W76:AA76) -> 0 | W76: =SUM(W77:W80) -> 0 | X76: =SUM(X77:X80) -> 0 | Y76: =SUM(Y77:Y80) -> 0 | Z76: =SUM(Z77:Z80) -> 0 | AA76: =SUM(AA77:AA80) -> 0 | AB76: =SUM(AC76:AF76) -> 0 | AC76: =SUM(AC77:AC80) -> 0 | AD76: =SUM(AD77:AD80) -> 0 | AE76: =SUM(AE77:AE80) -> 0 | AF76: =SUM(AF77:AF80) -> 0 | AG76: =SUM(I76:AF76) -> 0
G77: в том числе: Класс 75 мм | H77: 67 | I77: =J77+P77 -> 0 | J77: =SUM(K77:O77) -> 0 | P77: =SUM(Q77:T77) -> 0 | U77: =V77+AB77 -> 0 | V77: =SUM(W77:AA77) -> 0 | AB77: =SUM(AC77:AF77) -> 0 | AG77: =SUM(I77:AF77) -> 0
G78: Класс 200 мм | H78: 68 | I78: =J78+P78 -> 0 | J78: =SUM(K78:O78) -> 0 | P78: =SUM(Q78:T78) -> 0 | U78: =V78+AB78 -> 0 | V78: =SUM(W78:AA78) -> 0 | AB78: =SUM(AC78:AF78) -> 0 | AG78: =SUM(I78:AF78) -> 0
G79: Класс 330 мм | H79: 69 | I79: =J79+P79 -> 0 | J79: =SUM(K79:O79) -> 0 | P79: =SUM(Q79:T79) -> 0 | U79: =V79+AB79 -> 0 | V79: =SUM(W79:AA79) -> 0 | AB79: =SUM(AC79:AF79) -> 0 | AG79: =SUM(I79:AF79) -> 0
G80: Технический симулятор | H80: 70 | I80: =J80+P80 -> 0 | J80: =SUM(K80:O80) -> 0 | P80: =SUM(Q80:T80) -> 0 | U80: =V80+AB80 -> 0 | V80: =SUM(W80:AA80) -> 0 | AB80: =SUM(AC80:AF80) -> 0 | AG80: =SUM(I80:AF80) -> 0
G81: Гонки на охотничьих лыжах | H81: 71 | I81: =J81+P81 -> 0 | J81: =SUM(K81:O81) -> 0 | P81: =SUM(Q81:T81) -> 0 | U81: =V81+AB81 -> 0 | V81: =SUM(W81:AA81) -> 0 | AB81: =SUM(AC81:AF81) -> 0 | AG81: =SUM(I81:AF81) -> 0
G82: Гонки с препятствиями | H82: 72 | I82: =J82+P82 -> 0 | J82: =SUM(K82:O82) -> 0 | P82: =SUM(Q82:T82) -> 0 | U82: =V82+AB82 -> 0 | V82: =SUM(W82:AA82) -> 0 | AB82: =SUM(AC82:AF82) -> 0 | AG82: =SUM(I82:AF82) -> 0
G83: Горнолыжный спорт | H83: 73 | I83: =J83+P83 -> 0 | J83: =SUM(K83:O83) -> 0 | P83: =SUM(Q83:T83) -> 0 | U83: =V83+AB83 -> 0 | V83: =SUM(W83:AA83) -> 0 | AB83: =SUM(AC83:AF83) -> 0 | AG83: =SUM(I83:AF83) -> 0
G84: Городошный спорт | H84: 74 | I84: =J84+P84 -> 0 | J84: =SUM(K84:O84) -> 0 | P84: =SUM(Q84:T84) -> 0 | U84: =V84+AB84 -> 0 | V84: =SUM(W84:AA84) -> 0 | AB84: =SUM(AC84:AF84) -> 0 | AG84: =SUM(I84:AF84) -> 0
G85: Гребля на байдарках и каноэ | H85: 75 | I85: =J85+P85 -> 0 | J85: =SUM(K85:O85) -> 0 | P85: =SUM(Q85:T85) -> 0 | U85: =V85+AB85 -> 0 | V85: =SUM(W85:AA85) -> 0 | AB85: =SUM(AC85:AF85) -> 0 | AG85: =SUM(I85:AF85) -> 0
G86: Гребля на шлюпках | H86: 76 | I86: =J86+P86 -> 0 | J86: =SUM(K86:O86) -> 0 | P86: =SUM(Q86:T86) -> 0 | U86: =V86+AB86 -> 0 | V86: =SUM(W86:AA86) -> 0 | AB86: =SUM(AC86:AF86) -> 0 | AG86: =SUM(I86:AF86) -> 0
G87: Гребной слалом | H87: 77 | I87: =J87+P87 -> 0 | J87: =SUM(K87:O87) -> 0 | P87: =SUM(Q87:T87) -> 0 | U87: =V87+AB87 -> 0 | V87: =SUM(W87:AA87) -> 0 | AB87: =SUM(AC87:AF87) -> 0 | AG87: =SUM(I87:AF87) -> 0
G88: Гребной спорт - всего | H88: 78 | I88: =J88+P88 -> 0 | J88: =SUM(K88:O88) -> 0 | K88: =SUM(K89:K90) -> 0 | L88: =SUM(L89:L90) -> 0 | M88: =SUM(M89:M90) -> 0 | N88: =SUM(N89:N90) -> 0 | O88: =SUM(O89:O90) -> 0 | P88: =SUM(Q88:T88) -> 0 | Q88: =SUM(Q89:Q90) -> 0 | R88: =SUM(R89:R90) -> 0 | S88: =SUM(S89:S90) -> 0 | T88: =SUM(T89:T90) -> 0 | U88: =V88+AB88 -> 0 | V88: =SUM(W88:AA88) -> 0 | W88: =SUM(W89:W90) -> 0 | X88: =SUM(X89:X90) -> 0 | Y88: =SUM(Y89:Y90) -> 0 | Z88: =SUM(Z89:Z90) -> 0 | AA88: =SUM(AA89:AA90) -> 0 | AB88: =SUM(AC88:AF88) -> 0 | AC88: =SUM(AC89:AC90) -> 0 | AD88: =SUM(AD89:AD90) -> 0 | AE88: =SUM(AE89:AE90) -> 0 | AF88: =SUM(AF89:AF90) -> 0 | AG88: =SUM(I88:AF88) -> 0
G89: в том числе: Академическая гребля | H89: 79 | I89: =J89+P89 -> 0 | J89: =SUM(K89:O89) -> 0 | P89: =SUM(Q89:T89) -> 0 | U89: =V89+AB89 -> 0 | V89: =SUM(W89:AA89) -> 0 | AB89: =SUM(AC89:AF89) -> 0 | AG89: =SUM(I89:AF89) -> 0
G90: Иные дисциплины вида спорта "гребной спорт" | H90: 80 | I90: =J90+P90 -> 0 | J90: =SUM(K90:O90) -> 0 | P90: =SUM(Q90:T90) -> 0 | U90: =V90+AB90 -> 0 | V90: =SUM(W90:AA90) -> 0 | AB90: =SUM(AC90:AF90) -> 0 | AG90: =SUM(I90:AF90) -> 0
G91: Гребно-парусное двоеборье | H91: 81 | I91: =J91+P91 -> 0 | J91: =SUM(K91:O91) -> 0 | P91: =SUM(Q91:T91) -> 0 | U91: =V91+AB91 -> 0 | V91: =SUM(W91:AA91) -> 0 | AB91: =SUM(AC91:AF91) -> 0 | AG91: =SUM(I91:AF91) -> 0
G92: Дартс | H92: 82 | I92: =J92+P92 -> 0 | J92: =SUM(K92:O92) -> 0 | P92: =SUM(Q92:T92) -> 0 | U92: =V92+AB92 -> 0 | V92: =SUM(W92:AA92) -> 0 | AB92: =SUM(AC92:AF92) -> 0 | AG92: =SUM(I92:AF92) -> 0
G93: Джиу-джитсу | H93: 83 | I93: =J93+P93 -> 0 | J93: =SUM(K93:O93) -> 0 | P93: =SUM(Q93:T93) -> 0 | U93: =V93+AB93 -> 0 | V93: =SUM(W93:AA93) -> 0 | AB93: =SUM(AC93:AF93) -> 0 | AG93: =SUM(I93:AF93) -> 0
G94: Джутайдо | H94: 84 | I94: =J94+P94 -> 0 | J94: =SUM(K94:O94) -> 0 | P94: =SUM(Q94:T94) -> 0 | U94: =V94+AB94 -> 0 | V94: =SUM(W94:AA94) -> 0 | AB94: =SUM(AC94:AF94) -> 0 | AG94: =SUM(I94:AF94) -> 0
G95: Дзюдо | H95: 85 | I95: =J95+P95 -> 0 | J95: =SUM(K95:O95) -> 0 | P95: =SUM(Q95:T95) -> 0 | U95: =V95+AB95 -> 0 | V95: =SUM(W95:AA95) -> 0 | AB95: =SUM(AC95:AF95) -> 0 | AG95: =SUM(I95:AF95) -> 0
G96: Ездовой спорт | H96: 86 | I96: =J96+P96 -> 0 | J96: =SUM(K96:O96) -> 0 | P96: =SUM(Q96:T96) -> 0 | U96: =V96+AB96 -> 0 | V96: =SUM(W96:AA96) -> 0 | AB96: =SUM(AC96:AF96) -> 0 | AG96: =SUM(I96:AF96) -> 0
G97: Зимнее плавание | H97: 87 | I97: =J97+P97 -> 0 | J97: =SUM(K97:O97) -> 0 | P97: =SUM(Q97:T97) -> 0 | U97: =V97+AB97 -> 0 | V97: =SUM(W97:AA97) -> 0 | AB97: =SUM(AC97:AF97) -> 0 | AG97: =SUM(I97:AF97) -> 0
G98: Капоэйра | H98: 88 | I98: =J98+P98 -> 0 | J98: =SUM(K98:O98) -> 0 | P98: =SUM(Q98:T98) -> 0 | U98: =V98+AB98 -> 0 | V98: =SUM(W98:AA98) -> 0 | AB98: =SUM(AC98:AF98) -> 0 | AG98: =SUM(I98:AF98) -> 0
G99: Каратэ | H99: 89 | I99: =J99+P99 -> 0 | J99: =SUM(K99:O99) -> 0 | P99: =SUM(Q99:T99) -> 0 | U99: =V99+AB99 -> 0 | V99: =SUM(W99:AA99) -> 0 | AB99: =SUM(AC99:AF99) -> 0 | AG99: =SUM(I99:AF99) -> 0
G100: Кендо | H100: 90 | I100: =J100+P100 -> 0 | J100: =SUM(K100:O100) -> 0 | P100: =SUM(Q100:T100) -> 0 | U100: =V100+AB100 -> 0 | V100: =SUM(W100:AA100) -> 0 | AB100: =SUM(AC100:AF100) -> 0 | AG100: =SUM(I100:AF100) -> 0
G101: Керешу | H101: 91 | I101: =J101+P101 -> 0 | J101: =SUM(K101:O101) -> 0 | P101: =SUM(Q101:T101) -> 0 | U101: =V101+AB101 -> 0 | V101: =SUM(W101:AA101) -> 0 | AB101: =SUM(AC101:AF101) -> 0 | AG101: =SUM(I101:AF101) -> 0
G102: Кёрлинг - всего | H102: 92 | I102: =J102+P102 -> 0 | J102: =SUM(K102:O102) -> 0 | K102: =SUM(K103:K104) -> 0 | L102: =SUM(L103:L104) -> 0 | M102: =SUM(M103:M104) -> 0 | N102: =SUM(N103:N104) -> 0 | O102: =SUM(O103:O104) -> 0 | P102: =SUM(Q102:T102) -> 0 | Q102: =SUM(Q103:Q104) -> 0 | R102: =SUM(R103:R104) -> 0 | S102: =SUM(S103:S104) -> 0 | T102: =SUM(T103:T104) -> 0 | U102: =V102+AB102 -> 0 | V102: =SUM(W102:AA102) -> 0 | W102: =SUM(W103:W104) -> 0 | X102: =SUM(X103:X104) -> 0 | Y102: =SUM(Y103:Y104) -> 0 | Z102: =SUM(Z103:Z104) -> 0 | AA102: =SUM(AA103:AA104) -> 0 | AB102: =SUM(AC102:AF102) -> 0 | AC102: =SUM(AC103:AC104) -> 0 | AD102: =SUM(AD103:AD104) -> 0 | AE102: =SUM(AE103:AE104) -> 0 | AF102: =SUM(AF103:AF104) -> 0 | AG102: =SUM(I102:AF102) -> 0
G103: в том числе: Кёрлинг | H103: 93 | I103: =J103+P103 -> 0 | J103: =SUM(K103:O103) -> 0 | P103: =SUM(Q103:T103) -> 0 | U103: =V103+AB103 -> 0 | V103: =SUM(W103:AA103) -> 0 | AB103: =SUM(AC103:AF103) -> 0 | AG103: =SUM(I103:AF103) -> 0
G104: Кёрлинг - смешанные пары | H104: 94 | I104: =J104+P104 -> 0 | J104: =SUM(K104:O104) -> 0 | P104: =SUM(Q104:T104) -> 0 | U104: =V104+AB104 -> 0 | V104: =SUM(W104:AA104) -> 0 | AB104: =SUM(AC104:AF104) -> 0 | AG104: =SUM(I104:AF104) -> 0
...

Sheet Раздел 5
G4: Раздел V. Кандидаты в спортивные сборные команды Российской Федерации, человек
G5: Виды спорта | H5: № строки | I5: Из численности обучающихся и спортсменов, спортсменов-инструкторов на ставках (гр. 5 раздела II и стр. 05 раздела IX) – кандидаты, состоящие в списках спортивных сборных команд | S5: Кандидаты, подготовленные в отчетном периоде
I6: Итого | J6: Юношеский состав | M6: Юниорский состав | P6: Основной состав | S6: Итого | T6: Юношеский состав | W6: Юниорский состав | Z6: Основной состав
J8: Всего по юношескому составу | K8: в том числе: | M8: Всего по юниорскому составу | N8: в том числе: | P8: Всего по основному составу | Q8: в том числе: | T8: Всего подготовлено по юношескому составу | U8: в том числе: | W8: Всего подготовлено по юниорскому составу | X8: в том числе: | Z8: Всего подготовлено по основному составу | AA8: в том числе:
K9: основной | L9: резерв | N9: основной | O9: резерв | Q9: основной | R9: резерв | U9: основной | V9: резерв | X9: основной | Y9: резерв | AA9: основной | AB9: резерв
A10: ='Раздел 0'!M27 -> 0 | B10: ='Раздел 1'!D15 -> 0 | C10: {=_xlfn.IFS(SUM('Раздел 1'!$D$5:$D$6)>0,"ФКиС",SUM('Раздел 1'!$D$7:$D$8)>0,"Образование",SUM('Раздел 1'!$D$9:$D$10)>0,"Другая")} -> ФКиС | D10: {=_xlfn.IFS(SUM('Раздел 1'!$E$12)>0,"СШ",SUM('Раздел 1'!$F$12)>0,"СШОР",SUM('Раздел 1'!$G$12)>0,"УОР",SUM('Раздел 1'!$H$12)>0,"ЦСП",SUM('Раздел 1'!$I$12)>0,"ДРУГИЕ",SUM('Раздел 1'!$E$13)>0,"ОСП СШ",SUM('Раздел 1'!$F$13)>0,"ОСП СШОР",SUM('Раздел 1'!$I$13)>0,"ОСП ДРУГИЕ")} -> ЦСП | E10: =IF(SUM('Раздел 1'!$D$12)>0,SUM('Раздел 1'!$D$13),"") -> 0 | F10: {=_xlfn.IFS(SUM('Раздел 1'!$D$19)>0,"РФ",SUM('Раздел 1'!$E$19)>0,"СУБЪЕКТ",SUM('Раздел 1'!$F$19:$G$19)>0,"МУНИЦИПАЛ",SUM('Раздел 1'!$H$19:$I$19)>0,"ИНЫЕ")} -> #N/A | G10: 1 | H10: 2 | I10: 3 | J10: 4 | K10: 5 | L10: 6 | M10: 7 | N10: 8 | O10: 9 | P10: 10 | Q10: 11 | R10: 12 | S10: 13 | T10: 14 | U10: 15 | V10: 16 | W10: 17 | X10: 18 | Y10: 19 | Z10: 20 | AA10: 21 | AB10: 22 | AC10: 23
G11: Авиамодельный спорт | H11: 01 | I11: =J11+M11+P11 -> 0 | J11: =K11+L11 -> 0 | M11: =N11+O11 -> 0 | P11: =Q11+R11 -> 0 | S11: =T11+W11+Z11 -> 0 | T11: =U11+V11 -> 0 | W11: =X11+Y11 -> 0 | Z11: =AA11+AB11 -> 0 | AC11: =SUM(I11:AB11) -> 0
G12: Авиационные гонки | H12: 02 | I12: =J12+M12+P12 -> 0 | J12: =K12+L12 -> 0 | M12: =N12+O12 -> 0 | P12: =Q12+R12 -> 0 | S12: =T12+W12+Z12 -> 0 | T12: =U12+V12 -> 0 | W12: =X12+Y12 -> 0 | Z12: =AA12+AB12 -> 0 | AC12: =SUM(I12:AB12) -> 0
G13: Автомобильный спорт | H13: 03 | I13: =J13+M13+P13 -> 0 | J13: =K13+L13 -> 0 | M13: =N13+O13 -> 0 | P13: =Q13+R13 -> 0 | S13: =T13+W13+Z13 -> 0 | T13: =U13+V13 -> 0 | W13: =X13+Y13 -> 0 | Z13: =AA13+AB13 -> 0 | AC13: =SUM(I13:AB13) -> 0
G14: Автомодельный спорт | H14: 04 | I14: =J14+M14+P14 -> 0 | J14: =K14+L14 -> 0 | M14: =N14+O14 -> 0 | P14: =Q14+R14 -> 0 | S14: =T14+W14+Z14 -> 0 | T14: =U14+V14 -> 0 | W14: =X14+Y14 -> 0 | Z14: =AA14+AB14 -> 0 | AC14: =SUM(I14:AB14) -> 0
G15: Айкидо | H15: 05 | I15: =J15+M15+P15 -> 0 | J15: =K15+L15 -> 0 | M15: =N15+O15 -> 0 | P15: =Q15+R15 -> 0 | S15: =T15+W15+Z15 -> 0 | T15: =U15+V15 -> 0 | W15: =X15+Y15 -> 0 | Z15: =AA15+AB15 -> 0 | AC15: =SUM(I15:AB15) -> 0
G16: Акробатический рок-н-ролл | H16: 06 | I16: =J16+M16+P16 -> 0 | J16: =K16+L16 -> 0 | M16: =N16+O16 -> 0 | P16: =Q16+R16 -> 0 | S16: =T16+W16+Z16 -> 0 | T16: =U16+V16 -> 0 | W16: =X16+Y16 -> 0 | Z16: =AA16+AB16 -> 0 | AC16: =SUM(I16:AB16) -> 0
G17: Альпинизм - всего | H17: 07 | I17: =J17+M17+P17 -> 0 | J17: =K17+L17 -> 0 | K17: =SUM(K18:K19) -> 0 | L17: =SUM(L18:L19) -> 0 | M17: =N17+O17 -> 0 | N17: =SUM(N18:N19) -> 0 | O17: =SUM(O18:O19) -> 0 | P17: =Q17+R17 -> 0 | Q17: =SUM(Q18:Q19) -> 0 | R17: =SUM(R18:R19) -> 0 | S17: =T17+W17+Z17 -> 0 | T17: =U17+V17 -> 0 | U17: =SUM(U18:U19) -> 0 | V17: =SUM(V18:V19) -> 0 | W17: =X17+Y17 -> 0 | X17: =SUM(X18:X19) -> 0 | Y17: =SUM(Y18:Y19) -> 0 | Z17: =AA17+AB17 -> 0 | AA17: =SUM(AA18:AA19) -> 0 | AB17: =SUM(AB18:AB19) -> 0 | AC17: =SUM(I17:AB17) -> 0
G18: в том числе: Ски-альпинизм | H18: 08 | I18: =J18+M18+P18 -> 0 | J18: =K18+L18 -> 0 | M18: =N18+O18 -> 0 | P18: =Q18+R18 -> 0 | S18: =T18+W18+Z18 -> 0 | T18: =U18+V18 -> 0 | W18: =X18+Y18 -> 0 | Z18: =AA18+AB18 -> 0 | AC18: =SUM(I18:AB18) -> 0
G19: Иные дисциплины вида спорта "альпинизм" | H19: 09 | I19: =J19+M19+P19 -> 0 | J19: =K19+L19 -> 0 | M19: =N19+O19 -> 0 | P19: =Q19+R19 -> 0 | S19: =T19+W19+Z19 -> 0 | T19: =U19+V19 -> 0 | W19: =X19+Y19 -> 0 | Z19: =AA19+AB19 -> 0 | AC19: =SUM(I19:AB19) -> 0
G20: Американский футбол | H20: 10 | I20: =J20+M20+P20 -> 0 | J20: =K20+L20 -> 0 | M20: =N20+O20 -> 0 | P20: =Q20+R20 -> 0 | S20: =T20+W20+Z20 -> 0 | T20: =U20+V20 -> 0 | W20: =X20+Y20 -> 0 | Z20: =AA20+AB20 -> 0 | AC20: =SUM(I20:AB20) -> 0
G21: Армейская высокоточная стрельба | H21: 11 | I21: =J21+M21+P21 -> 0 | J21: =K21+L21 -> 0 | M21: =N21+O21 -> 0 | P21: =Q21+R21 -> 0 | S21: =T21+W21+Z21 -> 0 | T21: =U21+V21 -> 0 | W21: =X21+Y21 -> 0 | Z21: =AA21+AB21 -> 0 | AC21: =SUM(I21:AB21) -> 0
G22: Армейский рукопашный бой | H22: 12 | I22: =J22+M22+P22 -> 0 | J22: =K22+L22 -> 0 | M22: =N22+O22 -> 0 | P22: =Q22+R22 -> 0 | S22: =T22+W22+Z22 -> 0 | T22: =U22+V22 -> 0 | W22: =X22+Y22 -> 0 | Z22: =AA22+AB22 -> 0 | AC22: =SUM(I22:AB22) -> 0
G23: Армейское тактико-стрелковое многоборье | H23: 13 | I23: =J23+M23+P23 -> 0 | J23: =K23+L23 -> 0 | M23: =N23+O23 -> 0 | P23: =Q23+R23 -> 0 | S23: =T23+W23+Z23 -> 0 | T23: =U23+V23 -> 0 | W23: =X23+Y23 -> 0 | Z23: =AA23+AB23 -> 0 | AC23: =SUM(I23:AB23) -> 0
G24: Армрестлинг | H24: 14 | I24: =J24+M24+P24 -> 0 | J24: =K24+L24 -> 0 | M24: =N24+O24 -> 0 | P24: =Q24+R24 -> 0 | S24: =T24+W24+Z24 -> 0 | T24: =U24+V24 -> 0 | W24: =X24+Y24 -> 0 | Z24: =AA24+AB24 -> 0 | AC24: =SUM(I24:AB24) -> 0
G25: Бадминтон | H25: 15 | I25: =J25+M25+P25 -> 0 | J25: =K25+L25 -> 0 | M25: =N25+O25 -> 0 | P25: =Q25+R25 -> 0 | S25: =T25+W25+Z25 -> 0 | T25: =U25+V25 -> 0 | W25: =X25+Y25 -> 0 | Z25: =AA25+AB25 -> 0 | AC25: =SUM(I25:AB25) -> 0
G26: Баскетбол - всего | H26: 16 | I26: =J26+M26+P26 -> 0 | J26: =K26+L26 -> 0 | K26: =SUM(K27:K30) -> 0 | L26: =SUM(L27:L30) -> 0 | M26: =N26+O26 -> 0 | N26: =SUM(N27:N30) -> 0 | O26: =SUM(O27:O30) -> 0 | P26: =Q26+R26 -> 0 | Q26: =SUM(Q27:Q30) -> 0 | R26: =SUM(R27:R30) -> 0 | S26: =T26+W26+Z26 -> 0 | T26: =U26+V26 -> 0 | U26: =SUM(U27:U30) -> 0 | V26: =SUM(V27:V30) -> 0 | W26: =X26+Y26 -> 0 | X26: =SUM(X27:X30) -> 0 | Y26: =SUM(Y27:Y30) -> 0 | Z26: =AA26+AB26 -> 0 | AA26: =SUM(AA27:AA30) -> 0 | AB26: =SUM(AB27:AB30) -> 0 | AC26: =SUM(I26:AB26) -> 0
G27: в том числе: Баскетбол | H27: 17 | I27: =J27+M27+P27 -> 0 | J27: =K27+L27 -> 0 | M27: =N27+O27 -> 0 | P27: =Q27+R27 -> 0 | S27: =T27+W27+Z27 -> 0 | T27: =U27+V27 -> 0 | W27: =X27+Y27 -> 0 | Z27: =AA27+AB27 -> 0 | AC27: =SUM(I27:AB27) -> 0
G28: Баскетбол 3х3 | H28: 18 | I28: =J28+M28+P28 -> 0 | J28: =K28+L28 -> 0 | M28: =N28+O28 -> 0 | P28: =Q28+R28 -> 0 | S28: =T28+W28+Z28 -> 0 | T28: =U28+V28 -> 0 | W28: =X28+Y28 -> 0 | Z28: =AA28+AB28 -> 0 | AC28: =SUM(I28:AB28) -> 0
G29: Интерактивный баскетбол | H29: 19 | I29: =J29+M29+P29 -> 0 | J29: =K29+L29 -> 0 | M29: =N29+O29 -> 0 | P29: =Q29+R29 -> 0 | S29: =T29+W29+Z29 -> 0 | T29: =U29+V29 -> 0 | W29: =X29+Y29 -> 0 | Z29: =AA29+AB29 -> 0 | AC29: =SUM(I29:AB29) -> 0
G30: Иные дисциплины вида спорта "баскетбол" | H30: 20 | I30: =J30+M30+P30 -> 0 | J30: =K30+L30 -> 0 | M30: =N30+O30 -> 0 | P30: =Q30+R30 -> 0 | S30: =T30+W30+Z30 -> 0 | T30: =U30+V30 -> 0 | W30: =X30+Y30 -> 0 | Z30: =AA30+AB30 -> 0 | AC30: =SUM(I30:AB30) -> 0
G31: Бейсбол | H31: 21 | I31: =J31+M31+P31 -> 0 | J31: =K31+L31 -> 0 | M31: =N31+O31 -> 0 | P31: =Q31+R31 -> 0 | S31: =T31+W31+Z31 -> 0 | T31: =U31+V31 -> 0 | W31: =X31+Y31 -> 0 | Z31: =AA31+AB31 -> 0 | AC31: =SUM(I31:AB31) -> 0
G32: Биатлон | H32: 22 | I32: =J32+M32+P32 -> 0 | J32: =K32+L32 -> 0 | M32: =N32+O32 -> 0 | P32: =Q32+R32 -> 0 | S32: =T32+W32+Z32 -> 0 | T32: =U32+V32 -> 0 | W32: =X32+Y32 -> 0 | Z32: =AA32+AB32 -> 0 | AC32: =SUM(I32:AB32) -> 0
G33: Бильярдный спорт | H33: 23 | I33: =J33+M33+P33 -> 0 | J33: =K33+L33 -> 0 | M33: =N33+O33 -> 0 | P33: =Q33+R33 -> 0 | S33: =T33+W33+Z33 -> 0 | T33: =U33+V33 -> 0 | W33: =X33+Y33 -> 0 | Z33: =AA33+AB33 -> 0 | AC33: =SUM(I33:AB33) -> 0
G34: Бобслей - всего | H34: 24 | I34: =J34+M34+P34 -> 0 | J34: =K34+L34 -> 0 | K34: =SUM(K35:K38) -> 0 | L34: =SUM(L35:L38) -> 0 | M34: =N34+O34 -> 0 | N34: =SUM(N35:N38) -> 0 | O34: =SUM(O35:O38) -> 0 | P34: =Q34+R34 -> 0 | Q34: =SUM(Q35:Q38) -> 0 | R34: =SUM(R35:R38) -> 0 | S34: =T34+W34+Z34 -> 0 | T34: =U34+V34 -> 0 | U34: =SUM(U35:U38) -> 0 | V34: =SUM(V35:V38) -> 0 | W34: =X34+Y34 -> 0 | X34: =SUM(X35:X38) -> 0 | Y34: =SUM(Y35:Y38) -> 0 | Z34: =AA34+AB34 -> 0 | AA34: =SUM(AA35:AA38) -> 0 | AB34: =SUM(AB35:AB38) -> 0 | AC34: =SUM(I34:AB34) -> 0
G35: в том числе: Скелетон | H35: 25 | I35: =J35+M35+P35 -> 0 | J35: =K35+L35 -> 0 | M35: =N35+O35 -> 0 | P35: =Q35+R35 -> 0 | S35: =T35+W35+Z35 -> 0 | T35: =U35+V35 -> 0 | W35: =X35+Y35 -> 0 | Z35: =AA35+AB35 -> 0 | AC35: =SUM(I35:AB35) -> 0
G36: Экипаж | H36: 26 | I36: =J36+M36+P36 -> 0 | J36: =K36+L36 -> 0 | M36: =N36+O36 -> 0 | P36: =Q36+R36 -> 0 | S36: =T36+W36+Z36 -> 0 | T36: =U36+V36 -> 0 | W36: =X36+Y36 -> 0 | Z36: =AA36+AB36 -> 0 | AC36: =SUM(I36:AB36) -> 0
G37: Монобоб | H37: 27 | I37: =J37+M37+P37 -> 0 | J37: =K37+L37 -> 0 | M37: =N37+O37 -> 0 | P37: =Q37+R37 -> 0 | S37: =T37+W37+Z37 -> 0 | T37: =U37+V37 -> 0 | W37: =X37+Y37 -> 0 | Z37: =AA37+AB37 -> 0 | AC37: =SUM(I37:AB37) -> 0
G38: Иные дисциплины вида спорта "бобслей" | H38: 28 | I38: =J38+M38+P38 -> 0 | J38: =K38+L38 -> 0 | M38: =N38+O38 -> 0 | P38: =Q38+R38 -> 0 | S38: =T38+W38+Z38 -> 0 | T38: =U38+V38 -> 0 | W38: =X38+Y38 -> 0 | Z38: =AA38+AB38 -> 0 | AC38: =SUM(I38:AB38) -> 0
G39: Бодибилдинг | H39: 29 | I39: =J39+M39+P39 -> 0 | J39: =K39+L39 -> 0 | M39: =N39+O39 -> 0 | P39: =Q39+R39 -> 0 | S39: =T39+W39+Z39 -> 0 | T39: =U39+V39 -> 0 | W39: =X39+Y39 -> 0 | Z39: =AA39+AB39 -> 0 | AC39: =SUM(I39:AB39) -> 0
G40: Бокс | H40: 30 | I40: =J40+M40+P40 -> 0 | J40: =K40+L40 -> 0 | M40: =N40+O40 -> 0 | P40: =Q40+R40 -> 0 | S40: =T40+W40+Z40 -> 0 | T40: =U40+V40 -> 0 | W40: =X40+Y40 -> 0 | Z40: =AA40+AB40 -> 0 | AC40: =SUM(I40:AB40) -> 0
G41: Борьба на поясах | H41: 31 | I41: =J41+M41+P41 -> 0 | J41: =K41+L41 -> 0 | M41: =N41+O41 -> 0 | P41: =Q41+R41 -> 0 | S41: =T41+W41+Z41 -> 0 | T41: =U41+V41 -> 0 | W41: =X41+Y41 -> 0 | Z41: =AA41+AB41 -> 0 | AC41: =SUM(I41:AB41) -> 0
G42: Боулинг | H42: 32 | I42: =J42+M42+P42 -> 0 | J42: =K42+L42 -> 0 | M42: =N42+O42 -> 0 | P42: =Q42+R42 -> 0 | S42: =T42+W42+Z42 -> 0 | T42: =U42+V42 -> 0 | W42: =X42+Y42 -> 0 | Z42: =AA42+AB42 -> 0 | AC42: =SUM(I42:AB42) -> 0
G43: Боулспорт | H43: 33 | I43: =J43+M43+P43 -> 0 | J43: =K43+L43 -> 0 | M43: =N43+O43 -> 0 | P43: =Q43+R43 -> 0 | S43: =T43+W43+Z43 -> 0 | T43: =U43+V43 -> 0 | W43: =X43+Y43 -> 0 | Z43: =AA43+AB43 -> 0 | AC43: =SUM(I43:AB43) -> 0
G44: Брейкинг | H44: 34 | I44: =J44+M44+P44 -> 0 | J44: =K44+L44 -> 0 | M44: =N44+O44 -> 0 | P44: =Q44+R44 -> 0 | S44: =T44+W44+Z44 -> 0 | T44: =U44+V44 -> 0 | W44: =X44+Y44 -> 0 | Z44: =AA44+AB44 -> 0 | AC44: =SUM(I44:AB44) -> 0
G45: Велосипедный спорт - всего | H45: 35 | I45: =J45+M45+P45 -> 0 | J45: =K45+L45 -> 0 | K45: =SUM(K46:K51) -> 0 | L45: =SUM(L46:L51) -> 0 | M45: =N45+O45 -> 0 | N45: =SUM(N46:N51) -> 0 | O45: =SUM(O46:O51) -> 0 | P45: =Q45+R45 -> 0 | Q45: =SUM(Q46:Q51) -> 0 | R45: =SUM(R46:R51) -> 0 | S45: =T45+W45+Z45 -> 0 | T45: =U45+V45 -> 0 | U45: =SUM(U46:U51) -> 0 | V45: =SUM(V46:V51) -> 0 | W45: =X45+Y45 -> 0 | X45: =SUM(X46:X51) -> 0 | Y45: =SUM(Y46:Y51) -> 0 | Z45: =AA45+AB45 -> 0 | AA45: =SUM(AA46:AA51) -> 0 | AB45: =SUM(AB46:AB51) -> 0 | AC45: =SUM(I45:AB45) -> 0
G46: в том числе: BMX (гонка, эстафета) | H46: 36 | I46: =J46+M46+P46 -> 0 | J46: =K46+L46 -> 0 | M46: =N46+O46 -> 0 | P46: =Q46+R46 -> 0 | S46: =T46+W46+Z46 -> 0 | T46: =U46+V46 -> 0 | W46: =X46+Y46 -> 0 | Z46: =AA46+AB46 -> 0 | AC46: =SUM(I46:AB46) -> 0
G47: BMX - фристайл | H47: 37 | I47: =J47+M47+P47 -> 0 | J47: =K47+L47 -> 0 | M47: =N47+O47 -> 0 | P47: =Q47+R47 -> 0 | S47: =T47+W47+Z47 -> 0 | T47: =U47+V47 -> 0 | W47: =X47+Y47 -> 0 | Z47: =AA47+AB47 -> 0 | AC47: =SUM(I47:AB47) -> 0
G48: Маунтинбайк | H48: 38 | I48: =J48+M48+P48 -> 0 | J48: =K48+L48 -> 0 | M48: =N48+O48 -> 0 | P48: =Q48+R48 -> 0 | S48: =T48+W48+Z48 -> 0 | T48: =U48+V48 -> 0 | W48: =X48+Y48 -> 0 | Z48: =AA48+AB48 -> 0 | AC48: =SUM(I48:AB48) -> 0
G49: Трек | H49: 39 | I49: =J49+M49+P49 -> 0 | J49: =K49+L49 -> 0 | M49: =N49+O49 -> 0 | P49: =Q49+R49 -> 0 | S49: =T49+W49+Z49 -> 0 | T49: =U49+V49 -> 0 | W49: =X49+Y49 -> 0 | Z49: =AA49+AB49 -> 0 | AC49: =SUM(I49:AB49) -> 0
G50: Шоссе | H50: 40 | I50: =J50+M50+P50 -> 0 | J50: =K50+L50 -> 0 | M50: =N50+O50 -> 0 | P50: =Q50+R50 -> 0 | S50: =T50+W50+Z50 -> 0 | T50: =U50+V50 -> 0 | W50: =X50+Y50 -> 0 | Z50: =AA50+AB50 -> 0 | AC50: =SUM(I50:AB50) -> 0
G51: Технический симулятор | H51: 41 | I51: =J51+M51+P51 -> 0 | J51: =K51+L51 -> 0 | M51: =N51+O51 -> 0 | P51: =Q51+R51 -> 0 | S51: =T51+W51+Z51 -> 0 | T51: =U51+V51 -> 0 | W51: =X51+Y51 -> 0 | Z51: =AA51+AB51 -> 0 | AC51: =SUM(I51:AB51) -> 0
G52: Вертолетный спорт | H52: 42 | I52: =J52+M52+P52 -> 0 | J52: =K52+L52 -> 0 | M52: =N52+O52 -> 0 | P52: =Q52+R52 -> 0 | S52: =T52+W52+Z52 -> 0 | T52: =U52+V52 -> 0 | W52: =X52+Y52 -> 0 | Z52: =AA52+AB52 -> 0 | AC52: =SUM(I52:AB52) -> 0
G53: Водное поло - всего | H53: 43 | I53: =J53+M53+P53 -> 0 | J53: =K53+L53 -> 0 | K53: =SUM(K54:K55) -> 0 | L53: =SUM(L54:L55) -> 0 | M53: =N53+O53 -> 0 | N53: =SUM(N54:N55) -> 0 | O53: =SUM(O54:O55) -> 0 | P53: =Q53+R53 -> 0 | Q53: =SUM(Q54:Q55) -> 0 | R53: =SUM(R54:R55) -> 0 | S53: =T53+W53+Z53 -> 0 | T53: =U53+V53 -> 0 | U53: =SUM(U54:U55) -> 0 | V53: =SUM(V54:V55) -> 0 | W53: =X53+Y53 -> 0 | X53: =SUM(X54:X55) -> 0 | Y53: =SUM(Y54:Y55) -> 0 | Z53: =AA53+AB53 -> 0 | AA53: =SUM(AA54:AA55) -> 0 | AB53: =SUM(AB54:AB55) -> 0 | AC53: =SUM(I53:AB53) -> 0
G54: в том числе: Водное поло | H54: 44 | I54: =J54+M54+P54 -> 0 | J54: =K54+L54 -> 0 | M54: =N54+O54 -> 0 | P54: =Q54+R54 -> 0 | S54: =T54+W54+Z54 -> 0 | T54: =U54+V54 -> 0 | W54: =X54+Y54 -> 0 | Z54: =AA54+AB54 -> 0 | AC54: =SUM(I54:AB54) -> 0
G55: Иные дисциплины вида спорта "водное поло" | H55: 45 | I55: =J55+M55+P55 -> 0 | J55: =K55+L55 -> 0 | M55: =N55+O55 -> 0 | P55: =Q55+R55 -> 0 | S55: =T55+W55+Z55 -> 0 | T55: =U55+V55 -> 0 | W55: =X55+Y55 -> 0 | Z55: =AA55+AB55 -> 0 | AC55: =SUM(I55:AB55) -> 0
G56: Воднолыжный спорт | H56: 46 | I56: =J56+M56+P56 -> 0 | J56: =K56+L56 -> 0 | M56: =N56+O56 -> 0 | P56: =Q56+R56 -> 0 | S56: =T56+W56+Z56 -> 0 | T56: =U56+V56 -> 0 | W56: =X56+Y56 -> 0 | Z56: =AA56+AB56 -> 0 | AC56: =SUM(I56:AB56) -> 0
G57: Водно-моторный спорт | H57: 47 | I57: =J57+M57+P57 -> 0 | J57: =K57+L57 -> 0 | M57: =N57+O57 -> 0 | P57: =Q57+R57 -> 0 | S57: =T57+W57+Z57 -> 0 | T57: =U57+V57 -> 0 | W57: =X57+Y57 -> 0 | Z57: =AA57+AB57 -> 0 | AC57: =SUM(I57:AB57) -> 0
G58: Водно-спасательное многоборье | H58: 48 | I58: =J58+M58+P58 -> 0 | J58: =K58+L58 -> 0 | M58: =N58+O58 -> 0 | P58: =Q58+R58 -> 0 | S58: =T58+W58+Z58 -> 0 | T58: =U58+V58 -> 0 | W58: =X58+Y58 -> 0 | Z58: =AA58+AB58 -> 0 | AC58: =SUM(I58:AB58) -> 0
G59: Военно-прикладной спорт | H59: 49 | I59: =J59+M59+P59 -> 0 | J59: =K59+L59 -> 0 | M59: =N59+O59 -> 0 | P59: =Q59+R59 -> 0 | S59: =T59+W59+Z59 -> 0 | T59: =U59+V59 -> 0 | W59: =X59+Y59 -> 0 | Z59: =AA59+AB59 -> 0 | AC59: =SUM(I59:AB59) -> 0
G60: Военно-спортивное многоборье | H60: 50 | I60: =J60+M60+P60 -> 0 | J60: =K60+L60 -> 0 | M60: =N60+O60 -> 0 | P60: =Q60+R60 -> 0 | S60: =T60+W60+Z60 -> 0 | T60: =U60+V60 -> 0 | W60: =X60+Y60 -> 0 | Z60: =AA60+AB60 -> 0 | AC60: =SUM(I60:AB60) -> 0
G61: Воздухоплавательный спорт | H61: 51 | I61: =J61+M61+P61 -> 0 | J61: =K61+L61 -> 0 | M61: =N61+O61 -> 0 | P61: =Q61+R61 -> 0 | S61: =T61+W61+Z61 -> 0 | T61: =U61+V61 -> 0 | W61: =X61+Y61 -> 0 | Z61: =AA61+AB61 -> 0 | AC61: =SUM(I61:AB61) -> 0
G62: Воздушная гимнастика | H62: 52 | I62: =J62+M62+P62 -> 0 | J62: =K62+L62 -> 0 | M62: =N62+O62 -> 0 | P62: =Q62+R62 -> 0 | S62: =T62+W62+Z62 -> 0 | T62: =U62+V62 -> 0 | W62: =X62+Y62 -> 0 | Z62: =AA62+AB62 -> 0 | AC62: =SUM(I62:AB62) -> 0
G63: Воздушно-силовая атлетика | H63: 53 | I63: =J63+M63+P63 -> 0 | J63: =K63+L63 -> 0 | M63: =N63+O63 -> 0 | P63: =Q63+R63 -> 0 | S63: =T63+W63+Z63 -> 0 | T63: =U63+V63 -> 0 | W63: =X63+Y63 -> 0 | Z63: =AA63+AB63 -> 0 | AC63: =SUM(I63:AB63) -> 0
G64: Волейбол - всего | H64: 54 | I64: =J64+M64+P64 -> 0 | J64: =K64+L64 -> 0 | K64: =SUM(K65:K67) -> 0 | L64: =SUM(L65:L67) -> 0 | M64: =N64+O64 -> 0 | N64: =SUM(N65:N67) -> 0 | O64: =SUM(O65:O67) -> 0 | P64: =Q64+R64 -> 0 | Q64: =SUM(Q65:Q67) -> 0 | R64: =SUM(R65:R67) -> 0 | S64: =T64+W64+Z64 -> 0 | T64: =U64+V64 -> 0 | U64: =SUM(U65:U67) -> 0 | V64: =SUM(V65:V67) -> 0 | W64: =X64+Y64 -> 0 | X64: =SUM(X65:X67) -> 0 | Y64: =SUM(Y65:Y67) -> 0 | Z64: =AA64+AB64 -> 0 | AA64: =SUM(AA65:AA67) -> 0 | AB64: =SUM(AB65:AB67) -> 0 | AC64: =SUM(I64:AB64) -> 0
G65: в том числе: Волейбол | H65: 55 | I65: =J65+M65+P65 -> 0 | J65: =K65+L65 -> 0 | M65: =N65+O65 -> 0 | P65: =Q65+R65 -> 0 | S65: =T65+W65+Z65 -> 0 | T65: =U65+V65 -> 0 | W65: =X65+Y65 -> 0 | Z65: =AA65+AB65 -> 0 | AC65: =SUM(I65:AB65) -> 0
G66: Пляжный волейбол | H66: 56 | I66: =J66+M66+P66 -> 0 | J66: =K66+L66 -> 0 | M66: =N66+O66 -> 0 | P66: =Q66+R66 -> 0 | S66: =T66+W66+Z66 -> 0 | T66: =U66+V66 -> 0 | W66: =X66+Y66 -> 0 | Z66: =AA66+AB66 -> 0 | AC66: =SUM(I66:AB66) -> 0
G67: Волейбол на снегу | H67: 57 | I67: =J67+M67+P67 -> 0 | J67: =K67+L67 -> 0 | M67: =N67+O67 -> 0 | P67: =Q67+R67 -> 0 | S67: =T67+W67+Z67 -> 0 | T67: =U67+V67 -> 0 | W67: =X67+Y67 -> 0 | Z67: =AA67+AB67 -> 0 | AC67: =SUM(I67:AB67) -> 0
G68: Восточное боевое единоборство | H68: 58 | I68: =J68+M68+P68 -> 0 | J68: =K68+L68 -> 0 | M68: =N68+O68 -> 0 | P68: =Q68+R68 -> 0 | S68: =T68+W68+Z68 -> 0 | T68: =U68+V68 -> 0 | W68: =X68+Y68 -> 0 | Z68: =AA68+AB68 -> 0 | AC68: =SUM(I68:AB68) -> 0
G69: Всестилевое каратэ | H69: 59 | I69: =J69+M69+P69 -> 0 | J69: =K69+L69 -> 0 | M69: =N69+O69 -> 0 | P69: =Q69+R69 -> 0 | S69: =T69+W69+Z69 -> 0 | T69: =U69+V69 -> 0 | W69: =X69+Y69 -> 0 | Z69: =AA69+AB69 -> 0 | AC69: =SUM(I69:AB69) -> 0
G70: Гандбол - всего | H70: 60 | I70: =J70+M70+P70 -> 0 | J70: =K70+L70 -> 0 | K70: =SUM(K71:K72) -> 0 | L70: =SUM(L71:L72) -> 0 | M70: =N70+O70 -> 0 | N70: =SUM(N71:N72) -> 0 | O70: =SUM(O71:O72) -> 0 | P70: =Q70+R70 -> 0 | Q70: =SUM(Q71:Q72) -> 0 | R70: =SUM(R71:R72) -> 0 | S70: =T70+W70+Z70 -> 0 | T70: =U70+V70 -> 0 | U70: =SUM(U71:U72) -> 0 | V70: =SUM(V71:V72) -> 0 | W70: =X70+Y70 -> 0 | X70: =SUM(X71:X72) -> 0 | Y70: =SUM(Y71:Y72) -> 0 | Z70: =AA70+AB70 -> 0 | AA70: =SUM(AA71:AA72) -> 0 | AB70: =SUM(AB71:AB72) -> 0 | AC70: =SUM(I70:AB70) -> 0
G71: в том числе: Гандбол | H71: 61 | I71: =J71+M71+P71 -> 0 | J71: =K71+L71 -> 0 | M71: =N71+O71 -> 0 | P71: =Q71+R71 -> 0 | S71: =T71+W71+Z71 -> 0 | T71: =U71+V71 -> 0 | W71: =X71+Y71 -> 0 | Z71: =AA71+AB71 -> 0 | AC71: =SUM(I71:AB71) -> 0
G72: Пляжный гандбол | H72: 62 | I72: =J72+M72+P72 -> 0 | J72: =K72+L72 -> 0 | M72: =N72+O72 -> 0 | P72: =Q72+R72 -> 0 | S72: =T72+W72+Z72 -> 0 | T72: =U72+V72 -> 0 | W72: =X72+Y72 -> 0 | Z72: =AA72+AB72 -> 0 | AC72: =SUM(I72:AB72) -> 0
G73: Гиревой спорт | H73: 63 | I73: =J73+M73+P73 -> 0 | J73: =K73+L73 -> 0 | M73: =N73+O73 -> 0 | P73: =Q73+R73 -> 0 | S73: =T73+W73+Z73 -> 0 | T73: =U73+V73 -> 0 | W73: =X73+Y73 -> 0 | Z73: =AA73+AB73 -> 0 | AC73: =SUM(I73:AB73) -> 0
G74: Го | H74: 64 | I74: =J74+M74+P74 -> 0 | J74: =K74+L74 -> 0 | M74: =N74+O74 -> 0 | P74: =Q74+R74 -> 0 | S74: =T74+W74+Z74 -> 0 | T74: =U74+V74 -> 0 | W74: =X74+Y74 -> 0 | Z74: =AA74+AB74 -> 0 | AC74: =SUM(I74:AB74) -> 0
G75: Гольф | H75: 65 | I75: =J75+M75+P75 -> 0 | J75: =K75+L75 -> 0 | M75: =N75+O75 -> 0 | P75: =Q75+R75 -> 0 | S75: =T75+W75+Z75 -> 0 | T75: =U75+V75 -> 0 | W75: =X75+Y75 -> 0 | Z75: =AA75+AB75 -> 0 | AC75: =SUM(I75:AB75) -> 0
G76: Гонки дронов (беспилотных воздушных судов) - всего | H76: 66 | I76: =J76+M76+P76 -> 0 | J76: =K76+L76 -> 0 | K76: =SUM(K77:K80) -> 0 | L76: =SUM(L77:L80) -> 0 | M76: =N76+O76 -> 0 | N76: =SUM(N77:N80) -> 0 | O76: =SUM(O77:O80) -> 0 | P76: =Q76+R76 -> 0 | Q76: =SUM(Q77:Q80) -> 0 | R76: =SUM(R77:R80) -> 0 | S76: =T76+W76+Z76 -> 0 | T76: =U76+V76 -> 0 | U76: =SUM(U77:U80) -> 0 | V76: =SUM(V77:V80) -> 0 | W76: =X76+Y76 -> 0 | X76: =SUM(X77:X80) -> 0 | Y76: =SUM(Y77:Y80) -> 0 | Z76: =AA76+AB76 -> 0 | AA76: =SUM(AA77:AA80) -> 0 | AB76: =SUM(AB77:AB80) -> 0 | AC76: =SUM(I76:AB76) -> 0
G77: в том числе: Класс 75 мм | H77: 67 | I77: =J77+M77+P77 -> 0 | J77: =K77+L77 -> 0 | M77: =N77+O77 -> 0 | P77: =Q77+R77 -> 0 | S77: =T77+W77+Z77 -> 0 | T77: =U77+V77 -> 0 | W77: =X77+Y77 -> 0 | Z77: =AA77+AB77 -> 0 | AC77: =SUM(I77:AB77) -> 0
G78: Класс 200 мм | H78: 68 | I78: =J78+M78+P78 -> 0 | J78: =K78+L78 -> 0 | M78: =N78+O78 -> 0 | P78: =Q78+R78 -> 0 | S78: =T78+W78+Z78 -> 0 | T78: =U78+V78 -> 0 | W78: =X78+Y78 -> 0 | Z78: =AA78+AB78 -> 0 | AC78: =SUM(I78:AB78) -> 0
G79: Класс 330 мм | H79: 69 | I79: =J79+M79+P79 -> 0 | J79: =K79+L79 -> 0 | M79: =N79+O79 -> 0 | P79: =Q79+R79 -> 0 | S79: =T79+W79+Z79 -> 0 | T79: =U79+V79 -> 0 | W79: =X79+Y79 -> 0 | Z79: =AA79+AB79 -> 0 | AC79: =SUM(I79:AB79) -> 0
G80: Технический симулятор | H80: 70 | I80: =J80+M80+P80 -> 0 | J80: =K80+L80 -> 0 | M80: =N80+O80 -> 0 | P80: =Q80+R80 -> 0 | S80: =T80+W80+Z80 -> 0 | T80: =U80+V80 -> 0 | W80: =X80+Y80 -> 0 | Z80: =AA80+AB80 -> 0 | AC80: =SUM(I80:AB80) -> 0
G81: Гонки на охотничьих лыжах | H81: 71 | I81: =J81+M81+P81 -> 0 | J81: =K81+L81 -> 0 | M81: =N81+O81 -> 0 | P81: =Q81+R81 -> 0 | S81: =T81+W81+Z81 -> 0 | T81: =U81+V81 -> 0 | W81: =X81+Y81 -> 0 | Z81: =AA81+AB81 -> 0 | AC81: =SUM(I81:AB81) -> 0
G82: Гонки с препятствиями | H82: 72 | I82: =J82+M82+P82 -> 0 | J82: =K82+L82 -> 0 | M82: =N82+O82 -> 0 | P82: =Q82+R82 -> 0 | S82: =T82+W82+Z82 -> 0 | T82: =U82+V82 -> 0 | W82: =X82+Y82 -> 0 | Z82: =AA82+AB82 -> 0 | AC82: =SUM(I82:AB82) -> 0
G83: Горнолыжный спорт | H83: 73 | I83: =J83+M83+P83 -> 0 | J83: =K83+L83 -> 0 | M83: =N83+O83 -> 0 | P83: =Q83+R83 -> 0 | S83: =T83+W83+Z83 -> 0 | T83: =U83+V83 -> 0 | W83: =X83+Y83 -> 0 | Z83: =AA83+AB83 -> 0 | AC83: =SUM(I83:AB83) -> 0
G84: Городошный спорт | H84: 74 | I84: =J84+M84+P84 -> 0 | J84: =K84+L84 -> 0 | M84: =N84+O84 -> 0 | P84: =Q84+R84 -> 0 | S84: =T84+W84+Z84 -> 0 | T84: =U84+V84 -> 0 | W84: =X84+Y84 -> 0 | Z84: =AA84+AB84 -> 0 | AC84: =SUM(I84:AB84) -> 0
G85: Гребля на байдарках и каноэ | H85: 75 | I85: =J85+M85+P85 -> 0 | J85: =K85+L85 -> 0 | M85: =N85+O85 -> 0 | P85: =Q85+R85 -> 0 | S85: =T85+W85+Z85 -> 0 | T85: =U85+V85 -> 0 | W85: =X85+Y85 -> 0 | Z85: =AA85+AB85 -> 0 | AC85: =SUM(I85:AB85) -> 0
G86: Гребля на шлюпках | H86: 76 | I86: =J86+M86+P86 -> 0 | J86: =K86+L86 -> 0 | M86: =N86+O86 -> 0 | P86: =Q86+R86 -> 0 | S86: =T86+W86+Z86 -> 0 | T86: =U86+V86 -> 0 | W86: =X86+Y86 -> 0 | Z86: =AA86+AB86 -> 0 | AC86: =SUM(I86:AB86) -> 0
G87: Гребной слалом | H87: 77 | I87: =J87+M87+P87 -> 0 | J87: =K87+L87 -> 0 | M87: =N87+O87 -> 0 | P87: =Q87+R87 -> 0 | S87: =T87+W87+Z87 -> 0 | T87: =U87+V87 -> 0 | W87: =X87+Y87 -> 0 | Z87: =AA87+AB87 -> 0 | AC87: =SUM(I87:AB87) -> 0
G88: Гребной спорт - всего | H88: 78 | I88: =J88+M88+P88 -> 0 | J88: =K88+L88 -> 0 | K88: =SUM(K89:K90) -> 0 | L88: =SUM(L89:L90) -> 0 | M88: =N88+O88 -> 0 | N88: =SUM(N89:N90) -> 0 | O88: =SUM(O89:O90) -> 0 | P88: =Q88+R88 -> 0 | Q88: =SUM(Q89:Q90) -> 0 | R88: =SUM(R89:R90) -> 0 | S88: =T88+W88+Z88 -> 0 | T88: =U88+V88 -> 0 | U88: =SUM(U89:U90) -> 0 | V88: =SUM(V89:V90) -> 0 | W88: =X88+Y88 -> 0 | X88: =SUM(X89:X90) -> 0 | Y88: =SUM(Y89:Y90) -> 0 | Z88: =AA88+AB88 -> 0 | AA88: =SUM(AA89:AA90) -> 0 | AB88: =SUM(AB89:AB90) -> 0 | AC88: =SUM(I88:AB88) -> 0
G89: в том числе: Академическая гребля | H89: 79 | I89: =J89+M89+P89 -> 0 | J89: =K89+L89 -> 0 | M89: =N89+O89 -> 0 | P89: =Q89+R89 -> 0 | S89: =T89+W89+Z89 -> 0 | T89: =U89+V89 -> 0 | W89: =X89+Y89 -> 0 | Z89: =AA89+AB89 -> 0 | AC89: =SUM(I89:AB89) -> 0
G90: Иные дисциплины вида спорта "гребной спорт" | H90: 80 | I90: =J90+M90+P90 -> 0 | J90: =K90+L90 -> 0 | M90: =N90+O90 -> 0 | P90: =Q90+R90 -> 0 | S90: =T90+W90+Z90 -> 0 | T90: =U90+V90 -> 0 | W90: =X90+Y90 -> 0 | Z90: =AA90+AB90 -> 0 | AC90: =SUM(I90:AB90) -> 0
G91: Гребно-парусное двоеборье | H91: 81 | I91: =J91+M91+P91 -> 0 | J91: =K91+L91 -> 0 | M91: =N91+O91 -> 0 | P91: =Q91+R91 -> 0 | S91: =T91+W91+Z91 -> 0 | T91: =U91+V91 -> 0 | W91: =X91+Y91 -> 0 | Z91: =AA91+AB91 -> 0 | AC91: =SUM(I91:AB91) -> 0
G92: Дартс | H92: 82 | I92: =J92+M92+P92 -> 0 | J92: =K92+L92 -> 0 | M92: =N92+O92 -> 0 | P92: =Q92+R92 -> 0 | S92: =T92+W92+Z92 -> 0 | T92: =U92+V92 -> 0 | W92: =X92+Y92 -> 0 | Z92: =AA92+AB92 -> 0 | AC92: =SUM(I92:AB92) -> 0
G93: Джиу-джитсу | H93: 83 | I93: =J93+M93+P93 -> 0 | J93: =K93+L93 -> 0 | M93: =N93+O93 -> 0 | P93: =Q93+R93 -> 0 | S93: =T93+W93+Z93 -> 0 | T93: =U93+V93 -> 0 | W93: =X93+Y93 -> 0 | Z93: =AA93+AB93 -> 0 | AC93: =SUM(I93:AB93) -> 0
G94: Джутайдо | H94: 84 | I94: =J94+M94+P94 -> 0 | J94: =K94+L94 -> 0 | M94: =N94+O94 -> 0 | P94: =Q94+R94 -> 0 | S94: =T94+W94+Z94 -> 0 | T94: =U94+V94 -> 0 | W94: =X94+Y94 -> 0 | Z94: =AA94+AB94 -> 0 | AC94: =SUM(I94:AB94) -> 0
G95: Дзюдо | H95: 85 | I95: =J95+M95+P95 -> 0 | J95: =K95+L95 -> 0 | M95: =N95+O95 -> 0 | P95: =Q95+R95 -> 0 | S95: =T95+W95+Z95 -> 0 | T95: =U95+V95 -> 0 | W95: =X95+Y95 -> 0 | Z95: =AA95+AB95 -> 0 | AC95: =SUM(I95:AB95) -> 0
G96: Ездовой спорт | H96: 86 | I96: =J96+M96+P96 -> 0 | J96: =K96+L96 -> 0 | M96: =N96+O96 -> 0 | P96: =Q96+R96 -> 0 | S96: =T96+W96+Z96 -> 0 | T96: =U96+V96 -> 0 | W96: =X96+Y96 -> 0 | Z96: =AA96+AB96 -> 0 | AC96: =SUM(I96:AB96) -> 0
G97: Зимнее плавание | H97: 87 | I97: =J97+M97+P97 -> 0 | J97: =K97+L97 -> 0 | M97: =N97+O97 -> 0 | P97: =Q97+R97 -> 0 | S97: =T97+W97+Z97 -> 0 | T97: =U97+V97 -> 0 | W97: =X97+Y97 -> 0 | Z97: =AA97+AB97 -> 0 | AC97: =SUM(I97:AB97) -> 0
G98: Капоэйра | H98: 88 | I98: =J98+M98+P98 -> 0 | J98: =K98+L98 -> 0 | M98: =N98+O98 -> 0 | P98: =Q98+R98 -> 0 | S98: =T98+W98+Z98 -> 0 | T98: =U98+V98 -> 0 | W98: =X98+Y98 -> 0 | Z98: =AA98+AB98 -> 0 | AC98: =SUM(I98:AB98) -> 0
G99: Каратэ | H99: 89 | I99: =J99+M99+P99 -> 0 | J99: =K99+L99 -> 0 | M99: =N99+O99 -> 0 | P99: =Q99+R99 -> 0 | S99: =T99+W99+Z99 -> 0 | T99: =U99+V99 -> 0 | W99: =X99+Y99 -> 0 | Z99: =AA99+AB99 -> 0 | AC99: =SUM(I99:AB99) -> 0
G100: Кендо | H100: 90 | I100: =J100+M100+P100 -> 0 | J100: =K100+L100 -> 0 | M100: =N100+O100 -> 0 | P100: =Q100+R100 -> 0 | S100: =T100+W100+Z100 -> 0 | T100: =U100+V100 -> 0 | W100: =X100+Y100 -> 0 | Z100: =AA100+AB100 -> 0 | AC100: =SUM(I100:AB100) -> 0
G101: Керешу | H101: 91 | I101: =J101+M101+P101 -> 0 | J101: =K101+L101 -> 0 | M101: =N101+O101 -> 0 | P101: =Q101+R101 -> 0 | S101: =T101+W101+Z101 -> 0 | T101: =U101+V101 -> 0 | W101: =X101+Y101 -> 0 | Z101: =AA101+AB101 -> 0 | AC101: =SUM(I101:AB101) -> 0
G102: Кёрлинг - всего | H102: 92 | I102: =J102+M102+P102 -> 0 | J102: =K102+L102 -> 0 | K102: =SUM(K103:K104) -> 0 | L102: =SUM(L103:L104) -> 0 | M102: =N102+O102 -> 0 | N102: =SUM(N103:N104) -> 0 | O102: =SUM(O103:O104) -> 0 | P102: =Q102+R102 -> 0 | Q102: =SUM(Q103:Q104) -> 0 | R102: =SUM(R103:R104) -> 0 | S102: =T102+W102+Z102 -> 0 | T102: =U102+V102 -> 0 | U102: =SUM(U103:U104) -> 0 | V102: =SUM(V103:V104) -> 0 | W102: =X102+Y102 -> 0 | X102: =SUM(X103:X104) -> 0 | Y102: =SUM(Y103:Y104) -> 0 | Z102: =AA102+AB102 -> 0 | AA102: =SUM(AA103:AA104) -> 0 | AB102: =SUM(AB103:AB104) -> 0 | AC102: =SUM(I102:AB102) -> 0
G103: в том числе: Кёрлинг | H103: 93 | I103: =J103+M103+P103 -> 0 | J103: =K103+L103 -> 0 | M103: =N103+O103 -> 0 | P103: =Q103+R103 -> 0 | S103: =T103+W103+Z103 -> 0 | T103: =U103+V103 -> 0 | W103: =X103+Y103 -> 0 | Z103: =AA103+AB103 -> 0 | AC103: =SUM(I103:AB103) -> 0
G104: Кёрлинг - смешанные пары | H104: 94 | I104: =J104+M104+P104 -> 0 | J104: =K104+L104 -> 0 | M104: =N104+O104 -> 0 | P104: =Q104+R104 -> 0 | S104: =T104+W104+Z104 -> 0 | T104: =U104+V104 -> 0 | W104: =X104+Y104 -> 0 | Z104: =AA104+AB104 -> 0 | AC104: =SUM(I104:AB104) -> 0
...

Sheet Раздел 6
G5: Раздел VI. Всероссийские спортивные соревнования, единица
G6: Виды спорта | H6: № строки | I6: Результаты выступлений на соревнованиях
I7: Всего | O7: Чемпионат России | T7: Первенство России среди юниоров и юниорок | Y7: Первенство России среди юношей и девушек | AD7: Кубок России | AI7: Всероссийские спартакиады между спортсменами субъектов Российской Федерации по летним и зимним видам спорта | AN7: Прочие официальные всероссийские соревнования
I9: медали (1-3 место) | J9: 1 | K9: 2 | L9: 3 | M9: 4-6 | N9: учас-тие | O9: 1 | P9: 2 | Q9: 3 | R9: 4-6 | S9: учас-тие | T9: 1 | U9: 2 | V9: 3 | W9: 4-6 | X9: учас-тие | Y9: 1 | Z9: 2 | AA9: 3 | AB9: 4-6 | AC9: учас-тие | AD9: 1 | AE9: 2 | AF9: 3 | AG9: 4-6 | AH9: учас-тие | AI9: 1 | AJ9: 2 | AK9: 3 | AL9: 4-6 | AM9: учас-тие | AN9: 1 | AO9: 2 | AP9: 3 | AQ9: 4-6 | AR9: учас-тие
A10: ='Раздел 0'!M27 -> 0 | B10: ='Раздел 1'!D15 -> 0 | C10: {=_xlfn.IFS(SUM('Раздел 1'!$D$5:$D$6)>0,"ФКиС",SUM('Раздел 1'!$D$7:$D$8)>0,"Образование",SUM('Раздел 1'!$D$9:$D$10)>0,"Другая")} -> ФКиС | D10: {=_xlfn.IFS(SUM('Раздел 1'!$E$12)>0,"СШ",SUM('Раздел 1'!$F$12)>0,"СШОР",SUM('Раздел 1'!$G$12)>0,"УОР",SUM('Раздел 1'!$H$12)>0,"ЦСП",SUM('Раздел 1'!$I$12)>0,"ДРУГИЕ",SUM('Раздел 1'!$E$13)>0,"ОСП СШ",SUM('Раздел 1'!$F$13)>0,"ОСП СШОР",SUM('Раздел 1'!$I$13)>0,"ОСП ДРУГИЕ")} -> ЦСП | E10: =IF(SUM('Раздел 1'!$D$12)>0,SUM('Раздел 1'!$D$13),"") -> 0 | F10: {=_xlfn.IFS(SUM('Раздел 1'!$D$19)>0,"РФ",SUM('Раздел 1'!$E$19)>0,"СУБЪЕКТ",SUM('Раздел 1'!$F$19:$G$19)>0,"МУНИЦИПАЛ",SUM('Раздел 1'!$H$19:$I$19)>0,"ИНЫЕ")} -> #N/A | G10: 1 | H10: 2 | I10: 3 | J10: 4 | K10: 5 | L10: 6 | M10: 7 | N10: 8 | O10: 9 | P10: 10 | Q10: 11 | R10: 12 | S10: 13 | T10: 14 | U10: 15 | V10: 16 | W10: 17 | X10: 18 | Y10: 19 | Z10: 20 | AA10: 21 | AB10: 22 | AC10: 23 | AD10: 24 | AE10: 25 | AF10: 26 | AG10: 27 | AH10: 28 | AI10: 29 | AJ10: 30 | AK10: 31 | AL10: 32 | AM10: 33 | AN10: 34 | AO10: 35 | AP10: 36 | AQ10: 37 | AR10: 38 | AS10: 39
F11: НЕОЛИМП | G11: Авиамодельный спорт | H11: 01 | I11: =SUM(J11:L11) -> 0 | J11: =O11+T11+Y11+AD11+AI11+AN11 -> 0 | K11: =P11+U11+Z11+AE11+AJ11+AO11 -> 0 | L11: =Q11+V11+AA11+AF11+AK11+AP11 -> 0 | M11: =R11+W11+AB11+AG11+AL11+AQ11 -> 0 | N11: =S11+X11+AC11+AH11+AM11+AR11 -> 0 | AS11: =SUM(I11:AR11) -> 0
F12: НЕОЛИМП | G12: Авиационные гонки | H12: 02 | I12: =SUM(J12:L12) -> 0 | J12: =O12+T12+Y12+AD12+AI12+AN12 -> 0 | K12: =P12+U12+Z12+AE12+AJ12+AO12 -> 0 | L12: =Q12+V12+AA12+AF12+AK12+AP12 -> 0 | M12: =R12+W12+AB12+AG12+AL12+AQ12 -> 0 | N12: =S12+X12+AC12+AH12+AM12+AR12 -> 0 | AS12: =SUM(I12:AR12) -> 0
F13: НЕОЛИМП | G13: Автомобильный спорт | H13: 03 | I13: =SUM(J13:L13) -> 0 | J13: =O13+T13+Y13+AD13+AI13+AN13 -> 0 | K13: =P13+U13+Z13+AE13+AJ13+AO13 -> 0 | L13: =Q13+V13+AA13+AF13+AK13+AP13 -> 0 | M13: =R13+W13+AB13+AG13+AL13+AQ13 -> 0 | N13: =S13+X13+AC13+AH13+AM13+AR13 -> 0 | AS13: =SUM(I13:AR13) -> 0
F14: НЕОЛИМП | G14: Автомодельный спорт | H14: 04 | I14: =SUM(J14:L14) -> 0 | J14: =O14+T14+Y14+AD14+AI14+AN14 -> 0 | K14: =P14+U14+Z14+AE14+AJ14+AO14 -> 0 | L14: =Q14+V14+AA14+AF14+AK14+AP14 -> 0 | M14: =R14+W14+AB14+AG14+AL14+AQ14 -> 0 | N14: =S14+X14+AC14+AH14+AM14+AR14 -> 0 | AS14: =SUM(I14:AR14) -> 0
F15: НЕОЛИМП | G15: Айкидо | H15: 05 | I15: =SUM(J15:L15) -> 0 | J15: =O15+T15+Y15+AD15+AI15+AN15 -> 0 | K15: =P15+U15+Z15+AE15+AJ15+AO15 -> 0 | L15: =Q15+V15+AA15+AF15+AK15+AP15 -> 0 | M15: =R15+W15+AB15+AG15+AL15+AQ15 -> 0 | N15: =S15+X15+AC15+AH15+AM15+AR15 -> 0 | AS15: =SUM(I15:AR15) -> 0
F16: НЕОЛИМП | G16: Акробатический рок-н-ролл | H16: 06 | I16: =SUM(J16:L16) -> 0 | J16: =O16+T16+Y16+AD16+AI16+AN16 -> 0 | K16: =P16+U16+Z16+AE16+AJ16+AO16 -> 0 | L16: =Q16+V16+AA16+AF16+AK16+AP16 -> 0 | M16: =R16+W16+AB16+AG16+AL16+AQ16 -> 0 | N16: =S16+X16+AC16+AH16+AM16+AR16 -> 0 | AS16: =SUM(I16:AR16) -> 0
F17: ОЛИМП зима | G17: Альпинизм - всего | H17: 07 | I17: =SUM(J17:L17) -> 0 | J17: =O17+T17+Y17+AD17+AI17+AN17 -> 0 | K17: =P17+U17+Z17+AE17+AJ17+AO17 -> 0 | L17: =Q17+V17+AA17+AF17+AK17+AP17 -> 0 | M17: =R17+W17+AB17+AG17+AL17+AQ17 -> 0 | N17: =S17+X17+AC17+AH17+AM17+AR17 -> 0 | O17: =SUM(O18:O19) -> 0 | P17: =SUM(P18:P19) -> 0 | Q17: =SUM(Q18:Q19) -> 0 | R17: =SUM(R18:R19) -> 0 | S17: =SUM(S18:S19) -> 0 | T17: =SUM(T18:T19) -> 0 | U17: =SUM(U18:U19) -> 0 | V17: =SUM(V18:V19) -> 0 | ... AR17: =SUM(AR18:AR19) -> 0 | AS17: =SUM(I17:AR17) -> 0
F18: ОЛИМП зима | G18: в том числе: Ски-альпинизм | H18: 08 | I18: =SUM(J18:L18) -> 0 | J18: =O18+T18+Y18+AD18+AI18+AN18 -> 0 | K18: =P18+U18+Z18+AE18+AJ18+AO18 -> 0 | L18: =Q18+V18+AA18+AF18+AK18+AP18 -> 0 | M18: =R18+W18+AB18+AG18+AL18+AQ18 -> 0 | N18: =S18+X18+AC18+AH18+AM18+AR18 -> 0 | AS18: =SUM(I18:AR18) -> 0
F19: ОЛИМП зима | G19: Иные дисциплины вида спорта "альпинизм" | H19: 09 | I19: =SUM(J19:L19) -> 0 | J19: =O19+T19+Y19+AD19+AI19+AN19 -> 0 | K19: =P19+U19+Z19+AE19+AJ19+AO19 -> 0 | L19: =Q19+V19+AA19+AF19+AK19+AP19 -> 0 | M19: =R19+W19+AB19+AG19+AL19+AQ19 -> 0 | N19: =S19+X19+AC19+AH19+AM19+AR19 -> 0 | AS19: =SUM(I19:AR19) -> 0
F20: ОЛИМП лето | G20: Американский футбол | H20: 10 | I20: =SUM(J20:L20) -> 0 | J20: =O20+T20+Y20+AD20+AI20+AN20 -> 0 | K20: =P20+U20+Z20+AE20+AJ20+AO20 -> 0 | L20: =Q20+V20+AA20+AF20+AK20+AP20 -> 0 | M20: =R20+W20+AB20+AG20+AL20+AQ20 -> 0 | N20: =S20+X20+AC20+AH20+AM20+AR20 -> 0 | AS20: =SUM(I20:AR20) -> 0
F21: ПРИКЛАДН | G21: Армейская высокоточная стрельба | H21: 11 | I21: =SUM(J21:L21) -> 0 | J21: =O21+T21+Y21+AD21+AI21+AN21 -> 0 | K21: =P21+U21+Z21+AE21+AJ21+AO21 -> 0 | L21: =Q21+V21+AA21+AF21+AK21+AP21 -> 0 | M21: =R21+W21+AB21+AG21+AL21+AQ21 -> 0 | N21: =S21+X21+AC21+AH21+AM21+AR21 -> 0 | AS21: =SUM(I21:AR21) -> 0
F22: ПРИКЛАДН | G22: Армейский рукопашный бой | H22: 12 | I22: =SUM(J22:L22) -> 0 | J22: =O22+T22+Y22+AD22+AI22+AN22 -> 0 | K22: =P22+U22+Z22+AE22+AJ22+AO22 -> 0 | L22: =Q22+V22+AA22+AF22+AK22+AP22 -> 0 | M22: =R22+W22+AB22+AG22+AL22+AQ22 -> 0 | N22: =S22+X22+AC22+AH22+AM22+AR22 -> 0 | AS22: =SUM(I22:AR22) -> 0
F23: ПРИКЛАДН | G23: Армейское тактико-стрелковое многоборье | H23: 13 | I23: =SUM(J23:L23) -> 0 | J23: =O23+T23+Y23+AD23+AI23+AN23 -> 0 | K23: =P23+U23+Z23+AE23+AJ23+AO23 -> 0 | L23: =Q23+V23+AA23+AF23+AK23+AP23 -> 0 | M23: =R23+W23+AB23+AG23+AL23+AQ23 -> 0 | N23: =S23+X23+AC23+AH23+AM23+AR23 -> 0 | AS23: =SUM(I23:AR23) -> 0
F24: НЕОЛИМП | G24: Армрестлинг | H24: 14 | I24: =SUM(J24:L24) -> 0 | J24: =O24+T24+Y24+AD24+AI24+AN24 -> 0 | K24: =P24+U24+Z24+AE24+AJ24+AO24 -> 0 | L24: =Q24+V24+AA24+AF24+AK24+AP24 -> 0 | M24: =R24+W24+AB24+AG24+AL24+AQ24 -> 0 | N24: =S24+X24+AC24+AH24+AM24+AR24 -> 0 | AS24: =SUM(I24:AR24) -> 0
F25: ОЛИМП лето | G25: Бадминтон | H25: 15 | I25: =SUM(J25:L25) -> 0 | J25: =O25+T25+Y25+AD25+AI25+AN25 -> 0 | K25: =P25+U25+Z25+AE25+AJ25+AO25 -> 0 | L25: =Q25+V25+AA25+AF25+AK25+AP25 -> 0 | M25: =R25+W25+AB25+AG25+AL25+AQ25 -> 0 | N25: =S25+X25+AC25+AH25+AM25+AR25 -> 0 | AS25: =SUM(I25:AR25) -> 0
F26: ОЛИМП лето | G26: Баскетбол - всего | H26: 16 | I26: =SUM(J26:L26) -> 0 | J26: =O26+T26+Y26+AD26+AI26+AN26 -> 0 | K26: =P26+U26+Z26+AE26+AJ26+AO26 -> 0 | L26: =Q26+V26+AA26+AF26+AK26+AP26 -> 0 | M26: =R26+W26+AB26+AG26+AL26+AQ26 -> 0 | N26: =S26+X26+AC26+AH26+AM26+AR26 -> 0 | O26: =SUM(O27:O30) -> 0 | P26: =SUM(P27:P30) -> 0 | Q26: =SUM(Q27:Q30) -> 0 | R26: =SUM(R27:R30) -> 0 | S26: =SUM(S27:S30) -> 0 | T26: =SUM(T27:T30) -> 0 | U26: =SUM(U27:U30) -> 0 | V26: =SUM(V27:V30) -> 0 | ... AR26: =SUM(AR27:AR30) -> 0 | AS26: =SUM(I26:AR26) -> 0
F27: ОЛИМП лето | G27: в том числе: Баскетбол | H27: 17 | I27: =SUM(J27:L27) -> 0 | J27: =O27+T27+Y27+AD27+AI27+AN27 -> 0 | K27: =P27+U27+Z27+AE27+AJ27+AO27 -> 0 | L27: =Q27+V27+AA27+AF27+AK27+AP27 -> 0 | M27: =R27+W27+AB27+AG27+AL27+AQ27 -> 0 | N27: =S27+X27+AC27+AH27+AM27+AR27 -> 0 | AS27: =SUM(I27:AR27) -> 0
F28: ОЛИМП лето | G28: Баскетбол 3х3 | H28: 18 | I28: =SUM(J28:L28) -> 0 | J28: =O28+T28+Y28+AD28+AI28+AN28 -> 0 | K28: =P28+U28+Z28+AE28+AJ28+AO28 -> 0 | L28: =Q28+V28+AA28+AF28+AK28+AP28 -> 0 | M28: =R28+W28+AB28+AG28+AL28+AQ28 -> 0 | N28: =S28+X28+AC28+AH28+AM28+AR28 -> 0 | AS28: =SUM(I28:AR28) -> 0
F29: ОЛИМП лето | G29: Интерактивный баскетбол | H29: 19 | I29: =SUM(J29:L29) -> 0 | J29: =O29+T29+Y29+AD29+AI29+AN29 -> 0 | K29: =P29+U29+Z29+AE29+AJ29+AO29 -> 0 | L29: =Q29+V29+AA29+AF29+AK29+AP29 -> 0 | M29: =R29+W29+AB29+AG29+AL29+AQ29 -> 0 | N29: =S29+X29+AC29+AH29+AM29+AR29 -> 0 | AS29: =SUM(I29:AR29) -> 0
F30: ОЛИМП лето | G30: Иные дисциплины вида спорта "баскетбол" | H30: 20 | I30: =SUM(J30:L30) -> 0 | J30: =O30+T30+Y30+AD30+AI30+AN30 -> 0 | K30: =P30+U30+Z30+AE30+AJ30+AO30 -> 0 | L30: =Q30+V30+AA30+AF30+AK30+AP30 -> 0 | M30: =R30+W30+AB30+AG30+AL30+AQ30 -> 0 | N30: =S30+X30+AC30+AH30+AM30+AR30 -> 0 | AS30: =SUM(I30:AR30) -> 0
F31: ОЛИМП лето | G31: Бейсбол | H31: 21 | I31: =SUM(J31:L31) -> 0 | J31: =O31+T31+Y31+AD31+AI31+AN31 -> 0 | K31: =P31+U31+Z31+AE31+AJ31+AO31 -> 0 | L31: =Q31+V31+AA31+AF31+AK31+AP31 -> 0 | M31: =R31+W31+AB31+AG31+AL31+AQ31 -> 0 | N31: =S31+X31+AC31+AH31+AM31+AR31 -> 0 | AS31: =SUM(I31:AR31) -> 0
F32: ОЛИМП зима | G32: Биатлон | H32: 22 | I32: =SUM(J32:L32) -> 0 | J32: =O32+T32+Y32+AD32+AI32+AN32 -> 0 | K32: =P32+U32+Z32+AE32+AJ32+AO32 -> 0 | L32: =Q32+V32+AA32+AF32+AK32+AP32 -> 0 | M32: =R32+W32+AB32+AG32+AL32+AQ32 -> 0 | N32: =S32+X32+AC32+AH32+AM32+AR32 -> 0 | AS32: =SUM(I32:AR32) -> 0
F33: НЕОЛИМП | G33: Бильярдный спорт | H33: 23 | I33: =SUM(J33:L33) -> 0 | J33: =O33+T33+Y33+AD33+AI33+AN33 -> 0 | K33: =P33+U33+Z33+AE33+AJ33+AO33 -> 0 | L33: =Q33+V33+AA33+AF33+AK33+AP33 -> 0 | M33: =R33+W33+AB33+AG33+AL33+AQ33 -> 0 | N33: =S33+X33+AC33+AH33+AM33+AR33 -> 0 | AS33: =SUM(I33:AR33) -> 0
F34: ОЛИМП зима | G34: Бобслей - всего | H34: 24 | I34: =SUM(J34:L34) -> 0 | J34: =O34+T34+Y34+AD34+AI34+AN34 -> 0 | K34: =P34+U34+Z34+AE34+AJ34+AO34 -> 0 | L34: =Q34+V34+AA34+AF34+AK34+AP34 -> 0 | M34: =R34+W34+AB34+AG34+AL34+AQ34 -> 0 | N34: =S34+X34+AC34+AH34+AM34+AR34 -> 0 | O34: =SUM(O35:O38) -> 0 | P34: =SUM(P35:P38) -> 0 | Q34: =SUM(Q35:Q38) -> 0 | R34: =SUM(R35:R38) -> 0 | S34: =SUM(S35:S38) -> 0 | T34: =SUM(T35:T38) -> 0 | U34: =SUM(U35:U38) -> 0 | V34: =SUM(V35:V38) -> 0 | ... AR34: =SUM(AR35:AR38) -> 0 | AS34: =SUM(I34:AR34) -> 0
F35: ОЛИМП зима | G35: в том числе: Скелетон | H35: 25 | I35: =SUM(J35:L35) -> 0 | J35: =O35+T35+Y35+AD35+AI35+AN35 -> 0 | K35: =P35+U35+Z35+AE35+AJ35+AO35 -> 0 | L35: =Q35+V35+AA35+AF35+AK35+AP35 -> 0 | M35: =R35+W35+AB35+AG35+AL35+AQ35 -> 0 | N35: =S35+X35+AC35+AH35+AM35+AR35 -> 0 | AS35: =SUM(I35:AR35) -> 0
F36: ОЛИМП зима | G36: Экипаж | H36: 26 | I36: =SUM(J36:L36) -> 0 | J36: =O36+T36+Y36+AD36+AI36+AN36 -> 0 | K36: =P36+U36+Z36+AE36+AJ36+AO36 -> 0 | L36: =Q36+V36+AA36+AF36+AK36+AP36 -> 0 | M36: =R36+W36+AB36+AG36+AL36+AQ36 -> 0 | N36: =S36+X36+AC36+AH36+AM36+AR36 -> 0 | AS36: =SUM(I36:AR36) -> 0
F37: ОЛИМП зима | G37: Монобоб | H37: 27 | I37: =SUM(J37:L37) -> 0 | J37: =O37+T37+Y37+AD37+AI37+AN37 -> 0 | K37: =P37+U37+Z37+AE37+AJ37+AO37 -> 0 | L37: =Q37+V37+AA37+AF37+AK37+AP37 -> 0 | M37: =R37+W37+AB37+AG37+AL37+AQ37 -> 0 | N37: =S37+X37+AC37+AH37+AM37+AR37 -> 0 | AS37: =SUM(I37:AR37) -> 0
F38: ОЛИМП зима | G38: Иные дисциплины вида спорта "бобслей" | H38: 28 | I38: =SUM(J38:L38) -> 0 | J38: =O38+T38+Y38+AD38+AI38+AN38 -> 0 | K38: =P38+U38+Z38+AE38+AJ38+AO38 -> 0 | L38: =Q38+V38+AA38+AF38+AK38+AP38 -> 0 | M38: =R38+W38+AB38+AG38+AL38+AQ38 -> 0 | N38: =S38+X38+AC38+AH38+AM38+AR38 -> 0 | AS38: =SUM(I38:AR38) -> 0
F39: НЕОЛИМП | G39: Бодибилдинг | H39: 29 | I39: =SUM(J39:L39) -> 0 | J39: =O39+T39+Y39+AD39+AI39+AN39 -> 0 | K39: =P39+U39+Z39+AE39+AJ39+AO39 -> 0 | L39: =Q39+V39+AA39+AF39+AK39+AP39 -> 0 | M39: =R39+W39+AB39+AG39+AL39+AQ39 -> 0 | N39: =S39+X39+AC39+AH39+AM39+AR39 -> 0 | AS39: =SUM(I39:AR39) -> 0
F40: ОЛИМП лето | G40: Бокс | H40: 30 | I40: =SUM(J40:L40) -> 0 | J40: =O40+T40+Y40+AD40+AI40+AN40 -> 0 | K40: =P40+U40+Z40+AE40+AJ40+AO40 -> 0 | L40: =Q40+V40+AA40+AF40+AK40+AP40 -> 0 | M40: =R40+W40+AB40+AG40+AL40+AQ40 -> 0 | N40: =S40+X40+AC40+AH40+AM40+AR40 -> 0 | AS40: =SUM(I40:AR40) -> 0
F41: НЕОЛИМП | G41: Борьба на поясах | H41: 31 | I41: =SUM(J41:L41) -> 0 | J41: =O41+T41+Y41+AD41+AI41+AN41 -> 0 | K41: =P41+U41+Z41+AE41+AJ41+AO41 -> 0 | L41: =Q41+V41+AA41+AF41+AK41+AP41 -> 0 | M41: =R41+W41+AB41+AG41+AL41+AQ41 -> 0 | N41: =S41+X41+AC41+AH41+AM41+AR41 -> 0 | AS41: =SUM(I41:AR41) -> 0
F42: НЕОЛИМП | G42: Боулинг | H42: 32 | I42: =SUM(J42:L42) -> 0 | J42: =O42+T42+Y42+AD42+AI42+AN42 -> 0 | K42: =P42+U42+Z42+AE42+AJ42+AO42 -> 0 | L42: =Q42+V42+AA42+AF42+AK42+AP42 -> 0 | M42: =R42+W42+AB42+AG42+AL42+AQ42 -> 0 | N42: =S42+X42+AC42+AH42+AM42+AR42 -> 0 | AS42: =SUM(I42:AR42) -> 0
F43: НЕОЛИМП | G43: Боулспорт | H43: 33 | I43: =SUM(J43:L43) -> 0 | J43: =O43+T43+Y43+AD43+AI43+AN43 -> 0 | K43: =P43+U43+Z43+AE43+AJ43+AO43 -> 0 | L43: =Q43+V43+AA43+AF43+AK43+AP43 -> 0 | M43: =R43+W43+AB43+AG43+AL43+AQ43 -> 0 | N43: =S43+X43+AC43+AH43+AM43+AR43 -> 0 | AS43: =SUM(I43:AR43) -> 0
F44: НЕОЛИМП | G44: Брейкинг | H44: 34 | I44: =SUM(J44:L44) -> 0 | J44: =O44+T44+Y44+AD44+AI44+AN44 -> 0 | K44: =P44+U44+Z44+AE44+AJ44+AO44 -> 0 | L44: =Q44+V44+AA44+AF44+AK44+AP44 -> 0 | M44: =R44+W44+AB44+AG44+AL44+AQ44 -> 0 | N44: =S44+X44+AC44+AH44+AM44+AR44 -> 0 | AS44: =SUM(I44:AR44) -> 0
F45: ОЛИМП лето | G45: Велосипедный спорт - всего | H45: 35 | I45: =SUM(J45:L45) -> 0 | J45: =O45+T45+Y45+AD45+AI45+AN45 -> 0 | K45: =P45+U45+Z45+AE45+AJ45+AO45 -> 0 | L45: =Q45+V45+AA45+AF45+AK45+AP45 -> 0 | M45: =R45+W45+AB45+AG45+AL45+AQ45 -> 0 | N45: =S45+X45+AC45+AH45+AM45+AR45 -> 0 | O45: =SUM(O46:O51) -> 0 | P45: =SUM(P46:P51) -> 0 | Q45: =SUM(Q46:Q51) -> 0 | R45: =SUM(R46:R51) -> 0 | S45: =SUM(S46:S51) -> 0 | T45: =SUM(T46:T51) -> 0 | U45: =SUM(U46:U51) -> 0 | V45: =SUM(V46:V51) -> 0 | ... AR45: =SUM(AR46:AR51) -> 0 | AS45: =SUM(I45:AR45) -> 0
F46: ОЛИМП лето | G46: в том числе: BMX (гонка, эстафета) | H46: 36 | I46: =SUM(J46:L46) -> 0 | J46: =O46+T46+Y46+AD46+AI46+AN46 -> 0 | K46: =P46+U46+Z46+AE46+AJ46+AO46 -> 0 | L46: =Q46+V46+AA46+AF46+AK46+AP46 -> 0 | M46: =R46+W46+AB46+AG46+AL46+AQ46 -> 0 | N46: =S46+X46+AC46+AH46+AM46+AR46 -> 0 | AS46: =SUM(I46:AR46) -> 0
F47: ОЛИМП лето | G47: BMX - фристайл | H47: 37 | I47: =SUM(J47:L47) -> 0 | J47: =O47+T47+Y47+AD47+AI47+AN47 -> 0 | K47: =P47+U47+Z47+AE47+AJ47+AO47 -> 0 | L47: =Q47+V47+AA47+AF47+AK47+AP47 -> 0 | M47: =R47+W47+AB47+AG47+AL47+AQ47 -> 0 | N47: =S47+X47+AC47+AH47+AM47+AR47 -> 0 | AS47: =SUM(I47:AR47) -> 0
F48: ОЛИМП лето | G48: Маунтинбайк | H48: 38 | I48: =SUM(J48:L48) -> 0 | J48: =O48+T48+Y48+AD48+AI48+AN48 -> 0 | K48: =P48+U48+Z48+AE48+AJ48+AO48 -> 0 | L48: =Q48+V48+AA48+AF48+AK48+AP48 -> 0 | M48: =R48+W48+AB48+AG48+AL48+AQ48 -> 0 | N48: =S48+X48+AC48+AH48+AM48+AR48 -> 0 | AS48: =SUM(I48:AR48) -> 0
F49: ОЛИМП лето | G49: Трек | H49: 39 | I49: =SUM(J49:L49) -> 0 | J49: =O49+T49+Y49+AD49+AI49+AN49 -> 0 | K49: =P49+U49+Z49+AE49+AJ49+AO49 -> 0 | L49: =Q49+V49+AA49+AF49+AK49+AP49 -> 0 | M49: =R49+W49+AB49+AG49+AL49+AQ49 -> 0 | N49: =S49+X49+AC49+AH49+AM49+AR49 -> 0 | AS49: =SUM(I49:AR49) -> 0
F50: ОЛИМП лето | G50: Шоссе | H50: 40 | I50: =SUM(J50:L50) -> 0 | J50: =O50+T50+Y50+AD50+AI50+AN50 -> 0 | K50: =P50+U50+Z50+AE50+AJ50+AO50 -> 0 | L50: =Q50+V50+AA50+AF50+AK50+AP50 -> 0 | M50: =R50+W50+AB50+AG50+AL50+AQ50 -> 0 | N50: =S50+X50+AC50+AH50+AM50+AR50 -> 0 | AS50: =SUM(I50:AR50) -> 0
F51: ОЛИМП лето | G51: Технический симулятор | H51: 41 | I51: =SUM(J51:L51) -> 0 | J51: =O51+T51+Y51+AD51+AI51+AN51 -> 0 | K51: =P51+U51+Z51+AE51+AJ51+AO51 -> 0 | L51: =Q51+V51+AA51+AF51+AK51+AP51 -> 0 | M51: =R51+W51+AB51+AG51+AL51+AQ51 -> 0 | N51: =S51+X51+AC51+AH51+AM51+AR51 -> 0 | AS51: =SUM(I51:AR51) -> 0
F52: НЕОЛИМП | G52: Вертолетный спорт | H52: 42 | I52: =SUM(J52:L52) -> 0 | J52: =O52+T52+Y52+AD52+AI52+AN52 -> 0 | K52: =P52+U52+Z52+AE52+AJ52+AO52 -> 0 | L52: =Q52+V52+AA52+AF52+AK52+AP52 -> 0 | M52: =R52+W52+AB52+AG52+AL52+AQ52 -> 0 | N52: =S52+X52+AC52+AH52+AM52+AR52 -> 0 | AS52: =SUM(I52:AR52) -> 0
F53: ОЛИМП лето | G53: Водное поло - всего | H53: 43 | I53: =SUM(J53:L53) -> 0 | J53: =O53+T53+Y53+AD53+AI53+AN53 -> 0 | K53: =P53+U53+Z53+AE53+AJ53+AO53 -> 0 | L53: =Q53+V53+AA53+AF53+AK53+AP53 -> 0 | M53: =R53+W53+AB53+AG53+AL53+AQ53 -> 0 | N53: =S53+X53+AC53+AH53+AM53+AR53 -> 0 | O53: =SUM(O54:O55) -> 0 | P53: =SUM(P54:P55) -> 0 | Q53: =SUM(Q54:Q55) -> 0 | R53: =SUM(R54:R55) -> 0 | S53: =SUM(S54:S55) -> 0 | T53: =SUM(T54:T55) -> 0 | U53: =SUM(U54:U55) -> 0 | V53: =SUM(V54:V55) -> 0 | ... AR53: =SUM(AR54:AR55) -> 0 | AS53: =SUM(I53:AR53) -> 0
F54: ОЛИМП лето | G54: в том числе: Водное поло | H54: 44 | I54: =SUM(J54:L54) -> 0 | J54: =O54+T54+Y54+AD54+AI54+AN54 -> 0 | K54: =P54+U54+Z54+AE54+AJ54+AO54 -> 0 | L54: =Q54+V54+AA54+AF54+AK54+AP54 -> 0 | M54: =R54+W54+AB54+AG54+AL54+AQ54 -> 0 | N54: =S54+X54+AC54+AH54+AM54+AR54 -> 0 | AS54: =SUM(I54:AR54) -> 0
F55: ОЛИМП лето | G55: Иные дисциплины вида спорта "водное поло" | H55: 45 | I55: =SUM(J55:L55) -> 0 | J55: =O55+T55+Y55+AD55+AI55+AN55 -> 0 | K55: =P55+U55+Z55+AE55+AJ55+AO55 -> 0 | L55: =Q55+V55+AA55+AF55+AK55+AP55 -> 0 | M55: =R55+W55+AB55+AG55+AL55+AQ55 -> 0 | N55: =S55+X55+AC55+AH55+AM55+AR55 -> 0 | AS55: =SUM(I55:AR55) -> 0
F56: НЕОЛИМП | G56: Воднолыжный спорт | H56: 46 | I56: =SUM(J56:L56) -> 0 | J56: =O56+T56+Y56+AD56+AI56+AN56 -> 0 | K56: =P56+U56+Z56+AE56+AJ56+AO56 -> 0 | L56: =Q56+V56+AA56+AF56+AK56+AP56 -> 0 | M56: =R56+W56+AB56+AG56+AL56+AQ56 -> 0 | N56: =S56+X56+AC56+AH56+AM56+AR56 -> 0 | AS56: =SUM(I56:AR56) -> 0
F57: НЕОЛИМП | G57: Водно-моторный спорт | H57: 47 | I57: =SUM(J57:L57) -> 0 | J57: =O57+T57+Y57+AD57+AI57+AN57 -> 0 | K57: =P57+U57+Z57+AE57+AJ57+AO57 -> 0 | L57: =Q57+V57+AA57+AF57+AK57+AP57 -> 0 | M57: =R57+W57+AB57+AG57+AL57+AQ57 -> 0 | N57: =S57+X57+AC57+AH57+AM57+AR57 -> 0 | AS57: =SUM(I57:AR57) -> 0
F58: НЕОЛИМП | G58: Водно-спасательное многоборье | H58: 48 | I58: =SUM(J58:L58) -> 0 | J58: =O58+T58+Y58+AD58+AI58+AN58 -> 0 | K58: =P58+U58+Z58+AE58+AJ58+AO58 -> 0 | L58: =Q58+V58+AA58+AF58+AK58+AP58 -> 0 | M58: =R58+W58+AB58+AG58+AL58+AQ58 -> 0 | N58: =S58+X58+AC58+AH58+AM58+AR58 -> 0 | AS58: =SUM(I58:AR58) -> 0
F59: ПРИКЛАДН | G59: Военно-прикладной спорт | H59: 49 | I59: =SUM(J59:L59) -> 0 | J59: =O59+T59+Y59+AD59+AI59+AN59 -> 0 | K59: =P59+U59+Z59+AE59+AJ59+AO59 -> 0 | L59: =Q59+V59+AA59+AF59+AK59+AP59 -> 0 | M59: =R59+W59+AB59+AG59+AL59+AQ59 -> 0 | N59: =S59+X59+AC59+AH59+AM59+AR59 -> 0 | AS59: =SUM(I59:AR59) -> 0
F60: ПРИКЛАДН | G60: Военно-спортивное многоборье | H60: 50 | I60: =SUM(J60:L60) -> 0 | J60: =O60+T60+Y60+AD60+AI60+AN60 -> 0 | K60: =P60+U60+Z60+AE60+AJ60+AO60 -> 0 | L60: =Q60+V60+AA60+AF60+AK60+AP60 -> 0 | M60: =R60+W60+AB60+AG60+AL60+AQ60 -> 0 | N60: =S60+X60+AC60+AH60+AM60+AR60 -> 0 | AS60: =SUM(I60:AR60) -> 0
F61: НЕОЛИМП | G61: Воздухоплавательный спорт | H61: 51 | I61: =SUM(J61:L61) -> 0 | J61: =O61+T61+Y61+AD61+AI61+AN61 -> 0 | K61: =P61+U61+Z61+AE61+AJ61+AO61 -> 0 | L61: =Q61+V61+AA61+AF61+AK61+AP61 -> 0 | M61: =R61+W61+AB61+AG61+AL61+AQ61 -> 0 | N61: =S61+X61+AC61+AH61+AM61+AR61 -> 0 | AS61: =SUM(I61:AR61) -> 0
F62: НЕОЛИМП | G62: Воздушная гимнастика | H62: 52 | I62: =SUM(J62:L62) -> 0 | J62: =O62+T62+Y62+AD62+AI62+AN62 -> 0 | K62: =P62+U62+Z62+AE62+AJ62+AO62 -> 0 | L62: =Q62+V62+AA62+AF62+AK62+AP62 -> 0 | M62: =R62+W62+AB62+AG62+AL62+AQ62 -> 0 | N62: =S62+X62+AC62+AH62+AM62+AR62 -> 0 | AS62: =SUM(I62:AR62) -> 0
F63: НЕОЛИМП | G63: Воздушно-силовая атлетика | H63: 53 | I63: =SUM(J63:L63) -> 0 | J63: =O63+T63+Y63+AD63+AI63+AN63 -> 0 | K63: =P63+U63+Z63+AE63+AJ63+AO63 -> 0 | L63: =Q63+V63+AA63+AF63+AK63+AP63 -> 0 | M63: =R63+W63+AB63+AG63+AL63+AQ63 -> 0 | N63: =S63+X63+AC63+AH63+AM63+AR63 -> 0 | AS63: =SUM(I63:AR63) -> 0
F64: ОЛИМП лето | G64: Волейбол - всего | H64: 54 | I64: =SUM(J64:L64) -> 0 | J64: =O64+T64+Y64+AD64+AI64+AN64 -> 0 | K64: =P64+U64+Z64+AE64+AJ64+AO64 -> 0 | L64: =Q64+V64+AA64+AF64+AK64+AP64 -> 0 | M64: =R64+W64+AB64+AG64+AL64+AQ64 -> 0 | N64: =S64+X64+AC64+AH64+AM64+AR64 -> 0 | O64: =SUM(O65:O67) -> 0 | P64: =SUM(P65:P67) -> 0 | Q64: =SUM(Q65:Q67) -> 0 | R64: =SUM(R65:R67) -> 0 | S64: =SUM(S65:S67) -> 0 | T64: =SUM(T65:T67) -> 0 | U64: =SUM(U65:U67) -> 0 | V64: =SUM(V65:V67) -> 0 | ... AR64: =SUM(AR65:AR67) -> 0 | AS64: =SUM(I64:AR64) -> 0
F65: ОЛИМП лето | G65: в том числе: Волейбол | H65: 55 | I65: =SUM(J65:L65) -> 0 | J65: =O65+T65+Y65+AD65+AI65+AN65 -> 0 | K65: =P65+U65+Z65+AE65+AJ65+AO65 -> 0 | L65: =Q65+V65+AA65+AF65+AK65+AP65 -> 0 | M65: =R65+W65+AB65+AG65+AL65+AQ65 -> 0 | N65: =S65+X65+AC65+AH65+AM65+AR65 -> 0 | AS65: =SUM(I65:AR65) -> 0
F66: ОЛИМП лето | G66: Пляжный волейбол | H66: 56 | I66: =SUM(J66:L66) -> 0 | J66: =O66+T66+Y66+AD66+AI66+AN66 -> 0 | K66: =P66+U66+Z66+AE66+AJ66+AO66 -> 0 | L66: =Q66+V66+AA66+AF66+AK66+AP66 -> 0 | M66: =R66+W66+AB66+AG66+AL66+AQ66 -> 0 | N66: =S66+X66+AC66+AH66+AM66+AR66 -> 0 | AS66: =SUM(I66:AR66) -> 0
F67: ОЛИМП лето | G67: Волейбол на снегу | H67: 57 | I67: =SUM(J67:L67) -> 0 | J67: =O67+T67+Y67+AD67+AI67+AN67 -> 0 | K67: =P67+U67+Z67+AE67+AJ67+AO67 -> 0 | L67: =Q67+V67+AA67+AF67+AK67+AP67 -> 0 | M67: =R67+W67+AB67+AG67+AL67+AQ67 -> 0 | N67: =S67+X67+AC67+AH67+AM67+AR67 -> 0 | AS67: =SUM(I67:AR67) -> 0
F68: НЕОЛИМП | G68: Восточное боевое единоборство | H68: 58 | I68: =SUM(J68:L68) -> 0 | J68: =O68+T68+Y68+AD68+AI68+AN68 -> 0 | K68: =P68+U68+Z68+AE68+AJ68+AO68 -> 0 | L68: =Q68+V68+AA68+AF68+AK68+AP68 -> 0 | M68: =R68+W68+AB68+AG68+AL68+AQ68 -> 0 | N68: =S68+X68+AC68+AH68+AM68+AR68 -> 0 | AS68: =SUM(I68:AR68) -> 0
F69: НЕОЛИМП | G69: Всестилевое каратэ | H69: 59 | I69: =SUM(J69:L69) -> 0 | J69: =O69+T69+Y69+AD69+AI69+AN69 -> 0 | K69: =P69+U69+Z69+AE69+AJ69+AO69 -> 0 | L69: =Q69+V69+AA69+AF69+AK69+AP69 -> 0 | M69: =R69+W69+AB69+AG69+AL69+AQ69 -> 0 | N69: =S69+X69+AC69+AH69+AM69+AR69 -> 0 | AS69: =SUM(I69:AR69) -> 0
F70: ОЛИМП лето | G70: Гандбол - всего | H70: 60 | I70: =SUM(J70:L70) -> 0 | J70: =O70+T70+Y70+AD70+AI70+AN70 -> 0 | K70: =P70+U70+Z70+AE70+AJ70+AO70 -> 0 | L70: =Q70+V70+AA70+AF70+AK70+AP70 -> 0 | M70: =R70+W70+AB70+AG70+AL70+AQ70 -> 0 | N70: =S70+X70+AC70+AH70+AM70+AR70 -> 0 | O70: =SUM(O71:O72) -> 0 | P70: =SUM(P71:P72) -> 0 | Q70: =SUM(Q71:Q72) -> 0 | R70: =SUM(R71:R72) -> 0 | S70: =SUM(S71:S72) -> 0 | T70: =SUM(T71:T72) -> 0 | U70: =SUM(U71:U72) -> 0 | V70: =SUM(V71:V72) -> 0 | ... AR70: =SUM(AR71:AR72) -> 0 | AS70: =SUM(I70:AR70) -> 0
F71: ОЛИМП лето | G71: в том числе: Гандбол | H71: 61 | I71: =SUM(J71:L71) -> 0 | J71: =O71+T71+Y71+AD71+AI71+AN71 -> 0 | K71: =P71+U71+Z71+AE71+AJ71+AO71 -> 0 | L71: =Q71+V71+AA71+AF71+AK71+AP71 -> 0 | M71: =R71+W71+AB71+AG71+AL71+AQ71 -> 0 | N71: =S71+X71+AC71+AH71+AM71+AR71 -> 0 | AS71: =SUM(I71:AR71) -> 0
F72: ОЛИМП лето | G72: Пляжный гандбол | H72: 62 | I72: =SUM(J72:L72) -> 0 | J72: =O72+T72+Y72+AD72+AI72+AN72 -> 0 | K72: =P72+U72+Z72+AE72+AJ72+AO72 -> 0 | L72: =Q72+V72+AA72+AF72+AK72+AP72 -> 0 | M72: =R72+W72+AB72+AG72+AL72+AQ72 -> 0 | N72: =S72+X72+AC72+AH72+AM72+AR72 -> 0 | AS72: =SUM(I72:AR72) -> 0
F73: НЕОЛИМП | G73: Гиревой спорт | H73: 63 | I73: =SUM(J73:L73) -> 0 | J73: =O73+T73+Y73+AD73+AI73+AN73 -> 0 | K73: =P73+U73+Z73+AE73+AJ73+AO73 -> 0 | L73: =Q73+V73+AA73+AF73+AK73+AP73 -> 0 | M73: =R73+W73+AB73+AG73+AL73+AQ73 -> 0 | N73: =S73+X73+AC73+AH73+AM73+AR73 -> 0 | AS73: =SUM(I73:AR73) -> 0
F74: НЕОЛИМП | G74: Го | H74: 64 | I74: =SUM(J74:L74) -> 0 | J74: =O74+T74+Y74+AD74+AI74+AN74 -> 0 | K74: =P74+U74+Z74+AE74+AJ74+AO74 -> 0 | L74: =Q74+V74+AA74+AF74+AK74+AP74 -> 0 | M74: =R74+W74+AB74+AG74+AL74+AQ74 -> 0 | N74: =S74+X74+AC74+AH74+AM74+AR74 -> 0 | AS74: =SUM(I74:AR74) -> 0
F75: ОЛИМП лето | G75: Гольф | H75: 65 | I75: =SUM(J75:L75) -> 0 | J75: =O75+T75+Y75+AD75+AI75+AN75 -> 0 | K75: =P75+U75+Z75+AE75+AJ75+AO75 -> 0 | L75: =Q75+V75+AA75+AF75+AK75+AP75 -> 0 | M75: =R75+W75+AB75+AG75+AL75+AQ75 -> 0 | N75: =S75+X75+AC75+AH75+AM75+AR75 -> 0 | AS75: =SUM(I75:AR75) -> 0
F76: НЕОЛИМП | G76: Гонки дронов (беспилотных воздушных судов) - всего | H76: 66 | I76: =SUM(J76:L76) -> 0 | J76: =O76+T76+Y76+AD76+AI76+AN76 -> 0 | K76: =P76+U76+Z76+AE76+AJ76+AO76 -> 0 | L76: =Q76+V76+AA76+AF76+AK76+AP76 -> 0 | M76: =R76+W76+AB76+AG76+AL76+AQ76 -> 0 | N76: =S76+X76+AC76+AH76+AM76+AR76 -> 0 | O76: =SUM(O77:O80) -> 0 | P76: =SUM(P77:P80) -> 0 | Q76: =SUM(Q77:Q80) -> 0 | R76: =SUM(R77:R80) -> 0 | S76: =SUM(S77:S80) -> 0 | T76: =SUM(T77:T80) -> 0 | U76: =SUM(U77:U80) -> 0 | V76: =SUM(V77:V80) -> 0 | ... AR76: =SUM(AR77:AR80) -> 0 | AS76: =SUM(I76:AR76) -> 0
F77: НЕОЛИМП | G77: в том числе: Класс 75 мм | H77: 67 | I77: =SUM(J77:L77) -> 0 | J77: =O77+T77+Y77+AD77+AI77+AN77 -> 0 | K77: =P77+U77+Z77+AE77+AJ77+AO77 -> 0 | L77: =Q77+V77+AA77+AF77+AK77+AP77 -> 0 | M77: =R77+W77+AB77+AG77+AL77+AQ77 -> 0 | N77: =S77+X77+AC77+AH77+AM77+AR77 -> 0 | AS77: =SUM(I77:AR77) -> 0
F78: НЕОЛИМП | G78: Класс 200 мм | H78: 68 | I78: =SUM(J78:L78) -> 0 | J78: =O78+T78+Y78+AD78+AI78+AN78 -> 0 | K78: =P78+U78+Z78+AE78+AJ78+AO78 -> 0 | L78: =Q78+V78+AA78+AF78+AK78+AP78 -> 0 | M78: =R78+W78+AB78+AG78+AL78+AQ78 -> 0 | N78: =S78+X78+AC78+AH78+AM78+AR78 -> 0 | AS78: =SUM(I78:AR78) -> 0
F79: НЕОЛИМП | G79: Класс 330 мм | H79: 69 | I79: =SUM(J79:L79) -> 0 | J79: =O79+T79+Y79+AD79+AI79+AN79 -> 0 | K79: =P79+U79+Z79+AE79+AJ79+AO79 -> 0 | L79: =Q79+V79+AA79+AF79+AK79+AP79 -> 0 | M79: =R79+W79+AB79+AG79+AL79+AQ79 -> 0 | N79: =S79+X79+AC79+AH79+AM79+AR79 -> 0 | AS79: =SUM(I79:AR79) -> 0
F80: НЕОЛИМП | G80: Технический симулятор | H80: 70 | I80: =SUM(J80:L80) -> 0 | J80: =O80+T80+Y80+AD80+AI80+AN80 -> 0 | K80: =P80+U80+Z80+AE80+AJ80+AO80 -> 0 | L80: =Q80+V80+AA80+AF80+AK80+AP80 -> 0 | M80: =R80+W80+AB80+AG80+AL80+AQ80 -> 0 | N80: =S80+X80+AC80+AH80+AM80+AR80 -> 0 | AS80: =SUM(I80:AR80) -> 0
F81: НАЦИОНАЛЬН | G81: Гонки на охотничьих лыжах | H81: 71 | I81: =SUM(J81:L81) -> 0 | J81: =O81+T81+Y81+AD81+AI81+AN81 -> 0 | K81: =P81+U81+Z81+AE81+AJ81+AO81 -> 0 | L81: =Q81+V81+AA81+AF81+AK81+AP81 -> 0 | M81: =R81+W81+AB81+AG81+AL81+AQ81 -> 0 | N81: =S81+X81+AC81+AH81+AM81+AR81 -> 0 | AS81: =SUM(I81:AR81) -> 0
F82: НЕОЛИМП | G82: Гонки с препятствиями | H82: 72 | I82: =SUM(J82:L82) -> 0 | J82: =O82+T82+Y82+AD82+AI82+AN82 -> 0 | K82: =P82+U82+Z82+AE82+AJ82+AO82 -> 0 | L82: =Q82+V82+AA82+AF82+AK82+AP82 -> 0 | M82: =R82+W82+AB82+AG82+AL82+AQ82 -> 0 | N82: =S82+X82+AC82+AH82+AM82+AR82 -> 0 | AS82: =SUM(I82:AR82) -> 0
F83: ОЛИМП зима | G83: Горнолыжный спорт | H83: 73 | I83: =SUM(J83:L83) -> 0 | J83: =O83+T83+Y83+AD83+AI83+AN83 -> 0 | K83: =P83+U83+Z83+AE83+AJ83+AO83 -> 0 | L83: =Q83+V83+AA83+AF83+AK83+AP83 -> 0 | M83: =R83+W83+AB83+AG83+AL83+AQ83 -> 0 | N83: =S83+X83+AC83+AH83+AM83+AR83 -> 0 | AS83: =SUM(I83:AR83) -> 0
F84: НЕОЛИМП | G84: Городошный спорт | H84: 74 | I84: =SUM(J84:L84) -> 0 | J84: =O84+T84+Y84+AD84+AI84+AN84 -> 0 | K84: =P84+U84+Z84+AE84+AJ84+AO84 -> 0 | L84: =Q84+V84+AA84+AF84+AK84+AP84 -> 0 | M84: =R84+W84+AB84+AG84+AL84+AQ84 -> 0 | N84: =S84+X84+AC84+AH84+AM84+AR84 -> 0 | AS84: =SUM(I84:AR84) -> 0
F85: ОЛИМП лето | G85: Гребля на байдарках и каноэ | H85: 75 | I85: =SUM(J85:L85) -> 0 | J85: =O85+T85+Y85+AD85+AI85+AN85 -> 0 | K85: =P85+U85+Z85+AE85+AJ85+AO85 -> 0 | L85: =Q85+V85+AA85+AF85+AK85+AP85 -> 0 | M85: =R85+W85+AB85+AG85+AL85+AQ85 -> 0 | N85: =S85+X85+AC85+AH85+AM85+AR85 -> 0 | AS85: =SUM(I85:AR85) -> 0
F86: ПРИКЛАДН | G86: Гребля на шлюпках | H86: 76 | I86: =SUM(J86:L86) -> 0 | J86: =O86+T86+Y86+AD86+AI86+AN86 -> 0 | K86: =P86+U86+Z86+AE86+AJ86+AO86 -> 0 | L86: =Q86+V86+AA86+AF86+AK86+AP86 -> 0 | M86: =R86+W86+AB86+AG86+AL86+AQ86 -> 0 | N86: =S86+X86+AC86+AH86+AM86+AR86 -> 0 | AS86: =SUM(I86:AR86) -> 0
F87: ОЛИМП лето | G87: Гребной слалом | H87: 77 | I87: =SUM(J87:L87) -> 0 | J87: =O87+T87+Y87+AD87+AI87+AN87 -> 0 | K87: =P87+U87+Z87+AE87+AJ87+AO87 -> 0 | L87: =Q87+V87+AA87+AF87+AK87+AP87 -> 0 | M87: =R87+W87+AB87+AG87+AL87+AQ87 -> 0 | N87: =S87+X87+AC87+AH87+AM87+AR87 -> 0 | AS87: =SUM(I87:AR87) -> 0
F88: ОЛИМП лето | G88: Гребной спорт - всего | H88: 78 | I88: =SUM(J88:L88) -> 0 | J88: =O88+T88+Y88+AD88+AI88+AN88 -> 0 | K88: =P88+U88+Z88+AE88+AJ88+AO88 -> 0 | L88: =Q88+V88+AA88+AF88+AK88+AP88 -> 0 | M88: =R88+W88+AB88+AG88+AL88+AQ88 -> 0 | N88: =S88+X88+AC88+AH88+AM88+AR88 -> 0 | O88: =SUM(O89:O90) -> 0 | P88: =SUM(P89:P90) -> 0 | Q88: =SUM(Q89:Q90) -> 0 | R88: =SUM(R89:R90) -> 0 | S88: =SUM(S89:S90) -> 0 | T88: =SUM(T89:T90) -> 0 | U88: =SUM(U89:U90) -> 0 | V88: =SUM(V89:V90) -> 0 | ... AR88: =SUM(AR89:AR90) -> 0 | AS88: =SUM(I88:AR88) -> 0
F89: ОЛИМП лето | G89: в том числе: Академическая гребля | H89: 79 | I89: =SUM(J89:L89) -> 0 | J89: =O89+T89+Y89+AD89+AI89+AN89 -> 0 | K89: =P89+U89+Z89+AE89+AJ89+AO89 -> 0 | L89: =Q89+V89+AA89+AF89+AK89+AP89 -> 0 | M89: =R89+W89+AB89+AG89+AL89+AQ89 -> 0 | N89: =S89+X89+AC89+AH89+AM89+AR89 -> 0 | AS89: =SUM(I89:AR89) -> 0
F90: ОЛИМП лето | G90: Иные дисциплины вида спорта "гребной спорт" | H90: 80 | I90: =SUM(J90:L90) -> 0 | J90: =O90+T90+Y90+AD90+AI90+AN90 -> 0 | K90: =P90+U90+Z90+AE90+AJ90+AO90 -> 0 | L90: =Q90+V90+AA90+AF90+AK90+AP90 -> 0 | M90: =R90+W90+AB90+AG90+AL90+AQ90 -> 0 | N90: =S90+X90+AC90+AH90+AM90+AR90 -> 0 | AS90: =SUM(I90:AR90) -> 0
F91: ПРИКЛАДН | G91: Гребно-парусное двоеборье | H91: 81 | I91: =SUM(J91:L91) -> 0 | J91: =O91+T91+Y91+AD91+AI91+AN91 -> 0 | K91: =P91+U91+Z91+AE91+AJ91+AO91 -> 0 | L91: =Q91+V91+AA91+AF91+AK91+AP91 -> 0 | M91: =R91+W91+AB91+AG91+AL91+AQ91 -> 0 | N91: =S91+X91+AC91+AH91+AM91+AR91 -> 0 | AS91: =SUM(I91:AR91) -> 0
F92: НЕОЛИМП | G92: Дартс | H92: 82 | I92: =SUM(J92:L92) -> 0 | J92: =O92+T92+Y92+AD92+AI92+AN92 -> 0 | K92: =P92+U92+Z92+AE92+AJ92+AO92 -> 0 | L92: =Q92+V92+AA92+AF92+AK92+AP92 -> 0 | M92: =R92+W92+AB92+AG92+AL92+AQ92 -> 0 | N92: =S92+X92+AC92+AH92+AM92+AR92 -> 0 | AS92: =SUM(I92:AR92) -> 0
F93: НЕОЛИМП | G93: Джиу-джитсу | H93: 83 | I93: =SUM(J93:L93) -> 0 | J93: =O93+T93+Y93+AD93+AI93+AN93 -> 0 | K93: =P93+U93+Z93+AE93+AJ93+AO93 -> 0 | L93: =Q93+V93+AA93+AF93+AK93+AP93 -> 0 | M93: =R93+W93+AB93+AG93+AL93+AQ93 -> 0 | N93: =S93+X93+AC93+AH93+AM93+AR93 -> 0 | AS93: =SUM(I93:AR93) -> 0
F94: НЕОЛИМП | G94: Джутайдо | H94: 84 | I94: =SUM(J94:L94) -> 0 | J94: =O94+T94+Y94+AD94+AI94+AN94 -> 0 | K94: =P94+U94+Z94+AE94+AJ94+AO94 -> 0 | L94: =Q94+V94+AA94+AF94+AK94+AP94 -> 0 | M94: =R94+W94+AB94+AG94+AL94+AQ94 -> 0 | N94: =S94+X94+AC94+AH94+AM94+AR94 -> 0 | AS94: =SUM(I94:AR94) -> 0
F95: ОЛИМП лето | G95: Дзюдо | H95: 85 | I95: =SUM(J95:L95) -> 0 | J95: =O95+T95+Y95+AD95+AI95+AN95 -> 0 | K95: =P95+U95+Z95+AE95+AJ95+AO95 -> 0 | L95: =Q95+V95+AA95+AF95+AK95+AP95 -> 0 | M95: =R95+W95+AB95+AG95+AL95+AQ95 -> 0 | N95: =S95+X95+AC95+AH95+AM95+AR95 -> 0 | AS95: =SUM(I95:AR95) -> 0
F96: НЕОЛИМП | G96: Ездовой спорт | H96: 86 | I96: =SUM(J96:L96) -> 0 | J96: =O96+T96+Y96+AD96+AI96+AN96 -> 0 | K96: =P96+U96+Z96+AE96+AJ96+AO96 -> 0 | L96: =Q96+V96+AA96+AF96+AK96+AP96 -> 0 | M96: =R96+W96+AB96+AG96+AL96+AQ96 -> 0 | N96: =S96+X96+AC96+AH96+AM96+AR96 -> 0 | AS96: =SUM(I96:AR96) -> 0
F97: НЕОЛИМП | G97: Зимнее плавание | H97: 87 | I97: =SUM(J97:L97) -> 0 | J97: =O97+T97+Y97+AD97+AI97+AN97 -> 0 | K97: =P97+U97+Z97+AE97+AJ97+AO97 -> 0 | L97: =Q97+V97+AA97+AF97+AK97+AP97 -> 0 | M97: =R97+W97+AB97+AG97+AL97+AQ97 -> 0 | N97: =S97+X97+AC97+AH97+AM97+AR97 -> 0 | AS97: =SUM(I97:AR97) -> 0
F98: НЕОЛИМП | G98: Капоэйра | H98: 88 | I98: =SUM(J98:L98) -> 0 | J98: =O98+T98+Y98+AD98+AI98+AN98 -> 0 | K98: =P98+U98+Z98+AE98+AJ98+AO98 -> 0 | L98: =Q98+V98+AA98+AF98+AK98+AP98 -> 0 | M98: =R98+W98+AB98+AG98+AL98+AQ98 -> 0 | N98: =S98+X98+AC98+AH98+AM98+AR98 -> 0 | AS98: =SUM(I98:AR98) -> 0
F99: НЕОЛИМП | G99: Каратэ | H99: 89 | I99: =SUM(J99:L99) -> 0 | J99: =O99+T99+Y99+AD99+AI99+AN99 -> 0 | K99: =P99+U99+Z99+AE99+AJ99+AO99 -> 0 | L99: =Q99+V99+AA99+AF99+AK99+AP99 -> 0 | M99: =R99+W99+AB99+AG99+AL99+AQ99 -> 0 | N99: =S99+X99+AC99+AH99+AM99+AR99 -> 0 | AS99: =SUM(I99:AR99) -> 0
F100: НЕОЛИМП | G100: Кендо | H100: 90 | I100: =SUM(J100:L100) -> 0 | J100: =O100+T100+Y100+AD100+AI100+AN100 -> 0 | K100: =P100+U100+Z100+AE100+AJ100+AO100 -> 0 | L100: =Q100+V100+AA100+AF100+AK100+AP100 -> 0 | M100: =R100+W100+AB100+AG100+AL100+AQ100 -> 0 | N100: =S100+X100+AC100+AH100+AM100+AR100 -> 0 | AS100: =SUM(I100:AR100) -> 0
F101: НАЦИОНАЛЬН | G101: Керешу | H101: 91 | I101: =SUM(J101:L101) -> 0 | J101: =O101+T101+Y101+AD101+AI101+AN101 -> 0 | K101: =P101+U101+Z101+AE101+AJ101+AO101 -> 0 | L101: =Q101+V101+AA101+AF101+AK101+AP101 -> 0 | M101: =R101+W101+AB101+AG101+AL101+AQ101 -> 0 | N101: =S101+X101+AC101+AH101+AM101+AR101 -> 0 | AS101: =SUM(I101:AR101) -> 0
F102: ОЛИМП зима | G102: Кёрлинг - всего | H102: 92 | I102: =SUM(J102:L102) -> 0 | J102: =O102+T102+Y102+AD102+AI102+AN102 -> 0 | K102: =P102+U102+Z102+AE102+AJ102+AO102 -> 0 | L102: =Q102+V102+AA102+AF102+AK102+AP102 -> 0 | M102: =R102+W102+AB102+AG102+AL102+AQ102 -> 0 | N102: =S102+X102+AC102+AH102+AM102+AR102 -> 0 | O102: =SUM(O103:O104) -> 0 | P102: =SUM(P103:P104) -> 0 | Q102: =SUM(Q103:Q104) -> 0 | R102: =SUM(R103:R104) -> 0 | S102: =SUM(S103:S104) -> 0 | T102: =SUM(T103:T104) -> 0 | U102: =SUM(U103:U104) -> 0 | V102: =SUM(V103:V104) -> 0 | ... AR102: =SUM(AR103:AR104) -> 0 | AS102: =SUM(I102:AR102) -> 0
F103: ОЛИМП зима | G103: в том числе: Кёрлинг | H103: 93 | I103: =SUM(J103:L103) -> 0 | J103: =O103+T103+Y103+AD103+AI103+AN103 -> 0 | K103: =P103+U103+Z103+AE103+AJ103+AO103 -> 0 | L103: =Q103+V103+AA103+AF103+AK103+AP103 -> 0 | M103: =R103+W103+AB103+AG103+AL103+AQ103 -> 0 | N103: =S103+X103+AC103+AH103+AM103+AR103 -> 0 | AS103: =SUM(I103:AR103) -> 0
F104: ОЛИМП зима | G104: Кёрлинг - смешанные пары | H104: 94 | I104: =SUM(J104:L104) -> 0 | J104: =O104+T104+Y104+AD104+AI104+AN104 -> 0 | K104: =P104+U104+Z104+AE104+AJ104+AO104 -> 0 | L104: =Q104+V104+AA104+AF104+AK104+AP104 -> 0 | M104: =R104+W104+AB104+AG104+AL104+AQ104 -> 0 | N104: =S104+X104+AC104+AH104+AM104+AR104 -> 0 | AS104: =SUM(I104:AR104) -> 0
F105: НЕОЛИМП | G105: Кикбоксинг | H105: 95 | I105: =SUM(J105:L105) -> 0 | J105: =O105+T105+Y105+AD105+AI105+AN105 -> 0 | K105: =P105+U105+Z105+AE105+AJ105+AO105 -> 0 | L105: =Q105+V105+AA105+AF105+AK105+AP105 -> 0 | M105: =R105+W105+AB105+AG105+AL105+AQ105 -> 0 | N105: =S105+X105+AC105+AH105+AM105+AR105 -> 0 | AS105: =SUM(I105:AR105) -> 0
...

Sheet Раздел 7
G5: Раздел VII. Международные спортивные соревнования, единица
G6: Виды спорта | H6: № строки | I6: Результаты выступлений на соревнованиях
I7: Всего | O7: Олимпийские игры | T7: Чемпионат мира | Y7: Юношеские Олимпийские игры | AD7: Первенство мира | AI7: Кубок мира | AN7: Этапы Кубка мира | AS7: Чемпионат Европы | AX7: Первенство Европы | BC7: Кубок Европы | BH7: Прочие официальные международные соревнования
I9: медали (1-3 место) | J9: 1 | K9: 2 | L9: 3 | M9: 4-6 | N9: учас-тие | O9: 1 | P9: 2 | Q9: 3 | R9: 4-6 | S9: учас-тие | T9: 1 | U9: 2 | V9: 3 | W9: 4-6 | X9: учас-тие | Y9: 1 | Z9: 2 | AA9: 3 | AB9: 4-6 | AC9: учас-тие | AD9: 1 | AE9: 2 | AF9: 3 | AG9: 4-6 | AH9: учас-тие | AI9: 1 | AJ9: 2 | AK9: 3 | AL9: 4-6 | AM9: учас-тие | AN9: 1 | AO9: 2 | AP9: 3 | AQ9: 4-6 | AR9: учас-тие | AS9: 1 | AT9: 2 | AU9: 3 | AV9: 4-6 | AW9: учас-тие | AX9: 1 | AY9: 2 | AZ9: 3 | BA9: 4-6 | BB9: учас-тие | BC9: 1 | BD9: 2 | BE9: 3 | BF9: 4-6 | BG9: учас-тие | BH9: 1 | BI9: 2 | BJ9: 3 | BK9: 4-6 | BL9: учас-тие
A10: ='Раздел 0'!M27 -> 0 | B10: ='Раздел 1'!D15 -> 0 | C10: {=_xlfn.IFS(SUM('Раздел 1'!$D$5:$D$6)>0,"ФКиС",SUM('Раздел 1'!$D$7:$D$8)>0,"Образование",SUM('Раздел 1'!$D$9:$D$10)>0,"Другая")} -> ФКиС | D10: {=_xlfn.IFS(SUM('Раздел 1'!$E$12)>0,"СШ",SUM('Раздел 1'!$F$12)>0,"СШОР",SUM('Раздел 1'!$G$12)>0,"УОР",SUM('Раздел 1'!$H$12)>0,"ЦСП",SUM('Раздел 1'!$I$12)>0,"ДРУГИЕ",SUM('Раздел 1'!$E$13)>0,"ОСП СШ",SUM('Раздел 1'!$F$13)>0,"ОСП СШОР",SUM('Раздел 1'!$I$13)>0,"ОСП ДРУГИЕ")} -> ЦСП | E10: =IF(SUM('Раздел 1'!$D$12)>0,SUM('Раздел 1'!$D$13),"") -> 0 | F10: {=_xlfn.IFS(SUM('Раздел 1'!$D$19)>0,"РФ",SUM('Раздел 1'!$E$19)>0,"СУБЪЕКТ",SUM('Раздел 1'!$F$19:$G$19)>0,"МУНИЦИПАЛ",SUM('Раздел 1'!$H$19:$I$19)>0,"ИНЫЕ")} -> #N/A | G10: 1 | H10: 2 | I10: 3 | J10: 4 | K10: 5 | L10: 6 | M10: 7 | N10: 8 | O10: 9 | P10: 10 | Q10: 11 | R10: 12 | S10: 13 | T10: 14 | U10: 15 | V10: 16 | W10: 17 | X10: 18 | Y10: 19 | Z10: 20 | AA10: 21 | AB10: 22 | AC10: 23 | AD10: 24 | AE10: 25 | AF10: 26 | AG10: 27 | AH10: 28 | AI10: 29 | AJ10: 30 | AK10: 31 | AL10: 32 | AM10: 33 | AN10: 34 | AO10: 35 | AP10: 36 | AQ10: 37 | AR10: 38 | AS10: 39 | AT10: 40 | AU10: 41 | AV10: 42 | AW10: 43 | AX10: 44 | AY10: 45 | AZ10: 46 | BA10: 47 | BB10: 48 | BC10: 49 | BD10: 50 | BE10: 51 | BF10: 52 | BG10: 53 | BH10: 54 | BI10: 55 | BJ10: 56 | BK10: 57 | BL10: 58 | BM10: 59
F11: НЕОЛИМП | G11: Авиамодельный спорт | H11: 01 | I11: =SUM(J11:L11) -> 0 | J11: =O11+T11+Y11+AD11+AI11+AN11+AS11+AX11+BC11+BH11 -> 0 | K11: =P11+U11+Z11+AE11+AJ11+AO11+AT11+AY11+BD11+BI11 -> 0 | L11: =Q11+V11+AA11+AF11+AK11+AP11+AU11+AZ11+BE11+BJ11 -> 0 | M11: =R11+W11+AB11+AG11+AL11+AQ11+AV11+BA11+BF11+BK11 -> 0 | N11: =S11+X11+AC11+AH11+AM11+AR11+AW11+BB11+BG11+BL11 -> 0 | BM11: =SUM(I11:BL11) -> 0
F12: НЕОЛИМП | G12: Авиационные гонки | H12: 02 | I12: =SUM(J12:L12) -> 0 | J12: =O12+T12+Y12+AD12+AI12+AN12+AS12+AX12+BC12+BH12 -> 0 | K12: =P12+U12+Z12+AE12+AJ12+AO12+AT12+AY12+BD12+BI12 -> 0 | L12: =Q12+V12+AA12+AF12+AK12+AP12+AU12+AZ12+BE12+BJ12 -> 0 | M12: =R12+W12+AB12+AG12+AL12+AQ12+AV12+BA12+BF12+BK12 -> 0 | N12: =S12+X12+AC12+AH12+AM12+AR12+AW12+BB12+BG12+BL12 -> 0 | BM12: =SUM(I12:BL12) -> 0
F13: НЕОЛИМП | G13: Автомобильный спорт | H13: 03 | I13: =SUM(J13:L13) -> 0 | J13: =O13+T13+Y13+AD13+AI13+AN13+AS13+AX13+BC13+BH13 -> 0 | K13: =P13+U13+Z13+AE13+AJ13+AO13+AT13+AY13+BD13+BI13 -> 0 | L13: =Q13+V13+AA13+AF13+AK13+AP13+AU13+AZ13+BE13+BJ13 -> 0 | M13: =R13+W13+AB13+AG13+AL13+AQ13+AV13+BA13+BF13+BK13 -> 0 | N13: =S13+X13+AC13+AH13+AM13+AR13+AW13+BB13+BG13+BL13 -> 0 | BM13: =SUM(I13:BL13) -> 0
F14: НЕОЛИМП | G14: Автомодельный спорт | H14: 04 | I14: =SUM(J14:L14) -> 0 | J14: =O14+T14+Y14+AD14+AI14+AN14+AS14+AX14+BC14+BH14 -> 0 | K14: =P14+U14+Z14+AE14+AJ14+AO14+AT14+AY14+BD14+BI14 -> 0 | L14: =Q14+V14+AA14+AF14+AK14+AP14+AU14+AZ14+BE14+BJ14 -> 0 | M14: =R14+W14+AB14+AG14+AL14+AQ14+AV14+BA14+BF14+BK14 -> 0 | N14: =S14+X14+AC14+AH14+AM14+AR14+AW14+BB14+BG14+BL14 -> 0 | BM14: =SUM(I14:BL14) -> 0
F15: НЕОЛИМП | G15: Айкидо | H15: 05 | I15: =SUM(J15:L15) -> 0 | J15: =O15+T15+Y15+AD15+AI15+AN15+AS15+AX15+BC15+BH15 -> 0 | K15: =P15+U15+Z15+AE15+AJ15+AO15+AT15+AY15+BD15+BI15 -> 0 | L15: =Q15+V15+AA15+AF15+AK15+AP15+AU15+AZ15+BE15+BJ15 -> 0 | M15: =R15+W15+AB15+AG15+AL15+AQ15+AV15+BA15+BF15+BK15 -> 0 | N15: =S15+X15+AC15+AH15+AM15+AR15+AW15+BB15+BG15+BL15 -> 0 | BM15: =SUM(I15:BL15) -> 0
F16: НЕОЛИМП | G16: Акробатический рок-н-ролл | H16: 06 | I16: =SUM(J16:L16) -> 0 | J16: =O16+T16+Y16+AD16+AI16+AN16+AS16+AX16+BC16+BH16 -> 0 | K16: =P16+U16+Z16+AE16+AJ16+AO16+AT16+AY16+BD16+BI16 -> 0 | L16: =Q16+V16+AA16+AF16+AK16+AP16+AU16+AZ16+BE16+BJ16 -> 0 | M16: =R16+W16+AB16+AG16+AL16+AQ16+AV16+BA16+BF16+BK16 -> 0 | N16: =S16+X16+AC16+AH16+AM16+AR16+AW16+BB16+BG16+BL16 -> 0 | BM16: =SUM(I16:BL16) -> 0
F17: ОЛИМП зима | G17: Альпинизм - всего | H17: 07 | I17: =SUM(J17:L17) -> 0 | J17: =O17+T17+Y17+AD17+AI17+AN17+AS17+AX17+BC17+BH17 -> 0 | K17: =P17+U17+Z17+AE17+AJ17+AO17+AT17+AY17+BD17+BI17 -> 0 | L17: =Q17+V17+AA17+AF17+AK17+AP17+AU17+AZ17+BE17+BJ17 -> 0 | M17: =R17+W17+AB17+AG17+AL17+AQ17+AV17+BA17+BF17+BK17 -> 0 | N17: =S17+X17+AC17+AH17+AM17+AR17+AW17+BB17+BG17+BL17 -> 0 | O17: =SUM(O18:O19) -> 0 | P17: =SUM(P18:P19) -> 0 | Q17: =SUM(Q18:Q19) -> 0 | R17: =SUM(R18:R19) -> 0 | S17: =SUM(S18:S19) -> 0 | T17: =SUM(T18:T19) -> 0 | U17: =SUM(U18:U19) -> 0 | V17: =SUM(V18:V19) -> 0 | ... BL17: =SUM(BL18:BL19) -> 0 | BM17: =SUM(I17:BL17) -> 0
F18: ОЛИМП зима | G18: в том числе: Ски-альпинизм | H18: 08 | I18: =SUM(J18:L18) -> 0 | J18: =O18+T18+Y18+AD18+AI18+AN18+AS18+AX18+BC18+BH18 -> 0 | K18: =P18+U18+Z18+AE18+AJ18+AO18+AT18+AY18+BD18+BI18 -> 0 | L18: =Q18+V18+AA18+AF18+AK18+AP18+AU18+AZ18+BE18+BJ18 -> 0 | M18: =R18+W18+AB18+AG18+AL18+AQ18+AV18+BA18+BF18+BK18 -> 0 | N18: =S18+X18+AC18+AH18+AM18+AR18+AW18+BB18+BG18+BL18 -> 0 | BM18: =SUM(I18:BL18) -> 0
F19: ОЛИМП зима | G19: Иные дисциплины вида спорта "альпинизм" | H19: 09 | I19: =SUM(J19:L19) -> 0 | J19: =O19+T19+Y19+AD19+AI19+AN19+AS19+AX19+BC19+BH19 -> 0 | K19: =P19+U19+Z19+AE19+AJ19+AO19+AT19+AY19+BD19+BI19 -> 0 | L19: =Q19+V19+AA19+AF19+AK19+AP19+AU19+AZ19+BE19+BJ19 -> 0 | M19: =R19+W19+AB19+AG19+AL19+AQ19+AV19+BA19+BF19+BK19 -> 0 | N19: =S19+X19+AC19+AH19+AM19+AR19+AW19+BB19+BG19+BL19 -> 0 | BM19: =SUM(I19:BL19) -> 0
F20: ОЛИМП лето | G20: Американский футбол | H20: 10 | I20: =SUM(J20:L20) -> 0 | J20: =O20+T20+Y20+AD20+AI20+AN20+AS20+AX20+BC20+BH20 -> 0 | K20: =P20+U20+Z20+AE20+AJ20+AO20+AT20+AY20+BD20+BI20 -> 0 | L20: =Q20+V20+AA20+AF20+AK20+AP20+AU20+AZ20+BE20+BJ20 -> 0 | M20: =R20+W20+AB20+AG20+AL20+AQ20+AV20+BA20+BF20+BK20 -> 0 | N20: =S20+X20+AC20+AH20+AM20+AR20+AW20+BB20+BG20+BL20 -> 0 | BM20: =SUM(I20:BL20) -> 0
F21: ПРИКЛАДН | G21: Армейская высокоточная стрельба | H21: 11 | I21: =SUM(J21:L21) -> 0 | J21: =O21+T21+Y21+AD21+AI21+AN21+AS21+AX21+BC21+BH21 -> 0 | K21: =P21+U21+Z21+AE21+AJ21+AO21+AT21+AY21+BD21+BI21 -> 0 | L21: =Q21+V21+AA21+AF21+AK21+AP21+AU21+AZ21+BE21+BJ21 -> 0 | M21: =R21+W21+AB21+AG21+AL21+AQ21+AV21+BA21+BF21+BK21 -> 0 | N21: =S21+X21+AC21+AH21+AM21+AR21+AW21+BB21+BG21+BL21 -> 0 | BM21: =SUM(I21:BL21) -> 0
F22: ПРИКЛАДН | G22: Армейский рукопашный бой | H22: 12 | I22: =SUM(J22:L22) -> 0 | J22: =O22+T22+Y22+AD22+AI22+AN22+AS22+AX22+BC22+BH22 -> 0 | K22: =P22+U22+Z22+AE22+AJ22+AO22+AT22+AY22+BD22+BI22 -> 0 | L22: =Q22+V22+AA22+AF22+AK22+AP22+AU22+AZ22+BE22+BJ22 -> 0 | M22: =R22+W22+AB22+AG22+AL22+AQ22+AV22+BA22+BF22+BK22 -> 0 | N22: =S22+X22+AC22+AH22+AM22+AR22+AW22+BB22+BG22+BL22 -> 0 | BM22: =SUM(I22:BL22) -> 0
F23: ПРИКЛАДН | G23: Армейское тактико-стрелковое многоборье | H23: 13 | I23: =SUM(J23:L23) -> 0 | J23: =O23+T23+Y23+AD23+AI23+AN23+AS23+AX23+BC23+BH23 -> 0 | K23: =P23+U23+Z23+AE23+AJ23+AO23+AT23+AY23+BD23+BI23 -> 0 | L23: =Q23+V23+AA23+AF23+AK23+AP23+AU23+AZ23+BE23+BJ23 -> 0 | M23: =R23+W23+AB23+AG23+AL23+AQ23+AV23+BA23+BF23+BK23 -> 0 | N23: =S23+X23+AC23+AH23+AM23+AR23+AW23+BB23+BG23+BL23 -> 0 | BM23: =SUM(I23:BL23) -> 0
F24: НЕОЛИМП | G24: Армрестлинг | H24: 14 | I24: =SUM(J24:L24) -> 0 | J24: =O24+T24+Y24+AD24+AI24+AN24+AS24+AX24+BC24+BH24 -> 0 | K24: =P24+U24+Z24+AE24+AJ24+AO24+AT24+AY24+BD24+BI24 -> 0 | L24: =Q24+V24+AA24+AF24+AK24+AP24+AU24+AZ24+BE24+BJ24 -> 0 | M24: =R24+W24+AB24+AG24+AL24+AQ24+AV24+BA24+BF24+BK24 -> 0 | N24: =S24+X24+AC24+AH24+AM24+AR24+AW24+BB24+BG24+BL24 -> 0 | BM24: =SUM(I24:BL24) -> 0
F25: ОЛИМП лето | G25: Бадминтон | H25: 15 | I25: =SUM(J25:L25) -> 0 | J25: =O25+T25+Y25+AD25+AI25+AN25+AS25+AX25+BC25+BH25 -> 0 | K25: =P25+U25+Z25+AE25+AJ25+AO25+AT25+AY25+BD25+BI25 -> 0 | L25: =Q25+V25+AA25+AF25+AK25+AP25+AU25+AZ25+BE25+BJ25 -> 0 | M25: =R25+W25+AB25+AG25+AL25+AQ25+AV25+BA25+BF25+BK25 -> 0 | N25: =S25+X25+AC25+AH25+AM25+AR25+AW25+BB25+BG25+BL25 -> 0 | BM25: =SUM(I25:BL25) -> 0
F26: ОЛИМП лето | G26: Баскетбол - всего | H26: 16 | I26: =SUM(J26:L26) -> 0 | J26: =O26+T26+Y26+AD26+AI26+AN26+AS26+AX26+BC26+BH26 -> 0 | K26: =P26+U26+Z26+AE26+AJ26+AO26+AT26+AY26+BD26+BI26 -> 0 | L26: =Q26+V26+AA26+AF26+AK26+AP26+AU26+AZ26+BE26+BJ26 -> 0 | M26: =R26+W26+AB26+AG26+AL26+AQ26+AV26+BA26+BF26+BK26 -> 0 | N26: =S26+X26+AC26+AH26+AM26+AR26+AW26+BB26+BG26+BL26 -> 0 | O26: =SUM(O27:O30) -> 0 | P26: =SUM(P27:P30) -> 0 | Q26: =SUM(Q27:Q30) -> 0 | R26: =SUM(R27:R30) -> 0 | S26: =SUM(S27:S30) -> 0 | T26: =SUM(T27:T30) -> 0 | U26: =SUM(U27:U30) -> 0 | V26: =SUM(V27:V30) -> 0 | ... BL26: =SUM(BL27:BL30) -> 0 | BM26: =SUM(I26:BL26) -> 0
F27: ОЛИМП лето | G27: в том числе: Баскетбол | H27: 17 | I27: =SUM(J27:L27) -> 0 | J27: =O27+T27+Y27+AD27+AI27+AN27+AS27+AX27+BC27+BH27 -> 0 | K27: =P27+U27+Z27+AE27+AJ27+AO27+AT27+AY27+BD27+BI27 -> 0 | L27: =Q27+V27+AA27+AF27+AK27+AP27+AU27+AZ27+BE27+BJ27 -> 0 | M27: =R27+W27+AB27+AG27+AL27+AQ27+AV27+BA27+BF27+BK27 -> 0 | N27: =S27+X27+AC27+AH27+AM27+AR27+AW27+BB27+BG27+BL27 -> 0 | BM27: =SUM(I27:BL27) -> 0
F28: ОЛИМП лето | G28: Баскетбол 3х3 | H28: 18 | I28: =SUM(J28:L28) -> 0 | J28: =O28+T28+Y28+AD28+AI28+AN28+AS28+AX28+BC28+BH28 -> 0 | K28: =P28+U28+Z28+AE28+AJ28+AO28+AT28+AY28+BD28+BI28 -> 0 | L28: =Q28+V28+AA28+AF28+AK28+AP28+AU28+AZ28+BE28+BJ28 -> 0 | M28: =R28+W28+AB28+AG28+AL28+AQ28+AV28+BA28+BF28+BK28 -> 0 | N28: =S28+X28+AC28+AH28+AM28+AR28+AW28+BB28+BG28+BL28 -> 0 | BM28: =SUM(I28:BL28) -> 0
F29: ОЛИМП лето | G29: Интерактивный баскетбол | H29: 19 | I29: =SUM(J29:L29) -> 0 | J29: =O29+T29+Y29+AD29+AI29+AN29+AS29+AX29+BC29+BH29 -> 0 | K29: =P29+U29+Z29+AE29+AJ29+AO29+AT29+AY29+BD29+BI29 -> 0 | L29: =Q29+V29+AA29+AF29+AK29+AP29+AU29+AZ29+BE29+BJ29 -> 0 | M29: =R29+W29+AB29+AG29+AL29+AQ29+AV29+BA29+BF29+BK29 -> 0 | N29: =S29+X29+AC29+AH29+AM29+AR29+AW29+BB29+BG29+BL29 -> 0 | BM29: =SUM(I29:BL29) -> 0
F30: ОЛИМП лето | G30: Иные дисциплины вида спорта "баскетбол" | H30: 20 | I30: =SUM(J30:L30) -> 0 | J30: =O30+T30+Y30+AD30+AI30+AN30+AS30+AX30+BC30+BH30 -> 0 | K30: =P30+U30+Z30+AE30+AJ30+AO30+AT30+AY30+BD30+BI30 -> 0 | L30: =Q30+V30+AA30+AF30+AK30+AP30+AU30+AZ30+BE30+BJ30 -> 0 | M30: =R30+W30+AB30+AG30+AL30+AQ30+AV30+BA30+BF30+BK30 -> 0 | N30: =S30+X30+AC30+AH30+AM30+AR30+AW30+BB30+BG30+BL30 -> 0 | BM30: =SUM(I30:BL30) -> 0
F31: ОЛИМП лето | G31: Бейсбол | H31: 21 | I31: =SUM(J31:L31) -> 0 | J31: =O31+T31+Y31+AD31+AI31+AN31+AS31+AX31+BC31+BH31 -> 0 | K31: =P31+U31+Z31+AE31+AJ31+AO31+AT31+AY31+BD31+BI31 -> 0 | L31: =Q31+V31+AA31+AF31+AK31+AP31+AU31+AZ31+BE31+BJ31 -> 0 | M31: =R31+W31+AB31+AG31+AL31+AQ31+AV31+BA31+BF31+BK31 -> 0 | N31: =S31+X31+AC31+AH31+AM31+AR31+AW31+BB31+BG31+BL31 -> 0 | BM31: =SUM(I31:BL31) -> 0
F32: ОЛИМП зима | G32: Биатлон | H32: 22 | I32: =SUM(J32:L32) -> 0 | J32: =O32+T32+Y32+AD32+AI32+AN32+AS32+AX32+BC32+BH32 -> 0 | K32: =P32+U32+Z32+AE32+AJ32+AO32+AT32+AY32+BD32+BI32 -> 0 | L32: =Q32+V32+AA32+AF32+AK32+AP32+AU32+AZ32+BE32+BJ32 -> 0 | M32: =R32+W32+AB32+AG32+AL32+AQ32+AV32+BA32+BF32+BK32 -> 0 | N32: =S32+X32+AC32+AH32+AM32+AR32+AW32+BB32+BG32+BL32 -> 0 | BM32: =SUM(I32:BL32) -> 0
F33: НЕОЛИМП | G33: Бильярдный спорт | H33: 23 | I33: =SUM(J33:L33) -> 0 | J33: =O33+T33+Y33+AD33+AI33+AN33+AS33+AX33+BC33+BH33 -> 0 | K33: =P33+U33+Z33+AE33+AJ33+AO33+AT33+AY33+BD33+BI33 -> 0 | L33: =Q33+V33+AA33+AF33+AK33+AP33+AU33+AZ33+BE33+BJ33 -> 0 | M33: =R33+W33+AB33+AG33+AL33+AQ33+AV33+BA33+BF33+BK33 -> 0 | N33: =S33+X33+AC33+AH33+AM33+AR33+AW33+BB33+BG33+BL33 -> 0 | BM33: =SUM(I33:BL33) -> 0
F34: ОЛИМП зима | G34: Бобслей - всего | H34: 24 | I34: =SUM(J34:L34) -> 0 | J34: =O34+T34+Y34+AD34+AI34+AN34+AS34+AX34+BC34+BH34 -> 0 | K34: =P34+U34+Z34+AE34+AJ34+AO34+AT34+AY34+BD34+BI34 -> 0 | L34: =Q34+V34+AA34+AF34+AK34+AP34+AU34+AZ34+BE34+BJ34 -> 0 | M34: =R34+W34+AB34+AG34+AL34+AQ34+AV34+BA34+BF34+BK34 -> 0 | N34: =S34+X34+AC34+AH34+AM34+AR34+AW34+BB34+BG34+BL34 -> 0 | O34: =SUM(O35:O38) -> 0 | P34: =SUM(P35:P38) -> 0 | Q34: =SUM(Q35:Q38) -> 0 | R34: =SUM(R35:R38) -> 0 | S34: =SUM(S35:S38) -> 0 | T34: =SUM(T35:T38) -> 0 | U34: =SUM(U35:U38) -> 0 | V34: =SUM(V35:V38) -> 0 | ... BL34: =SUM(BL35:BL38) -> 0 | BM34: =SUM(I34:BL34) -> 0
F35: ОЛИМП зима | G35: в том числе: Скелетон | H35: 25 | I35: =SUM(J35:L35) -> 0 | J35: =O35+T35+Y35+AD35+AI35+AN35+AS35+AX35+BC35+BH35 -> 0 | K35: =P35+U35+Z35+AE35+AJ35+AO35+AT35+AY35+BD35+BI35 -> 0 | L35: =Q35+V35+AA35+AF35+AK35+AP35+AU35+AZ35+BE35+BJ35 -> 0 | M35: =R35+W35+AB35+AG35+AL35+AQ35+AV35+BA35+BF35+BK35 -> 0 | N35: =S35+X35+AC35+AH35+AM35+AR35+AW35+BB35+BG35+BL35 -> 0 | BM35: =SUM(I35:BL35) -> 0
F36: ОЛИМП зима | G36: Экипаж | H36: 26 | I36: =SUM(J36:L36) -> 0 | J36: =O36+T36+Y36+AD36+AI36+AN36+AS36+AX36+BC36+BH36 -> 0 | K36: =P36+U36+Z36+AE36+AJ36+AO36+AT36+AY36+BD36+BI36 -> 0 | L36: =Q36+V36+AA36+AF36+AK36+AP36+AU36+AZ36+BE36+BJ36 -> 0 | M36: =R36+W36+AB36+AG36+AL36+AQ36+AV36+BA36+BF36+BK36 -> 0 | N36: =S36+X36+AC36+AH36+AM36+AR36+AW36+BB36+BG36+BL36 -> 0 | BM36: =SUM(I36:BL36) -> 0
F37: ОЛИМП зима | G37: Монобоб | H37: 27 | I37: =SUM(J37:L37) -> 0 | J37: =O37+T37+Y37+AD37+AI37+AN37+AS37+AX37+BC37+BH37 -> 0 | K37: =P37+U37+Z37+AE37+AJ37+AO37+AT37+AY37+BD37+BI37 -> 0 | L37: =Q37+V37+AA37+AF37+AK37+AP37+AU37+AZ37+BE37+BJ37 -> 0 | M37: =R37+W37+AB37+AG37+AL37+AQ37+AV37+BA37+BF37+BK37 -> 0 | N37: =S37+X37+AC37+AH37+AM37+AR37+AW37+BB37+BG37+BL37 -> 0 | BM37: =SUM(I37:BL37) -> 0
F38: ОЛИМП зима | G38: Иные дисциплины вида спорта "бобслей" | H38: 28 | I38: =SUM(J38:L38) -> 0 | J38: =O38+T38+Y38+AD38+AI38+AN38+AS38+AX38+BC38+BH38 -> 0 | K38: =P38+U38+Z38+AE38+AJ38+AO38+AT38+AY38+BD38+BI38 -> 0 | L38: =Q38+V38+AA38+AF38+AK38+AP38+AU38+AZ38+BE38+BJ38 -> 0 | M38: =R38+W38+AB38+AG38+AL38+AQ38+AV38+BA38+BF38+BK38 -> 0 | N38: =S38+X38+AC38+AH38+AM38+AR38+AW38+BB38+BG38+BL38 -> 0 | BM38: =SUM(I38:BL38) -> 0
F39: НЕОЛИМП | G39: Бодибилдинг | H39: 29 | I39: =SUM(J39:L39) -> 0 | J39: =O39+T39+Y39+AD39+AI39+AN39+AS39+AX39+BC39+BH39 -> 0 | K39: =P39+U39+Z39+AE39+AJ39+AO39+AT39+AY39+BD39+BI39 -> 0 | L39: =Q39+V39+AA39+AF39+AK39+AP39+AU39+AZ39+BE39+BJ39 -> 0 | M39: =R39+W39+AB39+AG39+AL39+AQ39+AV39+BA39+BF39+BK39 -> 0 | N39: =S39+X39+AC39+AH39+AM39+AR39+AW39+BB39+BG39+BL39 -> 0 | BM39: =SUM(I39:BL39) -> 0
F40: ОЛИМП лето | G40: Бокс | H40: 30 | I40: =SUM(J40:L40) -> 0 | J40: =O40+T40+Y40+AD40+AI40+AN40+AS40+AX40+BC40+BH40 -> 0 | K40: =P40+U40+Z40+AE40+AJ40+AO40+AT40+AY40+BD40+BI40 -> 0 | L40: =Q40+V40+AA40+AF40+AK40+AP40+AU40+AZ40+BE40+BJ40 -> 0 | M40: =R40+W40+AB40+AG40+AL40+AQ40+AV40+BA40+BF40+BK40 -> 0 | N40: =S40+X40+AC40+AH40+AM40+AR40+AW40+BB40+BG40+BL40 -> 0 | BM40: =SUM(I40:BL40) -> 0
F41: НЕОЛИМП | G41: Борьба на поясах | H41: 31 | I41: =SUM(J41:L41) -> 0 | J41: =O41+T41+Y41+AD41+AI41+AN41+AS41+AX41+BC41+BH41 -> 0 | K41: =P41+U41+Z41+AE41+AJ41+AO41+AT41+AY41+BD41+BI41 -> 0 | L41: =Q41+V41+AA41+AF41+AK41+AP41+AU41+AZ41+BE41+BJ41 -> 0 | M41: =R41+W41+AB41+AG41+AL41+AQ41+AV41+BA41+BF41+BK41 -> 0 | N41: =S41+X41+AC41+AH41+AM41+AR41+AW41+BB41+BG41+BL41 -> 0 | BM41: =SUM(I41:BL41) -> 0
F42: НЕОЛИМП | G42: Боулинг | H42: 32 | I42: =SUM(J42:L42) -> 0 | J42: =O42+T42+Y42+AD42+AI42+AN42+AS42+AX42+BC42+BH42 -> 0 | K42: =P42+U42+Z42+AE42+AJ42+AO42+AT42+AY42+BD42+BI42 -> 0 | L42: =Q42+V42+AA42+AF42+AK42+AP42+AU42+AZ42+BE42+BJ42 -> 0 | M42: =R42+W42+AB42+AG42+AL42+AQ42+AV42+BA42+BF42+BK42 -> 0 | N42: =S42+X42+AC42+AH42+AM42+AR42+AW42+BB42+BG42+BL42 -> 0 | BM42: =SUM(I42:BL42) -> 0
F43: НЕОЛИМП | G43: Боулспорт | H43: 33 | I43: =SUM(J43:L43) -> 0 | J43: =O43+T43+Y43+AD43+AI43+AN43+AS43+AX43+BC43+BH43 -> 0 | K43: =P43+U43+Z43+AE43+AJ43+AO43+AT43+AY43+BD43+BI43 -> 0 | L43: =Q43+V43+AA43+AF43+AK43+AP43+AU43+AZ43+BE43+BJ43 -> 0 | M43: =R43+W43+AB43+AG43+AL43+AQ43+AV43+BA43+BF43+BK43 -> 0 | N43: =S43+X43+AC43+AH43+AM43+AR43+AW43+BB43+BG43+BL43 -> 0 | BM43: =SUM(I43:BL43) -> 0
F44: НЕОЛИМП | G44: Брейкинг | H44: 34 | I44: =SUM(J44:L44) -> 0 | J44: =O44+T44+Y44+AD44+AI44+AN44+AS44+AX44+BC44+BH44 -> 0 | K44: =P44+U44+Z44+AE44+AJ44+AO44+AT44+AY44+BD44+BI44 -> 0 | L44: =Q44+V44+AA44+AF44+AK44+AP44+AU44+AZ44+BE44+BJ44 -> 0 | M44: =R44+W44+AB44+AG44+AL44+AQ44+AV44+BA44+BF44+BK44 -> 0 | N44: =S44+X44+AC44+AH44+AM44+AR44+AW44+BB44+BG44+BL44 -> 0 | BM44: =SUM(I44:BL44) -> 0
F45: ОЛИМП лето | G45: Велосипедный спорт - всего | H45: 35 | I45: =SUM(J45:L45) -> 0 | J45: =O45+T45+Y45+AD45+AI45+AN45+AS45+AX45+BC45+BH45 -> 0 | K45: =P45+U45+Z45+AE45+AJ45+AO45+AT45+AY45+BD45+BI45 -> 0 | L45: =Q45+V45+AA45+AF45+AK45+AP45+AU45+AZ45+BE45+BJ45 -> 0 | M45: =R45+W45+AB45+AG45+AL45+AQ45+AV45+BA45+BF45+BK45 -> 0 | N45: =S45+X45+AC45+AH45+AM45+AR45+AW45+BB45+BG45+BL45 -> 0 | O45: =SUM(O46:O51) -> 0 | P45: =SUM(P46:P51) -> 0 | Q45: =SUM(Q46:Q51) -> 0 | R45: =SUM(R46:R51) -> 0 | S45: =SUM(S46:S51) -> 0 | T45: =SUM(T46:T51) -> 0 | U45: =SUM(U46:U51) -> 0 | V45: =SUM(V46:V51) -> 0 | ... BL45: =SUM(BL46:BL51) -> 0 | BM45: =SUM(I45:BL45) -> 0
F46: ОЛИМП лето | G46: в том числе: BMX (гонка, эстафета) | H46: 36 | I46: =SUM(J46:L46) -> 0 | J46: =O46+T46+Y46+AD46+AI46+AN46+AS46+AX46+BC46+BH46 -> 0 | K46: =P46+U46+Z46+AE46+AJ46+AO46+AT46+AY46+BD46+BI46 -> 0 | L46: =Q46+V46+AA46+AF46+AK46+AP46+AU46+AZ46+BE46+BJ46 -> 0 | M46: =R46+W46+AB46+AG46+AL46+AQ46+AV46+BA46+BF46+BK46 -> 0 | N46: =S46+X46+AC46+AH46+AM46+AR46+AW46+BB46+BG46+BL46 -> 0 | BM46: =SUM(I46:BL46) -> 0
F47: ОЛИМП лето | G47: BMX - фристайл | H47: 37 | I47: =SUM(J47:L47) -> 0 | J47: =O47+T47+Y47+AD47+AI47+AN47+AS47+AX47+BC47+BH47 -> 0 | K47: =P47+U47+Z47+AE47+AJ47+AO47+AT47+AY47+BD47+BI47 -> 0 | L47: =Q47+V47+AA47+AF47+AK47+AP47+AU47+AZ47+BE47+BJ47 -> 0 | M47: =R47+W47+AB47+AG47+AL47+AQ47+AV47+BA47+BF47+BK47 -> 0 | N47: =S47+X47+AC47+AH47+AM47+AR47+AW47+BB47+BG47+BL47 -> 0 | BM47: =SUM(I47:BL47) -> 0
F48: ОЛИМП лето | G48: Маунтинбайк | H48: 38 | I48: =SUM(J48:L48) -> 0 | J48: =O48+T48+Y48+AD48+AI48+AN48+AS48+AX48+BC48+BH48 -> 0 | K48: =P48+U48+Z48+AE48+AJ48+AO48+AT48+AY48+BD48+BI48 -> 0 | L48: =Q48+V48+AA48+AF48+AK48+AP48+AU48+AZ48+BE48+BJ48 -> 0 | M48: =R48+W48+AB48+AG48+AL48+AQ48+AV48+BA48+BF48+BK48 -> 0 | N48: =S48+X48+AC48+AH48+AM48+AR48+AW48+BB48+BG48+BL48 -> 0 | BM48: =SUM(I48:BL48) -> 0
F49: ОЛИМП лето | G49: Трек | H49: 39 | I49: =SUM(J49:L49) -> 0 | J49: =O49+T49+Y49+AD49+AI49+AN49+AS49+AX49+BC49+BH49 -> 0 | K49: =P49+U49+Z49+AE49+AJ49+AO49+AT49+AY49+BD49+BI49 -> 0 | L49: =Q49+V49+AA49+AF49+AK49+AP49+AU49+AZ49+BE49+BJ49 -> 0 | M49: =R49+W49+AB49+AG49+AL49+AQ49+AV49+BA49+BF49+BK49 -> 0 | N49: =S49+X49+AC49+AH49+AM49+AR49+AW49+BB49+BG49+BL49 -> 0 | BM49: =SUM(I49:BL49) -> 0
F50: ОЛИМП лето | G50: Шоссе | H50: 40 | I50: =SUM(J50:L50) -> 0 | J50: =O50+T50+Y50+AD50+AI50+AN50+AS50+AX50+BC50+BH50 -> 0 | K50: =P50+U50+Z50+AE50+AJ50+AO50+AT50+AY50+BD50+BI50 -> 0 | L50: =Q50+V50+AA50+AF50+AK50+AP50+AU50+AZ50+BE50+BJ50 -> 0 | M50: =R50+W50+AB50+AG50+AL50+AQ50+AV50+BA50+BF50+BK50 -> 0 | N50: =S50+X50+AC50+AH50+AM50+AR50+AW50+BB50+BG50+BL50 -> 0 | BM50: =SUM(I50:BL50) -> 0
F51: ОЛИМП лето | G51: Технический симулятор | H51: 41 | I51: =SUM(J51:L51) -> 0 | J51: =O51+T51+Y51+AD51+AI51+AN51+AS51+AX51+BC51+BH51 -> 0 | K51: =P51+U51+Z51+AE51+AJ51+AO51+AT51+AY51+BD51+BI51 -> 0 | L51: =Q51+V51+AA51+AF51+AK51+AP51+AU51+AZ51+BE51+BJ51 -> 0 | M51: =R51+W51+AB51+AG51+AL51+AQ51+AV51+BA51+BF51+BK51 -> 0 | N51: =S51+X51+AC51+AH51+AM51+AR51+AW51+BB51+BG51+BL51 -> 0 | BM51: =SUM(I51:BL51) -> 0
F52: НЕОЛИМП | G52: Вертолетный спорт | H52: 42 | I52: =SUM(J52:L52) -> 0 | J52: =O52+T52+Y52+AD52+AI52+AN52+AS52+AX52+BC52+BH52 -> 0 | K52: =P52+U52+Z52+AE52+AJ52+AO52+AT52+AY52+BD52+BI52 -> 0 | L52: =Q52+V52+AA52+AF52+AK52+AP52+AU52+AZ52+BE52+BJ52 -> 0 | M52: =R52+W52+AB52+AG52+AL52+AQ52+AV52+BA52+BF52+BK52 -> 0 | N52: =S52+X52+AC52+AH52+AM52+AR52+AW52+BB52+BG52+BL52 -> 0 | BM52: =SUM(I52:BL52) -> 0
F53: ОЛИМП лето | G53: Водное поло - всего | H53: 43 | I53: =SUM(J53:L53) -> 0 | J53: =O53+T53+Y53+AD53+AI53+AN53+AS53+AX53+BC53+BH53 -> 0 | K53: =P53+U53+Z53+AE53+AJ53+AO53+AT53+AY53+BD53+BI53 -> 0 | L53: =Q53+V53+AA53+AF53+AK53+AP53+AU53+AZ53+BE53+BJ53 -> 0 | M53: =R53+W53+AB53+AG53+AL53+AQ53+AV53+BA53+BF53+BK53 -> 0 | N53: =S53+X53+AC53+AH53+AM53+AR53+AW53+BB53+BG53+BL53 -> 0 | O53: =SUM(O54:O55) -> 0 | P53: =SUM(P54:P55) -> 0 | Q53: =SUM(Q54:Q55) -> 0 | R53: =SUM(R54:R55) -> 0 | S53: =SUM(S54:S55) -> 0 | T53: =SUM(T54:T55) -> 0 | U53: =SUM(U54:U55) -> 0 | V53: =SUM(V54:V55) -> 0 | ... BL53: =SUM(BL54:BL55) -> 0 | BM53: =SUM(I53:BL53) -> 0
F54: ОЛИМП лето | G54: в том числе: Водное поло | H54: 44 | I54: =SUM(J54:L54) -> 0 | J54: =O54+T54+Y54+AD54+AI54+AN54+AS54+AX54+BC54+BH54 -> 0 | K54: =P54+U54+Z54+AE54+AJ54+AO54+AT54+AY54+BD54+BI54 -> 0 | L54: =Q54+V54+AA54+AF54+AK54+AP54+AU54+AZ54+BE54+BJ54 -> 0 | M54: =R54+W54+AB54+AG54+AL54+AQ54+AV54+BA54+BF54+BK54 -> 0 | N54: =S54+X54+AC54+AH54+AM54+AR54+AW54+BB54+BG54+BL54 -> 0 | BM54: =SUM(I54:BL54) -> 0
F55: ОЛИМП лето | G55: Иные дисциплины вида спорта "водное поло" | H55: 45 | I55: =SUM(J55:L55) -> 0 | J55: =O55+T55+Y55+AD55+AI55+AN55+AS55+AX55+BC55+BH55 -> 0 | K55: =P55+U55+Z55+AE55+AJ55+AO55+AT55+AY55+BD55+BI55 -> 0 | L55: =Q55+V55+AA55+AF55+AK55+AP55+AU55+AZ55+BE55+BJ55 -> 0 | M55: =R55+W55+AB55+AG55+AL55+AQ55+AV55+BA55+BF55+BK55 -> 0 | N55: =S55+X55+AC55+AH55+AM55+AR55+AW55+BB55+BG55+BL55 -> 0 | BM55: =SUM(I55:BL55) -> 0
F56: НЕОЛИМП | G56: Воднолыжный спорт | H56: 46 | I56: =SUM(J56:L56) -> 0 | J56: =O56+T56+Y56+AD56+AI56+AN56+AS56+AX56+BC56+BH56 -> 0 | K56: =P56+U56+Z56+AE56+AJ56+AO56+AT56+AY56+BD56+BI56 -> 0 | L56: =Q56+V56+AA56+AF56+AK56+AP56+AU56+AZ56+BE56+BJ56 -> 0 | M56: =R56+W56+AB56+AG56+AL56+AQ56+AV56+BA56+BF56+BK56 -> 0 | N56: =S56+X56+AC56+AH56+AM56+AR56+AW56+BB56+BG56+BL56 -> 0 | BM56: =SUM(I56:BL56) -> 0
F57: НЕОЛИМП | G57: Водно-моторный спорт | H57: 47 | I57: =SUM(J57:L57) -> 0 | J57: =O57+T57+Y57+AD57+AI57+AN57+AS57+AX57+BC57+BH57 -> 0 | K57: =P57+U57+Z57+AE57+AJ57+AO57+AT57+AY57+BD57+BI57 -> 0 | L57: =Q57+V57+AA57+AF57+AK57+AP57+AU57+AZ57+BE57+BJ57 -> 0 | M57: =R57+W57+AB57+AG57+AL57+AQ57+AV57+BA57+BF57+BK57 -> 0 | N57: =S57+X57+AC57+AH57+AM57+AR57+AW57+BB57+BG57+BL57 -> 0 | BM57: =SUM(I57:BL57) -> 0
F58: НЕОЛИМП | G58: Водно-спасательное многоборье | H58: 48 | I58: =SUM(J58:L58) -> 0 | J58: =O58+T58+Y58+AD58+AI58+AN58+AS58+AX58+BC58+BH58 -> 0 | K58: =P58+U58+Z58+AE58+AJ58+AO58+AT58+AY58+BD58+BI58 -> 0 | L58: =Q58+V58+AA58+AF58+AK58+AP58+AU58+AZ58+BE58+BJ58 -> 0 | M58: =R58+W58+AB58+AG58+AL58+AQ58+AV58+BA58+BF58+BK58 -> 0 | N58: =S58+X58+AC58+AH58+AM58+AR58+AW58+BB58+BG58+BL58 -> 0 | BM58: =SUM(I58:BL58) -> 0
F59: ПРИКЛАДН | G59: Военно-прикладной спорт | H59: 49 | I59: =SUM(J59:L59) -> 0 | J59: =O59+T59+Y59+AD59+AI59+AN59+AS59+AX59+BC59+BH59 -> 0 | K59: =P59+U59+Z59+AE59+AJ59+AO59+AT59+AY59+BD59+BI59 -> 0 | L59: =Q59+V59+AA59+AF59+AK59+AP59+AU59+AZ59+BE59+BJ59 -> 0 | M59: =R59+W59+AB59+AG59+AL59+AQ59+AV59+BA59+BF59+BK59 -> 0 | N59: =S59+X59+AC59+AH59+AM59+AR59+AW59+BB59+BG59+BL59 -> 0 | BM59: =SUM(I59:BL59) -> 0
F60: ПРИКЛАДН | G60: Военно-спортивное многоборье | H60: 50 | I60: =SUM(J60:L60) -> 0 | J60: =O60+T60+Y60+AD60+AI60+AN60+AS60+AX60+BC60+BH60 -> 0 | K60: =P60+U60+Z60+AE60+AJ60+AO60+AT60+AY60+BD60+BI60 -> 0 | L60: =Q60+V60+AA60+AF60+AK60+AP60+AU60+AZ60+BE60+BJ60 -> 0 | M60: =R60+W60+AB60+AG60+AL60+AQ60+AV60+BA60+BF60+BK60 -> 0 | N60: =S60+X60+AC60+AH60+AM60+AR60+AW60+BB60+BG60+BL60 -> 0 | BM60: =SUM(I60:BL60) -> 0
F61: НЕОЛИМП | G61: Воздухоплавательный спорт | H61: 51 | I61: =SUM(J61:L61) -> 0 | J61: =O61+T61+Y61+AD61+AI61+AN61+AS61+AX61+BC61+BH61 -> 0 | K61: =P61+U61+Z61+AE61+AJ61+AO61+AT61+AY61+BD61+BI61 -> 0 | L61: =Q61+V61+AA61+AF61+AK61+AP61+AU61+AZ61+BE61+BJ61 -> 0 | M61: =R61+W61+AB61+AG61+AL61+AQ61+AV61+BA61+BF61+BK61 -> 0 | N61: =S61+X61+AC61+AH61+AM61+AR61+AW61+BB61+BG61+BL61 -> 0 | BM61: =SUM(I61:BL61) -> 0
F62: НЕОЛИМП | G62: Воздушная гимнастика | H62: 52 | I62: =SUM(J62:L62) -> 0 | J62: =O62+T62+Y62+AD62+AI62+AN62+AS62+AX62+BC62+BH62 -> 0 | K62: =P62+U62+Z62+AE62+AJ62+AO62+AT62+AY62+BD62+BI62 -> 0 | L62: =Q62+V62+AA62+AF62+AK62+AP62+AU62+AZ62+BE62+BJ62 -> 0 | M62: =R62+W62+AB62+AG62+AL62+AQ62+AV62+BA62+BF62+BK62 -> 0 | N62: =S62+X62+AC62+AH62+AM62+AR62+AW62+BB62+BG62+BL62 -> 0 | BM62: =SUM(I62:BL62) -> 0
F63: НЕОЛИМП | G63: Воздушно-силовая атлетика | H63: 53 | I63: =SUM(J63:L63) -> 0 | J63: =O63+T63+Y63+AD63+AI63+AN63+AS63+AX63+BC63+BH63 -> 0 | K63: =P63+U63+Z63+AE63+AJ63+AO63+AT63+AY63+BD63+BI63 -> 0 | L63: =Q63+V63+AA63+AF63+AK63+AP63+AU63+AZ63+BE63+BJ63 -> 0 | M63: =R63+W63+AB63+AG63+AL63+AQ63+AV63+BA63+BF63+BK63 -> 0 | N63: =S63+X63+AC63+AH63+AM63+AR63+AW63+BB63+BG63+BL63 -> 0 | BM63: =SUM(I63:BL63) -> 0
F64: ОЛИМП лето | G64: Волейбол - всего | H64: 54 | I64: =SUM(J64:L64) -> 0 | J64: =O64+T64+Y64+AD64+AI64+AN64+AS64+AX64+BC64+BH64 -> 0 | K64: =P64+U64+Z64+AE64+AJ64+AO64+AT64+AY64+BD64+BI64 -> 0 | L64: =Q64+V64+AA64+AF64+AK64+AP64+AU64+AZ64+BE64+BJ64 -> 0 | M64: =R64+W64+AB64+AG64+AL64+AQ64+AV64+BA64+BF64+BK64 -> 0 | N64: =S64+X64+AC64+AH64+AM64+AR64+AW64+BB64+BG64+BL64 -> 0 | O64: =SUM(O65:O67) -> 0 | P64: =SUM(P65:P67) -> 0 | Q64: =SUM(Q65:Q67) -> 0 | R64: =SUM(R65:R67) -> 0 | S64: =SUM(S65:S67) -> 0 | T64: =SUM(T65:T67) -> 0 | U64: =SUM(U65:U67) -> 0 | V64: =SUM(V65:V67) -> 0 | ... BL64: =SUM(BL65:BL67) -> 0 | BM64: =SUM(I64:BL64) -> 0
F65: ОЛИМП лето | G65: в том числе: Волейбол | H65: 55 | I65: =SUM(J65:L65) -> 0 | J65: =O65+T65+Y65+AD65+AI65+AN65+AS65+AX65+BC65+BH65 -> 0 | K65: =P65+U65+Z65+AE65+AJ65+AO65+AT65+AY65+BD65+BI65 -> 0 | L65: =Q65+V65+AA65+AF65+AK65+AP65+AU65+AZ65+BE65+BJ65 -> 0 | M65: =R65+W65+AB65+AG65+AL65+AQ65+AV65+BA65+BF65+BK65 -> 0 | N65: =S65+X65+AC65+AH65+AM65+AR65+AW65+BB65+BG65+BL65 -> 0 | BM65: =SUM(I65:BL65) -> 0
F66: ОЛИМП лето | G66: Пляжный волейбол | H66: 56 | I66: =SUM(J66:L66) -> 0 | J66: =O66+T66+Y66+AD66+AI66+AN66+AS66+AX66+BC66+BH66 -> 0 | K66: =P66+U66+Z66+AE66+AJ66+AO66+AT66+AY66+BD66+BI66 -> 0 | L66: =Q66+V66+AA66+AF66+AK66+AP66+AU66+AZ66+BE66+BJ66 -> 0 | M66: =R66+W66+AB66+AG66+AL66+AQ66+AV66+BA66+BF66+BK66 -> 0 | N66: =S66+X66+AC66+AH66+AM66+AR66+AW66+BB66+BG66+BL66 -> 0 | BM66: =SUM(I66:BL66) -> 0
F67: ОЛИМП лето | G67: Волейбол на снегу | H67: 57 | I67: =SUM(J67:L67) -> 0 | J67: =O67+T67+Y67+AD67+AI67+AN67+AS67+AX67+BC67+BH67 -> 0 | K67: =P67+U67+Z67+AE67+AJ67+AO67+AT67+AY67+BD67+BI67 -> 0 | L67: =Q67+V67+AA67+AF67+AK67+AP67+AU67+AZ67+BE67+BJ67 -> 0 | M67: =R67+W67+AB67+AG67+AL67+AQ67+AV67+BA67+BF67+BK67 -> 0 | N67: =S67+X67+AC67+AH67+AM67+AR67+AW67+BB67+BG67+BL67 -> 0 | BM67: =SUM(I67:BL67) -> 0
F68: НЕОЛИМП | G68: Восточное боевое единоборство | H68: 58 | I68: =SUM(J68:L68) -> 0 | J68: =O68+T68+Y68+AD68+AI68+AN68+AS68+AX68+BC68+BH68 -> 0 | K68: =P68+U68+Z68+AE68+AJ68+AO68+AT68+AY68+BD68+BI68 -> 0 | L68: =Q68+V68+AA68+AF68+AK68+AP68+AU68+AZ68+BE68+BJ68 -> 0 | M68: =R68+W68+AB68+AG68+AL68+AQ68+AV68+BA68+BF68+BK68 -> 0 | N68: =S68+X68+AC68+AH68+AM68+AR68+AW68+BB68+BG68+BL68 -> 0 | BM68: =SUM(I68:BL68) -> 0
F69: НЕОЛИМП | G69: Всестилевое каратэ | H69: 59 | I69: =SUM(J69:L69) -> 0 | J69: =O69+T69+Y69+AD69+AI69+AN69+AS69+AX69+BC69+BH69 -> 0 | K69: =P69+U69+Z69+AE69+AJ69+AO69+AT69+AY69+BD69+BI69 -> 0 | L69: =Q69+V69+AA69+AF69+AK69+AP69+AU69+AZ69+BE69+BJ69 -> 0 | M69: =R69+W69+AB69+AG69+AL69+AQ69+AV69+BA69+BF69+BK69 -> 0 | N69: =S69+X69+AC69+AH69+AM69+AR69+AW69+BB69+BG69+BL69 -> 0 | BM69: =SUM(I69:BL69) -> 0
F70: ОЛИМП лето | G70: Гандбол - всего | H70: 60 | I70: =SUM(J70:L70) -> 0 | J70: =O70+T70+Y70+AD70+AI70+AN70+AS70+AX70+BC70+BH70 -> 0 | K70: =P70+U70+Z70+AE70+AJ70+AO70+AT70+AY70+BD70+BI70 -> 0 | L70: =Q70+V70+AA70+AF70+AK70+AP70+AU70+AZ70+BE70+BJ70 -> 0 | M70: =R70+W70+AB70+AG70+AL70+AQ70+AV70+BA70+BF70+BK70 -> 0 | N70: =S70+X70+AC70+AH70+AM70+AR70+AW70+BB70+BG70+BL70 -> 0 | O70: =SUM(O71:O72) -> 0 | P70: =SUM(P71:P72) -> 0 | Q70: =SUM(Q71:Q72) -> 0 | R70: =SUM(R71:R72) -> 0 | S70: =SUM(S71:S72) -> 0 | T70: =SUM(T71:T72) -> 0 | U70: =SUM(U71:U72) -> 0 | V70: =SUM(V71:V72) -> 0 | ... BL70: =SUM(BL71:BL72) -> 0 | BM70: =SUM(I70:BL70) -> 0
F71: ОЛИМП лето | G71: в том числе: Гандбол | H71: 61 | I71: =SUM(J71:L71) -> 0 | J71: =O71+T71+Y71+AD71+AI71+AN71+AS71+AX71+BC71+BH71 -> 0 | K71: =P71+U71+Z71+AE71+AJ71+AO71+AT71+AY71+BD71+BI71 -> 0 | L71: =Q71+V71+AA71+AF71+AK71+AP71+AU71+AZ71+BE71+BJ71 -> 0 | M71: =R71+W71+AB71+AG71+AL71+AQ71+AV71+BA71+BF71+BK71 -> 0 | N71: =S71+X71+AC71+AH71+AM71+AR71+AW71+BB71+BG71+BL71 -> 0 | BM71: =SUM(I71:BL71) -> 0
F72: ОЛИМП лето | G72: Пляжный гандбол | H72: 62 | I72: =SUM(J72:L72) -> 0 | J72: =O72+T72+Y72+AD72+AI72+AN72+AS72+AX72+BC72+BH72 -> 0 | K72: =P72+U72+Z72+AE72+AJ72+AO72+AT72+AY72+BD72+BI72 -> 0 | L72: =Q72+V72+AA72+AF72+AK72+AP72+AU72+AZ72+BE72+BJ72 -> 0 | M72: =R72+W72+AB72+AG72+AL72+AQ72+AV72+BA72+BF72+BK72 -> 0 | N72: =S72+X72+AC72+AH72+AM72+AR72+AW72+BB72+BG72+BL72 -> 0 | BM72: =SUM(I72:BL72) -> 0
F73: НЕОЛИМП | G73: Гиревой спорт | H73: 63 | I73: =SUM(J73:L73) -> 0 | J73: =O73+T73+Y73+AD73+AI73+AN73+AS73+AX73+BC73+BH73 -> 0 | K73: =P73+U73+Z73+AE73+AJ73+AO73+AT73+AY73+BD73+BI73 -> 0 | L73: =Q73+V73+AA73+AF73+AK73+AP73+AU73+AZ73+BE73+BJ73 -> 0 | M73: =R73+W73+AB73+AG73+AL73+AQ73+AV73+BA73+BF73+BK73 -> 0 | N73: =S73+X73+AC73+AH73+AM73+AR73+AW73+BB73+BG73+BL73 -> 0 | BM73: =SUM(I73:BL73) -> 0
F74: НЕОЛИМП | G74: Го | H74: 64 | I74: =SUM(J74:L74) -> 0 | J74: =O74+T74+Y74+AD74+AI74+AN74+AS74+AX74+BC74+BH74 -> 0 | K74: =P74+U74+Z74+AE74+AJ74+AO74+AT74+AY74+BD74+BI74 -> 0 | L74: =Q74+V74+AA74+AF74+AK74+AP74+AU74+AZ74+BE74+BJ74 -> 0 | M74: =R74+W74+AB74+AG74+AL74+AQ74+AV74+BA74+BF74+BK74 -> 0 | N74: =S74+X74+AC74+AH74+AM74+AR74+AW74+BB74+BG74+BL74 -> 0 | BM74: =SUM(I74:BL74) -> 0
F75: ОЛИМП лето | G75: Гольф | H75: 65 | I75: =SUM(J75:L75) -> 0 | J75: =O75+T75+Y75+AD75+AI75+AN75+AS75+AX75+BC75+BH75 -> 0 | K75: =P75+U75+Z75+AE75+AJ75+AO75+AT75+AY75+BD75+BI75 -> 0 | L75: =Q75+V75+AA75+AF75+AK75+AP75+AU75+AZ75+BE75+BJ75 -> 0 | M75: =R75+W75+AB75+AG75+AL75+AQ75+AV75+BA75+BF75+BK75 -> 0 | N75: =S75+X75+AC75+AH75+AM75+AR75+AW75+BB75+BG75+BL75 -> 0 | BM75: =SUM(I75:BL75) -> 0
F76: НЕОЛИМП | G76: Гонки дронов (беспилотных воздушных судов) - всего | H76: 66 | I76: =SUM(J76:L76) -> 0 | J76: =O76+T76+Y76+AD76+AI76+AN76+AS76+AX76+BC76+BH76 -> 0 | K76: =P76+U76+Z76+AE76+AJ76+AO76+AT76+AY76+BD76+BI76 -> 0 | L76: =Q76+V76+AA76+AF76+AK76+AP76+AU76+AZ76+BE76+BJ76 -> 0 | M76: =R76+W76+AB76+AG76+AL76+AQ76+AV76+BA76+BF76+BK76 -> 0 | N76: =S76+X76+AC76+AH76+AM76+AR76+AW76+BB76+BG76+BL76 -> 0 | O76: =SUM(O77:O80) -> 0 | P76: =SUM(P77:P80) -> 0 | Q76: =SUM(Q77:Q80) -> 0 | R76: =SUM(R77:R80) -> 0 | S76: =SUM(S77:S80) -> 0 | T76: =SUM(T77:T80) -> 0 | U76: =SUM(U77:U80) -> 0 | V76: =SUM(V77:V80) -> 0 | ... BL76: =SUM(BL77:BL80) -> 0 | BM76: =SUM(I76:BL76) -> 0
F77: НЕОЛИМП | G77: в том числе: Класс 75 мм | H77: 67 | I77: =SUM(J77:L77) -> 0 | J77: =O77+T77+Y77+AD77+AI77+AN77+AS77+AX77+BC77+BH77 -> 0 | K77: =P77+U77+Z77+AE77+AJ77+AO77+AT77+AY77+BD77+BI77 -> 0 | L77: =Q77+V77+AA77+AF77+AK77+AP77+AU77+AZ77+BE77+BJ77 -> 0 | M77: =R77+W77+AB77+AG77+AL77+AQ77+AV77+BA77+BF77+BK77 -> 0 | N77: =S77+X77+AC77+AH77+AM77+AR77+AW77+BB77+BG77+BL77 -> 0 | BM77: =SUM(I77:BL77) -> 0
F78: НЕОЛИМП | G78: Класс 200 мм | H78: 68 | I78: =SUM(J78:L78) -> 0 | J78: =O78+T78+Y78+AD78+AI78+AN78+AS78+AX78+BC78+BH78 -> 0 | K78: =P78+U78+Z78+AE78+AJ78+AO78+AT78+AY78+BD78+BI78 -> 0 | L78: =Q78+V78+AA78+AF78+AK78+AP78+AU78+AZ78+BE78+BJ78 -> 0 | M78: =R78+W78+AB78+AG78+AL78+AQ78+AV78+BA78+BF78+BK78 -> 0 | N78: =S78+X78+AC78+AH78+AM78+AR78+AW78+BB78+BG78+BL78 -> 0 | BM78: =SUM(I78:BL78) -> 0
F79: НЕОЛИМП | G79: Класс 330 мм | H79: 69 | I79: =SUM(J79:L79) -> 0 | J79: =O79+T79+Y79+AD79+AI79+AN79+AS79+AX79+BC79+BH79 -> 0 | K79: =P79+U79+Z79+AE79+AJ79+AO79+AT79+AY79+BD79+BI79 -> 0 | L79: =Q79+V79+AA79+AF79+AK79+AP79+AU79+AZ79+BE79+BJ79 -> 0 | M79: =R79+W79+AB79+AG79+AL79+AQ79+AV79+BA79+BF79+BK79 -> 0 | N79: =S79+X79+AC79+AH79+AM79+AR79+AW79+BB79+BG79+BL79 -> 0 | BM79: =SUM(I79:BL79) -> 0
F80: НЕОЛИМП | G80: Технический симулятор | H80: 70 | I80: =SUM(J80:L80) -> 0 | J80: =O80+T80+Y80+AD80+AI80+AN80+AS80+AX80+BC80+BH80 -> 0 | K80: =P80+U80+Z80+AE80+AJ80+AO80+AT80+AY80+BD80+BI80 -> 0 | L80: =Q80+V80+AA80+AF80+AK80+AP80+AU80+AZ80+BE80+BJ80 -> 0 | M80: =R80+W80+AB80+AG80+AL80+AQ80+AV80+BA80+BF80+BK80 -> 0 | N80: =S80+X80+AC80+AH80+AM80+AR80+AW80+BB80+BG80+BL80 -> 0 | BM80: =SUM(I80:BL80) -> 0
F81: НАЦИОНАЛЬН | G81: Гонки на охотничьих лыжах | H81: 71 | I81: =SUM(J81:L81) -> 0 | J81: =O81+T81+Y81+AD81+AI81+AN81+AS81+AX81+BC81+BH81 -> 0 | K81: =P81+U81+Z81+AE81+AJ81+AO81+AT81+AY81+BD81+BI81 -> 0 | L81: =Q81+V81+AA81+AF81+AK81+AP81+AU81+AZ81+BE81+BJ81 -> 0 | M81: =R81+W81+AB81+AG81+AL81+AQ81+AV81+BA81+BF81+BK81 -> 0 | N81: =S81+X81+AC81+AH81+AM81+AR81+AW81+BB81+BG81+BL81 -> 0 | BM81: =SUM(I81:BL81) -> 0
F82: НЕОЛИМП | G82: Гонки с препятствиями | H82: 72 | I82: =SUM(J82:L82) -> 0 | J82: =O82+T82+Y82+AD82+AI82+AN82+AS82+AX82+BC82+BH82 -> 0 | K82: =P82+U82+Z82+AE82+AJ82+AO82+AT82+AY82+BD82+BI82 -> 0 | L82: =Q82+V82+AA82+AF82+AK82+AP82+AU82+AZ82+BE82+BJ82 -> 0 | M82: =R82+W82+AB82+AG82+AL82+AQ82+AV82+BA82+BF82+BK82 -> 0 | N82: =S82+X82+AC82+AH82+AM82+AR82+AW82+BB82+BG82+BL82 -> 0 | BM82: =SUM(I82:BL82) -> 0
F83: ОЛИМП зима | G83: Горнолыжный спорт | H83: 73 | I83: =SUM(J83:L83) -> 0 | J83: =O83+T83+Y83+AD83+AI83+AN83+AS83+AX83+BC83+BH83 -> 0 | K83: =P83+U83+Z83+AE83+AJ83+AO83+AT83+AY83+BD83+BI83 -> 0 | L83: =Q83+V83+AA83+AF83+AK83+AP83+AU83+AZ83+BE83+BJ83 -> 0 | M83: =R83+W83+AB83+AG83+AL83+AQ83+AV83+BA83+BF83+BK83 -> 0 | N83: =S83+X83+AC83+AH83+AM83+AR83+AW83+BB83+BG83+BL83 -> 0 | BM83: =SUM(I83:BL83) -> 0
F84: НЕОЛИМП | G84: Городошный спорт | H84: 74 | I84: =SUM(J84:L84) -> 0 | J84: =O84+T84+Y84+AD84+AI84+AN84+AS84+AX84+BC84+BH84 -> 0 | K84: =P84+U84+Z84+AE84+AJ84+AO84+AT84+AY84+BD84+BI84 -> 0 | L84: =Q84+V84+AA84+AF84+AK84+AP84+AU84+AZ84+BE84+BJ84 -> 0 | M84: =R84+W84+AB84+AG84+AL84+AQ84+AV84+BA84+BF84+BK84 -> 0 | N84: =S84+X84+AC84+AH84+AM84+AR84+AW84+BB84+BG84+BL84 -> 0 | BM84: =SUM(I84:BL84) -> 0
F85: ОЛИМП лето | G85: Гребля на байдарках и каноэ | H85: 75 | I85: =SUM(J85:L85) -> 0 | J85: =O85+T85+Y85+AD85+AI85+AN85+AS85+AX85+BC85+BH85 -> 0 | K85: =P85+U85+Z85+AE85+AJ85+AO85+AT85+AY85+BD85+BI85 -> 0 | L85: =Q85+V85+AA85+AF85+AK85+AP85+AU85+AZ85+BE85+BJ85 -> 0 | M85: =R85+W85+AB85+AG85+AL85+AQ85+AV85+BA85+BF85+BK85 -> 0 | N85: =S85+X85+AC85+AH85+AM85+AR85+AW85+BB85+BG85+BL85 -> 0 | BM85: =SUM(I85:BL85) -> 0
F86: ПРИКЛАДН | G86: Гребля на шлюпках | H86: 76 | I86: =SUM(J86:L86) -> 0 | J86: =O86+T86+Y86+AD86+AI86+AN86+AS86+AX86+BC86+BH86 -> 0 | K86: =P86+U86+Z86+AE86+AJ86+AO86+AT86+AY86+BD86+BI86 -> 0 | L86: =Q86+V86+AA86+AF86+AK86+AP86+AU86+AZ86+BE86+BJ86 -> 0 | M86: =R86+W86+AB86+AG86+AL86+AQ86+AV86+BA86+BF86+BK86 -> 0 | N86: =S86+X86+AC86+AH86+AM86+AR86+AW86+BB86+BG86+BL86 -> 0 | BM86: =SUM(I86:BL86) -> 0
F87: ОЛИМП лето | G87: Гребной слалом | H87: 77 | I87: =SUM(J87:L87) -> 0 | J87: =O87+T87+Y87+AD87+AI87+AN87+AS87+AX87+BC87+BH87 -> 0 | K87: =P87+U87+Z87+AE87+AJ87+AO87+AT87+AY87+BD87+BI87 -> 0 | L87: =Q87+V87+AA87+AF87+AK87+AP87+AU87+AZ87+BE87+BJ87 -> 0 | M87: =R87+W87+AB87+AG87+AL87+AQ87+AV87+BA87+BF87+BK87 -> 0 | N87: =S87+X87+AC87+AH87+AM87+AR87+AW87+BB87+BG87+BL87 -> 0 | BM87: =SUM(I87:BL87) -> 0
F88: ОЛИМП лето | G88: Гребной спорт - всего | H88: 78 | I88: =SUM(J88:L88) -> 0 | J88: =O88+T88+Y88+AD88+AI88+AN88+AS88+AX88+BC88+BH88 -> 0 | K88: =P88+U88+Z88+AE88+AJ88+AO88+AT88+AY88+BD88+BI88 -> 0 | L88: =Q88+V88+AA88+AF88+AK88+AP88+AU88+AZ88+BE88+BJ88 -> 0 | M88: =R88+W88+AB88+AG88+AL88+AQ88+AV88+BA88+BF88+BK88 -> 0 | N88: =S88+X88+AC88+AH88+AM88+AR88+AW88+BB88+BG88+BL88 -> 0 | O88: =SUM(O89:O90) -> 0 | P88: =SUM(P89:P90) -> 0 | Q88: =SUM(Q89:Q90) -> 0 | R88: =SUM(R89:R90) -> 0 | S88: =SUM(S89:S90) -> 0 | T88: =SUM(T89:T90) -> 0 | U88: =SUM(U89:U90) -> 0 | V88: =SUM(V89:V90) -> 0 | ... BL88: =SUM(BL89:BL90) -> 0 | BM88: =SUM(I88:BL88) -> 0
F89: ОЛИМП лето | G89: в том числе: Академическая гребля | H89: 79 | I89: =SUM(J89:L89) -> 0 | J89: =O89+T89+Y89+AD89+AI89+AN89+AS89+AX89+BC89+BH89 -> 0 | K89: =P89+U89+Z89+AE89+AJ89+AO89+AT89+AY89+BD89+BI89 -> 0 | L89: =Q89+V89+AA89+AF89+AK89+AP89+AU89+AZ89+BE89+BJ89 -> 0 | M89: =R89+W89+AB89+AG89+AL89+AQ89+AV89+BA89+BF89+BK89 -> 0 | N89: =S89+X89+AC89+AH89+AM89+AR89+AW89+BB89+BG89+BL89 -> 0 | BM89: =SUM(I89:BL89) -> 0
F90: ОЛИМП лето | G90: Иные дисциплины вида спорта "гребной спорт" | H90: 80 | I90: =SUM(J90:L90) -> 0 | J90: =O90+T90+Y90+AD90+AI90+AN90+AS90+AX90+BC90+BH90 -> 0 | K90: =P90+U90+Z90+AE90+AJ90+AO90+AT90+AY90+BD90+BI90 -> 0 | L90: =Q90+V90+AA90+AF90+AK90+AP90+AU90+AZ90+BE90+BJ90 -> 0 | M90: =R90+W90+AB90+AG90+AL90+AQ90+AV90+BA90+BF90+BK90 -> 0 | N90: =S90+X90+AC90+AH90+AM90+AR90+AW90+BB90+BG90+BL90 -> 0 | BM90: =SUM(I90:BL90) -> 0
F91: ПРИКЛАДН | G91: Гребно-парусное двоеборье | H91: 81 | I91: =SUM(J91:L91) -> 0 | J91: =O91+T91+Y91+AD91+AI91+AN91+AS91+AX91+BC91+BH91 -> 0 | K91: =P91+U91+Z91+AE91+AJ91+AO91+AT91+AY91+BD91+BI91 -> 0 | L91: =Q91+V91+AA91+AF91+AK91+AP91+AU91+AZ91+BE91+BJ91 -> 0 | M91: =R91+W91+AB91+AG91+AL91+AQ91+AV91+BA91+BF91+BK91 -> 0 | N91: =S91+X91+AC91+AH91+AM91+AR91+AW91+BB91+BG91+BL91 -> 0 | BM91: =SUM(I91:BL91) -> 0
F92: НЕОЛИМП | G92: Дартс | H92: 82 | I92: =SUM(J92:L92) -> 0 | J92: =O92+T92+Y92+AD92+AI92+AN92+AS92+AX92+BC92+BH92 -> 0 | K92: =P92+U92+Z92+AE92+AJ92+AO92+AT92+AY92+BD92+BI92 -> 0 | L92: =Q92+V92+AA92+AF92+AK92+AP92+AU92+AZ92+BE92+BJ92 -> 0 | M92: =R92+W92+AB92+AG92+AL92+AQ92+AV92+BA92+BF92+BK92 -> 0 | N92: =S92+X92+AC92+AH92+AM92+AR92+AW92+BB92+BG92+BL92 -> 0 | BM92: =SUM(I92:BL92) -> 0
F93: НЕОЛИМП | G93: Джиу-джитсу | H93: 83 | I93: =SUM(J93:L93) -> 0 | J93: =O93+T93+Y93+AD93+AI93+AN93+AS93+AX93+BC93+BH93 -> 0 | K93: =P93+U93+Z93+AE93+AJ93+AO93+AT93+AY93+BD93+BI93 -> 0 | L93: =Q93+V93+AA93+AF93+AK93+AP93+AU93+AZ93+BE93+BJ93 -> 0 | M93: =R93+W93+AB93+AG93+AL93+AQ93+AV93+BA93+BF93+BK93 -> 0 | N93: =S93+X93+AC93+AH93+AM93+AR93+AW93+BB93+BG93+BL93 -> 0 | BM93: =SUM(I93:BL93) -> 0
F94: НЕОЛИМП | G94: Джутайдо | H94: 84 | I94: =SUM(J94:L94) -> 0 | J94: =O94+T94+Y94+AD94+AI94+AN94+AS94+AX94+BC94+BH94 -> 0 | K94: =P94+U94+Z94+AE94+AJ94+AO94+AT94+AY94+BD94+BI94 -> 0 | L94: =Q94+V94+AA94+AF94+AK94+AP94+AU94+AZ94+BE94+BJ94 -> 0 | M94: =R94+W94+AB94+AG94+AL94+AQ94+AV94+BA94+BF94+BK94 -> 0 | N94: =S94+X94+AC94+AH94+AM94+AR94+AW94+BB94+BG94+BL94 -> 0 | BM94: =SUM(I94:BL94) -> 0
F95: ОЛИМП лето | G95: Дзюдо | H95: 85 | I95: =SUM(J95:L95) -> 0 | J95: =O95+T95+Y95+AD95+AI95+AN95+AS95+AX95+BC95+BH95 -> 0 | K95: =P95+U95+Z95+AE95+AJ95+AO95+AT95+AY95+BD95+BI95 -> 0 | L95: =Q95+V95+AA95+AF95+AK95+AP95+AU95+AZ95+BE95+BJ95 -> 0 | M95: =R95+W95+AB95+AG95+AL95+AQ95+AV95+BA95+BF95+BK95 -> 0 | N95: =S95+X95+AC95+AH95+AM95+AR95+AW95+BB95+BG95+BL95 -> 0 | BM95: =SUM(I95:BL95) -> 0
F96: НЕОЛИМП | G96: Ездовой спорт | H96: 86 | I96: =SUM(J96:L96) -> 0 | J96: =O96+T96+Y96+AD96+AI96+AN96+AS96+AX96+BC96+BH96 -> 0 | K96: =P96+U96+Z96+AE96+AJ96+AO96+AT96+AY96+BD96+BI96 -> 0 | L96: =Q96+V96+AA96+AF96+AK96+AP96+AU96+AZ96+BE96+BJ96 -> 0 | M96: =R96+W96+AB96+AG96+AL96+AQ96+AV96+BA96+BF96+BK96 -> 0 | N96: =S96+X96+AC96+AH96+AM96+AR96+AW96+BB96+BG96+BL96 -> 0 | BM96: =SUM(I96:BL96) -> 0
F97: НЕОЛИМП | G97: Зимнее плавание | H97: 87 | I97: =SUM(J97:L97) -> 0 | J97: =O97+T97+Y97+AD97+AI97+AN97+AS97+AX97+BC97+BH97 -> 0 | K97: =P97+U97+Z97+AE97+AJ97+AO97+AT97+AY97+BD97+BI97 -> 0 | L97: =Q97+V97+AA97+AF97+AK97+AP97+AU97+AZ97+BE97+BJ97 -> 0 | M97: =R97+W97+AB97+AG97+AL97+AQ97+AV97+BA97+BF97+BK97 -> 0 | N97: =S97+X97+AC97+AH97+AM97+AR97+AW97+BB97+BG97+BL97 -> 0 | BM97: =SUM(I97:BL97) -> 0
F98: НЕОЛИМП | G98: Капоэйра | H98: 88 | I98: =SUM(J98:L98) -> 0 | J98: =O98+T98+Y98+AD98+AI98+AN98+AS98+AX98+BC98+BH98 -> 0 | K98: =P98+U98+Z98+AE98+AJ98+AO98+AT98+AY98+BD98+BI98 -> 0 | L98: =Q98+V98+AA98+AF98+AK98+AP98+AU98+AZ98+BE98+BJ98 -> 0 | M98: =R98+W98+AB98+AG98+AL98+AQ98+AV98+BA98+BF98+BK98 -> 0 | N98: =S98+X98+AC98+AH98+AM98+AR98+AW98+BB98+BG98+BL98 -> 0 | BM98: =SUM(I98:BL98) -> 0
F99: НЕОЛИМП | G99: Каратэ | H99: 89 | I99: =SUM(J99:L99) -> 0 | J99: =O99+T99+Y99+AD99+AI99+AN99+AS99+AX99+BC99+BH99 -> 0 | K99: =P99+U99+Z99+AE99+AJ99+AO99+AT99+AY99+BD99+BI99 -> 0 | L99: =Q99+V99+AA99+AF99+AK99+AP99+AU99+AZ99+BE99+BJ99 -> 0 | M99: =R99+W99+AB99+AG99+AL99+AQ99+AV99+BA99+BF99+BK99 -> 0 | N99: =S99+X99+AC99+AH99+AM99+AR99+AW99+BB99+BG99+BL99 -> 0 | BM99: =SUM(I99:BL99) -> 0
F100: НЕОЛИМП | G100: Кендо | H100: 90 | I100: =SUM(J100:L100) -> 0 | J100: =O100+T100+Y100+AD100+AI100+AN100+AS100+AX100+BC100+BH100 -> 0 | K100: =P100+U100+Z100+AE100+AJ100+AO100+AT100+AY100+BD100+BI100 -> 0 | L100: =Q100+V100+AA100+AF100+AK100+AP100+AU100+AZ100+BE100+BJ100 -> 0 | M100: =R100+W100+AB100+AG100+AL100+AQ100+AV100+BA100+BF100+BK100 -> 0 | N100: =S100+X100+AC100+AH100+AM100+AR100+AW100+BB100+BG100+BL100 -> 0 | BM100: =SUM(I100:BL100) -> 0
F101: НАЦИОНАЛЬН | G101: Керешу | H101: 91 | I101: =SUM(J101:L101) -> 0 | J101: =O101+T101+Y101+AD101+AI101+AN101+AS101+AX101+BC101+BH101 -> 0 | K101: =P101+U101+Z101+AE101+AJ101+AO101+AT101+AY101+BD101+BI101 -> 0 | L101: =Q101+V101+AA101+AF101+AK101+AP101+AU101+AZ101+BE101+BJ101 -> 0 | M101: =R101+W101+AB101+AG101+AL101+AQ101+AV101+BA101+BF101+BK101 -> 0 | N101: =S101+X101+AC101+AH101+AM101+AR101+AW101+BB101+BG101+BL101 -> 0 | BM101: =SUM(I101:BL101) -> 0
F102: ОЛИМП зима | G102: Кёрлинг - всего | H102: 92 | I102: =SUM(J102:L102) -> 0 | J102: =O102+T102+Y102+AD102+AI102+AN102+AS102+AX102+BC102+BH102 -> 0 | K102: =P102+U102+Z102+AE102+AJ102+AO102+AT102+AY102+BD102+BI102 -> 0 | L102: =Q102+V102+AA102+AF102+AK102+AP102+AU102+AZ102+BE102+BJ102 -> 0 | M102: =R102+W102+AB102+AG102+AL102+AQ102+AV102+BA102+BF102+BK102 -> 0 | N102: =S102+X102+AC102+AH102+AM102+AR102+AW102+BB102+BG102+BL102 -> 0 | O102: =SUM(O103:O104) -> 0 | P102: =SUM(P103:P104) -> 0 | Q102: =SUM(Q103:Q104) -> 0 | R102: =SUM(R103:R104) -> 0 | S102: =SUM(S103:S104) -> 0 | T102: =SUM(T103:T104) -> 0 | U102: =SUM(U103:U104) -> 0 | V102: =SUM(V103:V104) -> 0 | ... BL102: =SUM(BL103:BL104) -> 0 | BM102: =SUM(I102:BL102) -> 0
F103: ОЛИМП зима | G103: в том числе: Кёрлинг | H103: 93 | I103: =SUM(J103:L103) -> 0 | J103: =O103+T103+Y103+AD103+AI103+AN103+AS103+AX103+BC103+BH103 -> 0 | K103: =P103+U103+Z103+AE103+AJ103+AO103+AT103+AY103+BD103+BI103 -> 0 | L103: =Q103+V103+AA103+AF103+AK103+AP103+AU103+AZ103+BE103+BJ103 -> 0 | M103: =R103+W103+AB103+AG103+AL103+AQ103+AV103+BA103+BF103+BK103 -> 0 | N103: =S103+X103+AC103+AH103+AM103+AR103+AW103+BB103+BG103+BL103 -> 0 | BM103: =SUM(I103:BL103) -> 0
F104: ОЛИМП зима | G104: Кёрлинг - смешанные пары | H104: 94 | I104: =SUM(J104:L104) -> 0 | J104: =O104+T104+Y104+AD104+AI104+AN104+AS104+AX104+BC104+BH104 -> 0 | K104: =P104+U104+Z104+AE104+AJ104+AO104+AT104+AY104+BD104+BI104 -> 0 | L104: =Q104+V104+AA104+AF104+AK104+AP104+AU104+AZ104+BE104+BJ104 -> 0 | M104: =R104+W104+AB104+AG104+AL104+AQ104+AV104+BA104+BF104+BK104 -> 0 | N104: =S104+X104+AC104+AH104+AM104+AR104+AW104+BB104+BG104+BL104 -> 0 | BM104: =SUM(I104:BL104) -> 0
F105: НЕОЛИМП | G105: Кикбоксинг | H105: 95 | I105: =SUM(J105:L105) -> 0 | J105: =O105+T105+Y105+AD105+AI105+AN105+AS105+AX105+BC105+BH105 -> 0 | K105: =P105+U105+Z105+AE105+AJ105+AO105+AT105+AY105+BD105+BI105 -> 0 | L105: =Q105+V105+AA105+AF105+AK105+AP105+AU105+AZ105+BE105+BJ105 -> 0 | M105: =R105+W105+AB105+AG105+AL105+AQ105+AV105+BA105+BF105+BK105 -> 0 | N105: =S105+X105+AC105+AH105+AM105+AR105+AW105+BB105+BG105+BL105 -> 0 | BM105: =SUM(I105:BL105) -> 0
...

Sheet Раздел 8
G3: Раздел VIII. Тренерско-преподавательский состав, человек
G4: Виды спорта | H4: № строки | I4: Тренеры-преподаватели
I5: Всего тренеров-преподавателей | J5: Всего по основному месту работы | K5: внутреннее совмещение/ совместительство | L5: по основному месту работы: | U5: внешние совместители: | AE5: из гр.4: | AJ5: Впервые трудоустроенные тренеры-преподаватели в отчетном периоде
L6: профессиональное образование | Q6: Прошедшие профессиональную переподготовку (за отчетный период) | R6: Прошедшие повышение квалификации (за отчетный период) | S6: квалификационные категории | U6: Всего внешних совместителей | V6: профессиональное образование | AA6: Прошедшие профессиональную переподготовку (за отчетный период) | AB6: Прошедшие повышение квалификации (за отчетный период) | AC6: квалификационные категории | AE6: в возрасте: | AH6: Звание «Заслуженный тренер России» | AI6: имеющие стаж работы 25 лет и более
L7: высшее | M7: среднее | N7: в том числе физкультурное или педагогическое с направленностью "физическая культура" | P7: имеющие дополнительное профессиональное образование в области физической культуры и спорта (из гр.6 и 7) | S7: высшая | T7: первая | V7: высшее | W7: среднее | X7: в том числе физкультурное или педагогическое с направленностью "физическая культура" | Z7: имеющие дополнительное профессиональное образование в области физической культуры и спорта (из гр.16 и 17) | AC7: высшая | AD7: первая | AJ7: по основному месту работы | AK7: внешние совместители | AL7: в возрасте до 35 лет (из гр. 30)
AE8: до 35 лет | AF8: от 36 до 64 лет | AG8: старше 64 лет
N9: высшее | O9: среднее | X9: высшее | Y9: среднее
A10: ='Раздел 0'!M27 -> 0 | B10: ='Раздел 1'!D15 -> 0 | C10: {=_xlfn.IFS(SUM('Раздел 1'!$D$5:$D$6)>0,"ФКиС",SUM('Раздел 1'!$D$7:$D$8)>0,"Образование",SUM('Раздел 1'!$D$9:$D$10)>0,"Другая")} -> ФКиС | D10: {=_xlfn.IFS(SUM('Раздел 1'!$E$12)>0,"СШ",SUM('Раздел 1'!$F$12)>0,"СШОР",SUM('Раздел 1'!$G$12)>0,"УОР",SUM('Раздел 1'!$H$12)>0,"ЦСП",SUM('Раздел 1'!$I$12)>0,"ДРУГИЕ",SUM('Раздел 1'!$E$13)>0,"ОСП СШ",SUM('Раздел 1'!$F$13)>0,"ОСП СШОР",SUM('Раздел 1'!$I$13)>0,"ОСП ДРУГИЕ")} -> ЦСП | E10: =IF(SUM('Раздел 1'!$D$12)>0,SUM('Раздел 1'!$D$13),"") -> 0 | F10: {=_xlfn.IFS(SUM('Раздел 1'!$D$19)>0,"РФ",SUM('Раздел 1'!$E$19)>0,"СУБЪЕКТ",SUM('Раздел 1'!$F$19:$G$19)>0,"МУНИЦИПАЛ",SUM('Раздел 1'!$H$19:$I$19)>0,"ИНЫЕ")} -> #N/A | G10: 1 | H10: 2 | I10: 3 | J10: 4 | K10: 5 | L10: 6 | M10: 7 | N10: 8 | O10: 9 | P10: 10 | Q10: 11 | R10: 12 | S10: 13 | T10: 14 | U10: 15 | V10: 16 | W10: 17 | X10: 18 | Y10: 19 | Z10: 20 | AA10: 21 | AB10: 22 | AC10: 23 | AD10: 24 | AE10: 25 | AF10: 26 | AG10: 27 | AH10: 28 | AI10: 29 | AJ10: 30 | AK10: 31 | AL10: 32 | AM10: 33
G11: Авиамодельный спорт | H11: 01 | I11: =J11+U11 -> 0 | AM11: =SUM(I11:AL11) -> 0
G12: Авиационные гонки | H12: 02 | I12: =J12+U12 -> 0 | AM12: =SUM(I12:AL12) -> 0
G13: Автомобильный спорт | H13: 03 | I13: =J13+U13 -> 0 | AM13: =SUM(I13:AL13) -> 0
G14: Автомодельный спорт | H14: 04 | I14: =J14+U14 -> 0 | AM14: =SUM(I14:AL14) -> 0
G15: Айкидо | H15: 05 | I15: =J15+U15 -> 0 | AM15: =SUM(I15:AL15) -> 0
G16: Акробатический рок-н-ролл | H16: 06 | I16: =J16+U16 -> 0 | AM16: =SUM(I16:AL16) -> 0
G17: Альпинизм - всего | H17: 07 | I17: =J17+U17 -> 0 | J17: =SUM(J18:J19) -> 0 | K17: =SUM(K18:K19) -> 0 | L17: =SUM(L18:L19) -> 0 | M17: =SUM(M18:M19) -> 0 | N17: =SUM(N18:N19) -> 0 | O17: =SUM(O18:O19) -> 0 | P17: =SUM(P18:P19) -> 0 | Q17: =SUM(Q18:Q19) -> 0 | ... AL17: =SUM(AL18:AL19) -> 0 | AM17: =SUM(I17:AL17) -> 0
G18: в том числе: Ски-альпинизм | H18: 08 | I18: =J18+U18 -> 0 | AM18: =SUM(I18:AL18) -> 0
G19: Иные дисциплины вида спорта "альпинизм" | H19: 09 | I19: =J19+U19 -> 0 | AM19: =SUM(I19:AL19) -> 0
G20: Американский футбол | H20: 10 | I20: =J20+U20 -> 0 | AM20: =SUM(I20:AL20) -> 0
G21: Армейская высокоточная стрельба | H21: 11 | I21: =J21+U21 -> 0 | AM21: =SUM(I21:AL21) -> 0
G22: Армейский рукопашный бой | H22: 12 | I22: =J22+U22 -> 0 | AM22: =SUM(I22:AL22) -> 0
G23: Армейское тактико-стрелковое многоборье | H23: 13 | I23: =J23+U23 -> 0 | AM23: =SUM(I23:AL23) -> 0
G24: Армрестлинг | H24: 14 | I24: =J24+U24 -> 0 | AM24: =SUM(I24:AL24) -> 0
G25: Бадминтон | H25: 15 | I25: =J25+U25 -> 0 | AM25: =SUM(I25:AL25) -> 0
G26: Баскетбол - всего | H26: 16 | I26: =J26+U26 -> 0 | J26: =SUM(J27:J30) -> 0 | K26: =SUM(K27:K30) -> 0 | L26: =SUM(L27:L30) -> 0 | M26: =SUM(M27:M30) -> 0 | N26: =SUM(N27:N30) -> 0 | O26: =SUM(O27:O30) -> 0 | P26: =SUM(P27:P30) -> 0 | Q26: =SUM(Q27:Q30) -> 0 | ... AL26: =SUM(AL27:AL30) -> 0 | AM26: =SUM(I26:AL26) -> 0
G27: в том числе: Баскетбол | H27: 17 | I27: =J27+U27 -> 0 | AM27: =SUM(I27:AL27) -> 0
G28: Баскетбол 3х3 | H28: 18 | I28: =J28+U28 -> 0 | AM28: =SUM(I28:AL28) -> 0
G29: Интерактивный баскетбол | H29: 19 | I29: =J29+U29 -> 0 | AM29: =SUM(I29:AL29) -> 0
G30: Иные дисциплины вида спорта "баскетбол" | H30: 20 | I30: =J30+U30 -> 0 | AM30: =SUM(I30:AL30) -> 0
G31: Бейсбол | H31: 21 | I31: =J31+U31 -> 0 | AM31: =SUM(I31:AL31) -> 0
G32: Биатлон | H32: 22 | I32: =J32+U32 -> 0 | AM32: =SUM(I32:AL32) -> 0
G33: Бильярдный спорт | H33: 23 | I33: =J33+U33 -> 0 | AM33: =SUM(I33:AL33) -> 0
G34: Бобслей - всего | H34: 24 | I34: =J34+U34 -> 0 | J34: =SUM(J35:J38) -> 0 | K34: =SUM(K35:K38) -> 0 | L34: =SUM(L35:L38) -> 0 | M34: =SUM(M35:M38) -> 0 | N34: =SUM(N35:N38) -> 0 | O34: =SUM(O35:O38) -> 0 | P34: =SUM(P35:P38) -> 0 | Q34: =SUM(Q35:Q38) -> 0 | ... AL34: =SUM(AL35:AL38) -> 0 | AM34: =SUM(I34:AL34) -> 0
G35: в том числе: Скелетон | H35: 25 | I35: =J35+U35 -> 0 | AM35: =SUM(I35:AL35) -> 0
G36: Экипаж | H36: 26 | I36: =J36+U36 -> 0 | AM36: =SUM(I36:AL36) -> 0
G37: Монобоб | H37: 27 | I37: =J37+U37 -> 0 | AM37: =SUM(I37:AL37) -> 0
G38: Иные дисциплины вида спорта "бобслей" | H38: 28 | I38: =J38+U38 -> 0 | AM38: =SUM(I38:AL38) -> 0
G39: Бодибилдинг | H39: 29 | I39: =J39+U39 -> 0 | AM39: =SUM(I39:AL39) -> 0
G40: Бокс | H40: 30 | I40: =J40+U40 -> 0 | AM40: =SUM(I40:AL40) -> 0
G41: Борьба на поясах | H41: 31 | I41: =J41+U41 -> 0 | AM41: =SUM(I41:AL41) -> 0
G42: Боулинг | H42: 32 | I42: =J42+U42 -> 0 | AM42: =SUM(I42:AL42) -> 0
G43: Боулспорт | H43: 33 | I43: =J43+U43 -> 0 | AM43: =SUM(I43:AL43) -> 0
G44: Брейкинг | H44: 34 | I44: =J44+U44 -> 0 | AM44: =SUM(I44:AL44) -> 0
G45: Велосипедный спорт - всего | H45: 35 | I45: =J45+U45 -> 0 | J45: =SUM(J46:J51) -> 0 | K45: =SUM(K46:K51) -> 0 | L45: =SUM(L46:L51) -> 0 | M45: =SUM(M46:M51) -> 0 | N45: =SUM(N46:N51) -> 0 | O45: =SUM(O46:O51) -> 0 | P45: =SUM(P46:P51) -> 0 | Q45: =SUM(Q46:Q51) -> 0 | ... AL45: =SUM(AL46:AL51) -> 0 | AM45: =SUM(I45:AL45) -> 0
G46: в том числе: BMX (гонка, эстафета) | H46: 36 | I46: =J46+U46 -> 0 | AM46: =SUM(I46:AL46) -> 0
G47: BMX - фристайл | H47: 37 | I47: =J47+U47 -> 0 | AM47: =SUM(I47:AL47) -> 0
G48: Маунтинбайк | H48: 38 | I48: =J48+U48 -> 0 | AM48: =SUM(I48:AL48) -> 0
G49: Трек | H49: 39 | I49: =J49+U49 -> 0 | AM49: =SUM(I49:AL49) -> 0
G50: Шоссе | H50: 40 | I50: =J50+U50 -> 0 | AM50: =SUM(I50:AL50) -> 0
G51: Технический симулятор | H51: 41 | I51: =J51+U51 -> 0 | AM51: =SUM(I51:AL51) -> 0
G52: Вертолетный спорт | H52: 42 | I52: =J52+U52 -> 0 | AM52: =SUM(I52:AL52) -> 0
G53: Водное поло - всего | H53: 43 | I53: =J53+U53 -> 0 | J53: =SUM(J54:J55) -> 0 | K53: =SUM(K54:K55) -> 0 | L53: =SUM(L54:L55) -> 0 | M53: =SUM(M54:M55) -> 0 | N53: =SUM(N54:N55) -> 0 | O53: =SUM(O54:O55) -> 0 | P53: =SUM(P54:P55) -> 0 | Q53: =SUM(Q54:Q55) -> 0 | ... AL53: =SUM(AL54:AL55) -> 0 | AM53: =SUM(I53:AL53) -> 0
G54: в том числе: Водное поло | H54: 44 | I54: =J54+U54 -> 0 | AM54: =SUM(I54:AL54) -> 0
G55: Иные дисциплины вида спорта "водное поло" | H55: 45 | I55: =J55+U55 -> 0 | AM55: =SUM(I55:AL55) -> 0
G56: Воднолыжный спорт | H56: 46 | I56: =J56+U56 -> 0 | AM56: =SUM(I56:AL56) -> 0
G57: Водно-моторный спорт | H57: 47 | I57: =J57+U57 -> 0 | AM57: =SUM(I57:AL57) -> 0
G58: Водно-спасательное многоборье | H58: 48 | I58: =J58+U58 -> 0 | AM58: =SUM(I58:AL58) -> 0
G59: Военно-прикладной спорт | H59: 49 | I59: =J59+U59 -> 0 | AM59: =SUM(I59:AL59) -> 0
G60: Военно-спортивное многоборье | H60: 50 | I60: =J60+U60 -> 0 | AM60: =SUM(I60:AL60) -> 0
G61: Воздухоплавательный спорт | H61: 51 | I61: =J61+U61 -> 0 | AM61: =SUM(I61:AL61) -> 0
G62: Воздушная гимнастика | H62: 52 | I62: =J62+U62 -> 0 | AM62: =SUM(I62:AL62) -> 0
G63: Воздушно-силовая атлетика | H63: 53 | I63: =J63+U63 -> 0 | AM63: =SUM(I63:AL63) -> 0
G64: Волейбол - всего | H64: 54 | I64: =J64+U64 -> 0 | J64: =SUM(J65:J67) -> 0 | K64: =SUM(K65:K67) -> 0 | L64: =SUM(L65:L67) -> 0 | M64: =SUM(M65:M67) -> 0 | N64: =SUM(N65:N67) -> 0 | O64: =SUM(O65:O67) -> 0 | P64: =SUM(P65:P67) -> 0 | Q64: =SUM(Q65:Q67) -> 0 | ... AL64: =SUM(AL65:AL67) -> 0 | AM64: =SUM(I64:AL64) -> 0
G65: в том числе: Волейбол | H65: 55 | I65: =J65+U65 -> 0 | AM65: =SUM(I65:AL65) -> 0
G66: Пляжный волейбол | H66: 56 | I66: =J66+U66 -> 0 | AM66: =SUM(I66:AL66) -> 0
G67: Волейбол на снегу | H67: 57 | I67: =J67+U67 -> 0 | AM67: =SUM(I67:AL67) -> 0
G68: Восточное боевое единоборство | H68: 58 | I68: =J68+U68 -> 0 | AM68: =SUM(I68:AL68) -> 0
G69: Всестилевое каратэ | H69: 59 | I69: =J69+U69 -> 0 | AM69: =SUM(I69:AL69) -> 0
G70: Гандбол - всего | H70: 60 | I70: =J70+U70 -> 0 | J70: =SUM(J71:J72) -> 0 | K70: =SUM(K71:K72) -> 0 | L70: =SUM(L71:L72) -> 0 | M70: =SUM(M71:M72) -> 0 | N70: =SUM(N71:N72) -> 0 | O70: =SUM(O71:O72) -> 0 | P70: =SUM(P71:P72) -> 0 | Q70: =SUM(Q71:Q72) -> 0 | ... AL70: =SUM(AL71:AL72) -> 0 | AM70: =SUM(I70:AL70) -> 0
G71: в том числе: Гандбол | H71: 61 | I71: =J71+U71 -> 0 | AM71: =SUM(I71:AL71) -> 0
G72: Пляжный гандбол | H72: 62 | I72: =J72+U72 -> 0 | AM72: =SUM(I72:AL72) -> 0
G73: Гиревой спорт | H73: 63 | I73: =J73+U73 -> 0 | AM73: =SUM(I73:AL73) -> 0
G74: Го | H74: 64 | I74: =J74+U74 -> 0 | AM74: =SUM(I74:AL74) -> 0
G75: Гольф | H75: 65 | I75: =J75+U75 -> 0 | AM75: =SUM(I75:AL75) -> 0
G76: Гонки дронов (беспилотных воздушных судов) - всего | H76: 66 | I76: =J76+U76 -> 0 | J76: =SUM(J77:J80) -> 0 | K76: =SUM(K77:K80) -> 0 | L76: =SUM(L77:L80) -> 0 | M76: =SUM(M77:M80) -> 0 | N76: =SUM(N77:N80) -> 0 | O76: =SUM(O77:O80) -> 0 | P76: =SUM(P77:P80) -> 0 | Q76: =SUM(Q77:Q80) -> 0 | ... AL76: =SUM(AL77:AL80) -> 0 | AM76: =SUM(I76:AL76) -> 0
G77: в том числе: Класс 75 мм | H77: 67 | I77: =J77+U77 -> 0 | AM77: =SUM(I77:AL77) -> 0
G78: Класс 200 мм | H78: 68 | I78: =J78+U78 -> 0 | AM78: =SUM(I78:AL78) -> 0
G79: Класс 330 мм | H79: 69 | I79: =J79+U79 -> 0 | AM79: =SUM(I79:AL79) -> 0
G80: Технический симулятор | H80: 70 | I80: =J80+U80 -> 0 | AM80: =SUM(I80:AL80) -> 0
G81: Гонки на охотничьих лыжах | H81: 71 | I81: =J81+U81 -> 0 | AM81: =SUM(I81:AL81) -> 0
G82: Гонки с препятствиями | H82: 72 | I82: =J82+U82 -> 0 | AM82: =SUM(I82:AL82) -> 0
G83: Горнолыжный спорт | H83: 73 | I83: =J83+U83 -> 0 | AM83: =SUM(I83:AL83) -> 0
G84: Городошный спорт | H84: 74 | I84: =J84+U84 -> 0 | AM84: =SUM(I84:AL84) -> 0
G85: Гребля на байдарках и каноэ | H85: 75 | I85: =J85+U85 -> 0 | AM85: =SUM(I85:AL85) -> 0
G86: Гребля на шлюпках | H86: 76 | I86: =J86+U86 -> 0 | AM86: =SUM(I86:AL86) -> 0
G87: Гребной слалом | H87: 77 | I87: =J87+U87 -> 0 | AM87: =SUM(I87:AL87) -> 0
G88: Гребной спорт - всего | H88: 78 | I88: =J88+U88 -> 0 | J88: =SUM(J89:J90) -> 0 | K88: =SUM(K89:K90) -> 0 | L88: =SUM(L89:L90) -> 0 | M88: =SUM(M89:M90) -> 0 | N88: =SUM(N89:N90) -> 0 | O88: =SUM(O89:O90) -> 0 | P88: =SUM(P89:P90) -> 0 | Q88: =SUM(Q89:Q90) -> 0 | ... AL88: =SUM(AL89:AL90) -> 0 | AM88: =SUM(I88:AL88) -> 0
G89: в том числе: Академическая гребля | H89: 79 | I89: =J89+U89 -> 0 | AM89: =SUM(I89:AL89) -> 0
G90: Иные дисциплины вида спорта "гребной спорт" | H90: 80 | I90: =J90+U90 -> 0 | AM90: =SUM(I90:AL90) -> 0
G91: Гребно-парусное двоеборье | H91: 81 | I91: =J91+U91 -> 0 | AM91: =SUM(I91:AL91) -> 0
G92: Дартс | H92: 82 | I92: =J92+U92 -> 0 | AM92: =SUM(I92:AL92) -> 0
G93: Джиу-джитсу | H93: 83 | I93: =J93+U93 -> 0 | AM93: =SUM(I93:AL93) -> 0
G94: Джутайдо | H94: 84 | I94: =J94+U94 -> 0 | AM94: =SUM(I94:AL94) -> 0
G95: Дзюдо | H95: 85 | I95: =J95+U95 -> 0 | AM95: =SUM(I95:AL95) -> 0
G96: Ездовой спорт | H96: 86 | I96: =J96+U96 -> 0 | AM96: =SUM(I96:AL96) -> 0
G97: Зимнее плавание | H97: 87 | I97: =J97+U97 -> 0 | AM97: =SUM(I97:AL97) -> 0
G98: Капоэйра | H98: 88 | I98: =J98+U98 -> 0 | AM98: =SUM(I98:AL98) -> 0
G99: Каратэ | H99: 89 | I99: =J99+U99 -> 0 | AM99: =SUM(I99:AL99) -> 0
G100: Кендо | H100: 90 | I100: =J100+U100 -> 0 | AM100: =SUM(I100:AL100) -> 0
G101: Керешу | H101: 91 | I101: =J101+U101 -> 0 | AM101: =SUM(I101:AL101) -> 0
G102: Кёрлинг - всего | H102: 92 | I102: =J102+U102 -> 0 | J102: =SUM(J103:J104) -> 0 | K102: =SUM(K103:K104) -> 0 | L102: =SUM(L103:L104) -> 0 | M102: =SUM(M103:M104) -> 0 | N102: =SUM(N103:N104) -> 0 | O102: =SUM(O103:O104) -> 0 | P102: =SUM(P103:P104) -> 0 | Q102: =SUM(Q103:Q104) -> 0 | ... AL102: =SUM(AL103:AL104) -> 0 | AM102: =SUM(I102:AL102) -> 0
...

Sheet Раздел 9
G2: Раздел IX. Кадровый состав, человек
G3: Наименование должности | H3: № строки | I3: Численность работников | K3: из численности работников по основному месту работы (гр.4)
K4: профессиональное образование | P4: квалификационные категории | S4: в возрасте: | V4: почетные звания
I5: Всего | J5: в том числе по основному месту работы | K5: высшее | L5: среднее | M5: в том числе физкультурное | O5: имеющие дополнительное профессиональное образование в области физической культуры и спорта (из гр.5 и 6) | P5: высшая | Q5: первая | R5: вторая | S5: до 35 лет | T5: от 36 до 64 лет | U5: старше 64 лет | V5: Заслуженный тренер России | W5: Заслуженный работник физической культуры Российской Федерации
M6: высшее | N6: среднее
A7: ='Раздел 0'!M27 -> 0 | B7: ='Раздел 1'!D15 -> 0 | C7: {=_xlfn.IFS(SUM('Раздел 1'!$D$5:$D$6)>0,"ФКиС",SUM('Раздел 1'!$D$7:$D$8)>0,"Образование",SUM('Раздел 1'!$D$9:$D$10)>0,"Другая")} -> ФКиС | D7: {=_xlfn.IFS(SUM('Раздел 1'!$E$12)>0,"СШ",SUM('Раздел 1'!$F$12)>0,"СШОР",SUM('Раздел 1'!$G$12)>0,"УОР",SUM('Раздел 1'!$H$12)>0,"ЦСП",SUM('Раздел 1'!$I$12)>0,"ДРУГИЕ",SUM('Раздел 1'!$E$13)>0,"ОСП СШ",SUM('Раздел 1'!$F$13)>0,"ОСП СШОР",SUM('Раздел 1'!$I$13)>0,"ОСП ДРУГИЕ")} -> ЦСП | E7: =IF(SUM('Раздел 1'!$D$12)>0,SUM('Раздел 1'!$D$13),"") -> 0 | F7: {=_xlfn.IFS(SUM('Раздел 1'!$D$19)>0,"РФ",SUM('Раздел 1'!$E$19)>0,"СУБЪЕКТ",SUM('Раздел 1'!$F$19:$G$19)>0,"МУНИЦИПАЛ",SUM('Раздел 1'!$H$19:$I$19)>0,"ИНЫЕ")} -> #N/A | G7: 1 | H7: 2 | I7: 3 | J7: 4 | K7: 5 | L7: 6 | M7: 7 | N7: 8 | O7: 9 | P7: 10 | Q7: 11 | R7: 12 | S7: 13 | T7: 14 | U7: 15 | V7: 16 | W7: 17 | X7: 18
G8: Директор (руководитель) | H8: 01 | X8: =SUM(I8:W8) -> 0
G9: Руководители обособленных структурных подразделений | H9: 02 | X9: =SUM(I9:W9) -> 0
G10: Тренеры ЦСП | H10: 03 | X10: =SUM(I10:W10) -> 0
G11: из них: впервые трудоустроены в отчетном периоде | H11: 04 | X11: =SUM(I11:W11) -> 0
G12: Спортсмены, спортсмены-инструкторы | H12: 05 | X12: =SUM(I12:W12) -> 0
G13: из них: проходящие дополнительные общеобразовательные программы в области физической культуры и спорта в организациях, реализующих дополнительные образовательные программы спортивной подготовки | H13: 06 | X13: =SUM(I13:W13) -> 0
G14: Инструкторы-методисты (включая старшего) | H14: 07 | X14: =SUM(I14:W14) -> 0
G15: Медицинские работники | H15: 08 | I15: =SUM(I16,I18,I19) -> 0 | J15: =SUM(J16,J18,J19) -> 0 | K15: =SUM(K16,K18,K19) -> 0 | L15: =SUM(L16,L18,L19) -> 0 | M15: =SUM(M16,M18,M19) -> 0 | N15: =SUM(N16,N18,N19) -> 0 | O15: =SUM(O16,O18,O19) -> 0 | P15: =SUM(P16,P18,P19) -> 0 | ... W15: =SUM(W16,W18,W19) -> 0 | X15: =SUM(I15:W15) -> 0
G16: в том числе: врачи | H16: 09 | X16: =SUM(I16:W16) -> 0
G17: из них: по спортивной медицине | H17: 10 | X17: =SUM(I17:W17) -> 0
G18: средний медицинский персонал | H18: 11 | X18: =SUM(I18:W18) -> 0
G19: младший медицинский персонал | H19: 12 | X19: =SUM(I19:W19) -> 0
G20: Прочий персонал | H20: 13 | X20: =SUM(I20:W20) -> 0
G21: ИТОГО | H21: 14 | I21: =SUM(I8:I10,I12,I14:I15,I20) -> 0 | J21: =SUM(J8:J10,J12,J14:J15,J20) -> 0 | K21: =SUM(K8:K10,K12,K14:K15,K20) -> 0 | L21: =SUM(L8:L10,L12,L14:L15,L20) -> 0 | M21: =SUM(M8:M10,M12,M14:M15,M20) -> 0 | N21: =SUM(N8:N10,N12,N14:N15,N20) -> 0 | O21: =SUM(O8:O10,O12,O14:O15,O20) -> 0 | P21: =SUM(P8:P10,P12,P14:P15,P20) -> 0 | ... W21: =SUM(W8:W10,W12,W14:W15,W20) -> 0 | X21: =SUM(I8:W21) -> 0

Sheet Раздел 10
G1: Раздел X. Спортивная инфраструктура, единица
G2: Наименование объектов спорта и иных спортивных сооружений | H2: № строки | I2: Находящихся в собственности и/или оперативном управлении | O2: Арендуемых | T2: Используемых на безвозмездной основе
I3: Всего | J3: в том числе по формам собственности: | N3: Включенные в лицензию на образовательную деятельность (из гр.3) | O3: Всего | P3: в том числе по формам собственности: | T3: Всего | U3: в том числе по формам собственности:
J4: федеральной | K4: субъектов Российской Федерации | L4: муниципальной | M4: другой | P4: федеральной | Q4: субъектов Российской Федерации | R4: муниципальной | S4: другой | U4: федеральной | V4: субъектов Российской Федерации | W4: муниципальной | X4: другой
A5: ='Раздел 0'!M27 -> 0 | B5: ='Раздел 1'!D15 -> 0 | C5: {=_xlfn.IFS(SUM('Раздел 1'!$D$5:$D$6)>0,"ФКиС",SUM('Раздел 1'!$D$7:$D$8)>0,"Образование",SUM('Раздел 1'!$D$9:$D$10)>0,"Другая")} -> ФКиС | D5: {=_xlfn.IFS(SUM('Раздел 1'!$E$12)>0,"СШ",SUM('Раздел 1'!$F$12)>0,"СШОР",SUM('Раздел 1'!$G$12)>0,"УОР",SUM('Раздел 1'!$H$12)>0,"ЦСП",SUM('Раздел 1'!$I$12)>0,"ДРУГИЕ",SUM('Раздел 1'!$E$13)>0,"ОСП СШ",SUM('Раздел 1'!$F$13)>0,"ОСП СШОР",SUM('Раздел 1'!$I$13)>0,"ОСП ДРУГИЕ")} -> ЦСП | E5: =IF(SUM('Раздел 1'!$D$12)>0,SUM('Раздел 1'!$D$13),"") -> 0 | F5: {=_xlfn.IFS(SUM('Раздел 1'!$D$19)>0,"РФ",SUM('Раздел 1'!$E$19)>0,"СУБЪЕКТ",SUM('Раздел 1'!$F$19:$G$19)>0,"МУНИЦИПАЛ",SUM('Раздел 1'!$H$19:$I$19)>0,"ИНЫЕ")} -> #N/A | G5: 1 | H5: 2 | I5: 3 | J5: 4 | K5: 5 | L5: 6 | M5: 7 | N5: 8 | O5: 9 | P5: 10 | Q5: 11 | R5: 12 | S5: 13 | T5: 14 | U5: 15 | V5: 16 | W5: 17 | X5: 18 | Y5: 19
G6: Стадионы с трибунами – всего | H6: 01 | I6: =SUM(J6:M6) -> 0 | O6: =SUM(P6:S6) -> 0 | T6: =SUM(U6:X6) -> 0 | Y6: =SUM(I6:X6) -> 0
G7: из них: на 1500 мест и более | H7: 02 | I7: =SUM(J7:M7) -> 0 | O7: =SUM(P7:S7) -> 0 | T7: =SUM(U7:X7) -> 0 | Y7: =SUM(I7:X7) -> 0
G8: Плоскостные спортивные сооружения – всего | H8: 03 | I8: =SUM(J8:M8) -> 0 | J8: =SUM(J9:J11) -> 0 | K8: =SUM(K9:K11) -> 0 | L8: =SUM(L9:L11) -> 0 | M8: =SUM(M9:M11) -> 0 | N8: =SUM(N9:N11) -> 0 | O8: =SUM(P8:S8) -> 0 | P8: =SUM(P9:P11) -> 0 | Q8: =SUM(Q9:Q11) -> 0 | R8: =SUM(R9:R11) -> 0 | S8: =SUM(S9:S11) -> 0 | T8: =SUM(U8:X8) -> 0 | U8: =SUM(U9:U11) -> 0 | V8: =SUM(V9:V11) -> 0 | W8: =SUM(W9:W11) -> 0 | X8: =SUM(X9:X11) -> 0 | Y8: =SUM(I8:X8) -> 0
G9: в том числе: футбольные поля | H9: 04 | I9: =SUM(J9:M9) -> 0 | O9: =SUM(P9:S9) -> 0 | T9: =SUM(U9:X9) -> 0 | Y9: =SUM(I9:X9) -> 0
G10: "умные" спортивные площадки | H10: 05 | I10: =SUM(J10:M10) -> 0 | O10: =SUM(P10:S10) -> 0 | T10: =SUM(U10:X10) -> 0 | Y10: =SUM(I10:X10) -> 0
G11: иные плоскостные спортивные сооружения | H11: 06 | I11: =SUM(J11:M11) -> 0 | O11: =SUM(P11:S11) -> 0 | T11: =SUM(U11:X11) -> 0 | Y11: =SUM(I11:X11) -> 0
G12: Спортивные залы – всего | H12: 07 | I12: =SUM(J12:M12) -> 0 | J12: =SUM(J13:J16) -> 0 | K12: =SUM(K13:K16) -> 0 | L12: =SUM(L13:L16) -> 0 | M12: =SUM(M13:M16) -> 0 | N12: =SUM(N13:N16) -> 0 | O12: =SUM(P12:S12) -> 0 | P12: =SUM(P13:P16) -> 0 | Q12: =SUM(Q13:Q16) -> 0 | R12: =SUM(R13:R16) -> 0 | S12: =SUM(S13:S16) -> 0 | T12: =SUM(U12:X12) -> 0 | U12: =SUM(U13:U16) -> 0 | V12: =SUM(V13:V16) -> 0 | W12: =SUM(W13:W16) -> 0 | X12: =SUM(X13:X16) -> 0 | Y12: =SUM(I12:X12) -> 0
G13: в том числе размером: (42 х 24 м) | H13: 08 | I13: =SUM(J13:M13) -> 0 | O13: =SUM(P13:S13) -> 0 | T13: =SUM(U13:X13) -> 0 | Y13: =SUM(I13:X13) -> 0
G14: (36 х 18 м); (30 х 18 м) и (30 х 15 м) | H14: 09 | I14: =SUM(J14:M14) -> 0 | O14: =SUM(P14:S14) -> 0 | T14: =SUM(U14:X14) -> 0 | Y14: =SUM(I14:X14) -> 0
G15: (24 х 12 м) и (18 х 9 м) | H15: 10 | I15: =SUM(J15:M15) -> 0 | O15: =SUM(P15:S15) -> 0 | T15: =SUM(U15:X15) -> 0 | Y15: =SUM(I15:X15) -> 0
G16: иных размеров | H16: 11 | I16: =SUM(J16:M16) -> 0 | O16: =SUM(P16:S16) -> 0 | T16: =SUM(U16:X16) -> 0 | Y16: =SUM(I16:X16) -> 0
G17: Манежи легкоатлетические | H17: 12 | I17: =SUM(J17:M17) -> 0 | O17: =SUM(P17:S17) -> 0 | T17: =SUM(U17:X17) -> 0 | Y17: =SUM(I17:X17) -> 0
G18: Манежи футбольные | H18: 13 | I18: =SUM(J18:M18) -> 0 | O18: =SUM(P18:S18) -> 0 | T18: =SUM(U18:X18) -> 0 | Y18: =SUM(I18:X18) -> 0
G19: Велотреки | H19: 14 | I19: =SUM(J19:M19) -> 0 | O19: =SUM(P19:S19) -> 0 | T19: =SUM(U19:X19) -> 0 | Y19: =SUM(I19:X19) -> 0
G20: Велодромы | H20: 15 | I20: =SUM(J20:M20) -> 0 | O20: =SUM(P20:S20) -> 0 | T20: =SUM(U20:X20) -> 0 | Y20: =SUM(I20:X20) -> 0
G21: Бассейны – всего | H21: 16 | I21: =SUM(J21:M21) -> 0 | J21: =SUM(J22:J25) -> 0 | K21: =SUM(K22:K25) -> 0 | L21: =SUM(L22:L25) -> 0 | M21: =SUM(M22:M25) -> 0 | N21: =SUM(N22:N25) -> 0 | O21: =SUM(P21:S21) -> 0 | P21: =SUM(P22:P25) -> 0 | Q21: =SUM(Q22:Q25) -> 0 | R21: =SUM(R22:R25) -> 0 | S21: =SUM(S22:S25) -> 0 | T21: =SUM(U21:X21) -> 0 | U21: =SUM(U22:U25) -> 0 | V21: =SUM(V22:V25) -> 0 | W21: =SUM(W22:W25) -> 0 | X21: =SUM(X22:X25) -> 0 | Y21: =SUM(I21:X21) -> 0
G22: в том числе: с длиной чаши 50 метров | H22: 17 | I22: =SUM(J22:M22) -> 0 | O22: =SUM(P22:S22) -> 0 | T22: =SUM(U22:X22) -> 0 | Y22: =SUM(I22:X22) -> 0
G23: с длиной чаши 25 метров | H23: 18 | I23: =SUM(J23:M23) -> 0 | O23: =SUM(P23:S23) -> 0 | T23: =SUM(U23:X23) -> 0 | Y23: =SUM(I23:X23) -> 0
G24: нестандартных размеров | H24: 19 | I24: =SUM(J24:M24) -> 0 | O24: =SUM(P24:S24) -> 0 | T24: =SUM(U24:X24) -> 0 | Y24: =SUM(I24:X24) -> 0
G25: для прыжков в воду | H25: 20 | I25: =SUM(J25:M25) -> 0 | O25: =SUM(P25:S25) -> 0 | T25: =SUM(U25:X25) -> 0 | Y25: =SUM(I25:X25) -> 0
G26: из строки 16 – крытые | H26: 21 | I26: =SUM(J26:M26) -> 0 | O26: =SUM(P26:S26) -> 0 | T26: =SUM(U26:X26) -> 0 | Y26: =SUM(I26:X26) -> 0
G27: Гребные базы | H27: 22 | I27: =SUM(J27:M27) -> 0 | O27: =SUM(P27:S27) -> 0 | T27: =SUM(U27:X27) -> 0 | Y27: =SUM(I27:X27) -> 0
G28: Гребные каналы | H28: 23 | I28: =SUM(J28:M28) -> 0 | O28: =SUM(P28:S28) -> 0 | T28: =SUM(U28:X28) -> 0 | Y28: =SUM(I28:X28) -> 0
G29: Спортивные объекты с искусственным льдом – всего | H29: 24 | I29: =SUM(J29:M29) -> 0 | J29: =SUM(J30:J32) -> 0 | K29: =SUM(K30:K32) -> 0 | L29: =SUM(L30:L32) -> 0 | M29: =SUM(M30:M32) -> 0 | N29: =SUM(N30:N32) -> 0 | O29: =SUM(P29:S29) -> 0 | P29: =SUM(P30:P32) -> 0 | Q29: =SUM(Q30:Q32) -> 0 | R29: =SUM(R30:R32) -> 0 | S29: =SUM(S30:S32) -> 0 | T29: =SUM(U29:X29) -> 0 | U29: =SUM(U30:U32) -> 0 | V29: =SUM(V30:V32) -> 0 | W29: =SUM(W30:W32) -> 0 | X29: =SUM(X30:X32) -> 0 | Y29: =SUM(I29:X29) -> 0
G30: в том числе: крытые спортивные объекты с искусственным льдом | H30: 25 | I30: =SUM(J30:M30) -> 0 | O30: =SUM(P30:S30) -> 0 | T30: =SUM(U30:X30) -> 0 | Y30: =SUM(I30:X30) -> 0
G31: открытые спортивные объекты с искусственным льдом | H31: 26 | I31: =SUM(J31:M31) -> 0 | O31: =SUM(P31:S31) -> 0 | T31: =SUM(U31:X31) -> 0 | Y31: =SUM(I31:X31) -> 0
G32: конькобежные | H32: 27 | I32: =SUM(J32:M32) -> 0 | O32: =SUM(P32:S32) -> 0 | T32: =SUM(U32:X32) -> 0 | Y32: =SUM(I32:X32) -> 0
G33: Лыжные базы | H33: 28 | I33: =SUM(J33:M33) -> 0 | O33: =SUM(P33:S33) -> 0 | T33: =SUM(U33:X33) -> 0 | Y33: =SUM(I33:X33) -> 0
G34: Лыжные стадионы | H34: 29 | I34: =SUM(J34:M34) -> 0 | O34: =SUM(P34:S34) -> 0 | T34: =SUM(U34:X34) -> 0 | Y34: =SUM(I34:X34) -> 0
G35: Биатлонные комплексы | H35: 30 | I35: =SUM(J35:M35) -> 0 | O35: =SUM(P35:S35) -> 0 | T35: =SUM(U35:X35) -> 0 | Y35: =SUM(I35:X35) -> 0
G36: Сооружения для стрелковых видов спорта – всего | H36: 31 | I36: =SUM(J36:M36) -> 0 | J36: =SUM(J37:J40) -> 0 | K36: =SUM(K37:K40) -> 0 | L36: =SUM(L37:L40) -> 0 | M36: =SUM(M37:M40) -> 0 | N36: =SUM(N37:N40) -> 0 | O36: =SUM(P36:S36) -> 0 | P36: =SUM(P37:P40) -> 0 | Q36: =SUM(Q37:Q40) -> 0 | R36: =SUM(R37:R40) -> 0 | S36: =SUM(S37:S40) -> 0 | T36: =SUM(U36:X36) -> 0 | U36: =SUM(U37:U40) -> 0 | V36: =SUM(V37:V40) -> 0 | W36: =SUM(W37:W40) -> 0 | X36: =SUM(X37:X40) -> 0 | Y36: =SUM(I36:X36) -> 0
G37: в том числе: тиры | H37: 32 | I37: =SUM(J37:M37) -> 0 | O37: =SUM(P37:S37) -> 0 | T37: =SUM(U37:X37) -> 0 | Y37: =SUM(I37:X37) -> 0
G38: стрельбища | H38: 33 | I38: =SUM(J38:M38) -> 0 | O38: =SUM(P38:S38) -> 0 | T38: =SUM(U38:X38) -> 0 | Y38: =SUM(I38:X38) -> 0
G39: стенды | H39: 34 | I39: =SUM(J39:M39) -> 0 | O39: =SUM(P39:S39) -> 0 | T39: =SUM(U39:X39) -> 0 | Y39: =SUM(I39:X39) -> 0
G40: лукодромы | H40: 35 | I40: =SUM(J40:M40) -> 0 | O40: =SUM(P40:S40) -> 0 | T40: =SUM(U40:X40) -> 0 | Y40: =SUM(I40:X40) -> 0
G41: Автодромы | H41: 36 | I41: =SUM(J41:M41) -> 0 | O41: =SUM(P41:S41) -> 0 | T41: =SUM(U41:X41) -> 0 | Y41: =SUM(I41:X41) -> 0
G42: из них: крытые | H42: 37 | I42: =SUM(J42:M42) -> 0 | O42: =SUM(P42:S42) -> 0 | T42: =SUM(U42:X42) -> 0 | Y42: =SUM(I42:X42) -> 0
G43: Площадка открытая универсальная с искусственным покрытием по авиационным и другим техническим видам спорта с сопутствующей инфраструктурой | H43: 38 | I43: =SUM(J43:M43) -> 0 | O43: =SUM(P43:S43) -> 0 | T43: =SUM(U43:X43) -> 0 | Y43: =SUM(I43:X43) -> 0
G44: Комплексы конноспортивные | H44: 39 | I44: =SUM(J44:M44) -> 0 | O44: =SUM(P44:S44) -> 0 | T44: =SUM(U44:X44) -> 0 | Y44: =SUM(I44:X44) -> 0
G45: из них: крытые | H45: 40 | I45: =SUM(J45:M45) -> 0 | O45: =SUM(P45:S45) -> 0 | T45: =SUM(U45:X45) -> 0 | Y45: =SUM(I45:X45) -> 0
G46: Фиджитал центры | H46: 41 | I46: =SUM(J46:M46) -> 0 | O46: =SUM(P46:S46) -> 0 | T46: =SUM(U46:X46) -> 0 | Y46: =SUM(I46:X46) -> 0
